Workbook

Sheet Identitas
B2: Nama | C2: :
B3: Nama Atasan yang menilai | C3: :
B4: Level Saat Ini | C4: : | D4: Officer
B5: Level Tujuan | C5: : | D5: Analyst
B6: Tanggal Assesment | C6: :
B7: Unit | C7: :
B8: Departemen | C8: :
B9: Divisi | C9: :
B10: Direktorat | C10: :
B12: Level Next Path | C12: : | D12: Unit Head/Specialist

Sheet mental agility
B2: =Identitas!B2 -> Nama | C2: =Identitas!D2 -> 0
B3: =Identitas!B3 -> Nama Atasan yang menilai | C3: =Identitas!D3 -> 0
B4: =Identitas!B4 -> Level Saat Ini | C4: =Identitas!D4 -> Officer
B5: =Identitas!B5 -> Level Tujuan | C5: =Identitas!D5 -> Analyst
B6: =Identitas!B6 -> Tanggal Assesment | C6: =Identitas!D6 -> 0
B7: =Identitas!B7 -> Unit | C7: =Identitas!D7 -> 0
B8: =Identitas!B8 -> Departemen | C8: =Identitas!D8 -> 0
B9: =Identitas!B9 -> Divisi | C9: =Identitas!D9 -> 0
B10: =Identitas!B10 -> Direktorat | C10: =Identitas!D10 -> 0
A12: No | B12: Indikator | C12: Pernyataan Situasi | D12: Level 1 (Rendah) | E12: Level 2 (Cukup) | F12: Level 3 (Baik) | G12: Level 4 (Sangat Baik) | H12: Level 5 (Luar Biasa) | I12: Rating (1-5) self | J12: Komentar / Contoh Perilaku | K12: Rating (1-5) superior | L12: Komentar / Contoh Perilaku | M12: Self Awareness GAP Score Self - Sup | N12: Gap | O12: Keterangan | P12: Intepretasi
A13: 1 | B13: Analytical Thinking (memahami data & fakta dasar) | C13: Ketika menghadapi data, fakta, atau informasi baru yang belum pernah saya tangani sebelumnya, perilaku yang paling sering saya tunjukkan adalah… | D13: Membutuhkan penjelasan rinci sebelum dapat memahami informasi tersebut. | E13: Memahami informasi dasarnya, namun masih memerlukan bantuan untuk menarik kesimpulan. | F13: Memahami data dan fakta utamanya serta menarik kesimpulan yang relevan secara mandiri. | G13: Memahami informasi kompleks dengan cepat dan menghubungkannya dengan konteks pekerjaan. | H13: Menangkap pola di balik informasi dan mengubahnya menjadi insight atau rekomendasi baru. | I13: 4 | K13: 4 | M13: =I13-K13 -> 0 | N13: {=_xlfn.IFS( M13>=2, "Major Positive Gap", M13>=1, "Minor Positive Gap", M13>=0, "No Gap", M13>=-1, "Minor Negative Gap", M13<=-2, "Major Negative Gap" )} -> No Gap | O13: {=_xlfn.SWITCH(N13, "No Gap","persepsi diri Selaras dengan penilaian Atasan", "Minor Positive Gap","Self-assessment sedikit lebih tinggi dari superior assessment", "Major Positive Gap","Self-assessment jauh lebih tinggi dari perilaku yang tampak menurut atasan", "Minor Negative Gap","Self-assessment sedikit lebih rendah dari superior assessment", "Major Negative Gap","Self-assessment jauh lebih rendah dari perilaku yang tampak menurut atasan", "" )} -> persepsi diri Selaras dengan penilaian Atasan | P13: {=_xlfn.SWITCH(N13, "No Gap","persepsi diri Selaras dengan perilaku yang ditunjukan", "Minor Positive Gap","Individu merasa sudah sangat baik, tetapi atasan melihat baru cukup baik", "Major Positive Gap","Ada potensi blind spot; perilaku belum terlihat sekuat persepsi diri", "Minor Negative Gap","Individu mungkin kurang percaya diri atau belum menyadari kekuatannya", "Major Negative Gap","Ada hidden strength; individu tidak menyadari bahwa perilakunya sudah terlihat kuat", "" )} -> persepsi diri Selaras dengan perilaku yang ditunjukan
A14: =A13+1 -> 2 | B14: Root Cause Analysis (mencari penyebab masalah) | C14: Ketika menghadapi masalah dalam pekerjaan, perilaku yang paling sering saya tunjukkan adalah… | D14: Berfokus pada gejala yang terlihat di permukaan. | E14: Menemukan penyebab masalah sederhana ketika mendapat arahan. | F14: Menganalisis informasi yang ada dan menemukan akar masalah utamanya secara mandiri. | G14: Mengurai masalah kompleks dengan membedakan gejala, penyebab, dan dampaknya. | H14: Menemukan akar masalah secara cepat dan akurat pada situasi kompleks, ambigu, atau lintas fungsi. | I14: 3 | K14: 3 | M14: =I14-K14 -> 0 | N14: {=_xlfn.IFS( M14>=2, "Major Positive Gap", M14>=1, "Minor Positive Gap", M14>=0, "No Gap", M14>=-1, "Minor Negative Gap", M14<=-2, "Major Negative Gap" )} -> No Gap | O14: {=_xlfn.SWITCH(N14, "No Gap","persepsi diri Selaras dengan penilaian Atasan", "Minor Positive Gap","Self-assessment sedikit lebih tinggi dari superior assessment", "Major Positive Gap","Self-assessment jauh lebih tinggi dari perilaku yang tampak menurut atasan", "Minor Negative Gap","Self-assessment sedikit lebih rendah dari superior assessment", "Major Negative Gap","Self-assessment jauh lebih rendah dari perilaku yang tampak menurut atasan", "" )} -> persepsi diri Selaras dengan penilaian Atasan | P14: {=_xlfn.SWITCH(N14, "No Gap","persepsi diri Selaras dengan perilaku yang ditunjukan", "Minor Positive Gap","Individu merasa sudah sangat baik, tetapi atasan melihat baru cukup baik", "Major Positive Gap","Ada potensi blind spot; perilaku belum terlihat sekuat persepsi diri", "Minor Negative Gap","Individu mungkin kurang percaya diri atau belum menyadari kekuatannya", "Major Negative Gap","Ada hidden strength; individu tidak menyadari bahwa perilakunya sudah terlihat kuat", "" )} -> persepsi diri Selaras dengan perilaku yang ditunjukan
A15: =A14+1 -> 3 | B15: Critical Thinking & Inquisitiveness (mempertanyakan & mengevaluasi) | C15: Ketika menerima informasi, arahan, data, atau usulan, perilaku yang paling sering saya tunjukkan adalah… | D15: Menerima informasi tersebut apa adanya. | E15: Mengajukan pertanyaan dasar untuk memastikan pemahaman atas faktanya. | F15: Menanyakan "mengapa" dan "bagaimana" untuk memahami alasan di baliknya. | G15: Menguji asumsi yang mendasarinya serta mencari data atau perspektif pembanding. | H15: Menyusun kerangka berpikir yang menghubungkan informasi kompleks, kontradiktif, atau belum lengkap. | I15: 3 | K15: 2 | M15: =I15-K15 -> 1 | N15: {=_xlfn.IFS( M15>=2, "Major Positive Gap", M15>=1, "Minor Positive Gap", M15>=0, "No Gap", M15>=-1, "Minor Negative Gap", M15<=-2, "Major Negative Gap" )} -> Minor Positive Gap | O15: {=_xlfn.SWITCH(N15, "No Gap","persepsi diri Selaras dengan penilaian Atasan", "Minor Positive Gap","Self-assessment sedikit lebih tinggi dari superior assessment", "Major Positive Gap","Self-assessment jauh lebih tinggi dari perilaku yang tampak menurut atasan", "Minor Negative Gap","Self-assessment sedikit lebih rendah dari superior assessment", "Major Negative Gap","Self-assessment jauh lebih rendah dari perilaku yang tampak menurut atasan", "" )} -> Self-assessment sedikit lebih tinggi dari superior assessment | P15: {=_xlfn.SWITCH(N15, "No Gap","persepsi diri Selaras dengan perilaku yang ditunjukan", "Minor Positive Gap","Individu merasa sudah sangat baik, tetapi atasan melihat baru cukup baik", "Major Positive Gap","Ada potensi blind spot; perilaku belum terlihat sekuat persepsi diri", "Minor Negative Gap","Individu mungkin kurang percaya diri atau belum menyadari kekuatannya", "Major Negative Gap","Ada hidden strength; individu tidak menyadari bahwa perilakunya sudah terlihat kuat", "" )} -> Individu merasa sudah sangat baik, tetapi atasan melihat baru cukup baik
A16: =A15+1 -> 4 | B16: Explaining Complexity (menjelaskan hal kompleks secara sederhana) | C16: Ketika menjelaskan ide, data, atau masalah kompleks kepada orang lain, perilaku yang paling sering saya tunjukkan adalah… | D16: Menyampaikan sesuai urutan yang saya pahami, sehingga inti pesan belum selalu tertangkap. | E16: Menjelaskan dengan bantuan contoh, meski penjelasannya masih panjang dan kurang fokus. | F16: Menjelaskan isu kompleks secara runtut dan mudah diikuti. | G16: Menyederhanakan konsep kompleks sesuai kebutuhan audiens yang berbeda-beda. | H16: Mengemas kompleksitas menjadi narasi yang sederhana, meyakinkan, dan mendorong tindakan. | I16: 3 | K16: 1 | M16: =I16-K16 -> 2 | N16: {=_xlfn.IFS( M16>=2, "Major Positive Gap", M16>=1, "Minor Positive Gap", M16>=0, "No Gap", M16>=-1, "Minor Negative Gap", M16<=-2, "Major Negative Gap" )} -> Major Positive Gap | O16: {=_xlfn.SWITCH(N16, "No Gap","persepsi diri Selaras dengan penilaian Atasan", "Minor Positive Gap","Self-assessment sedikit lebih tinggi dari superior assessment", "Major Positive Gap","Self-assessment jauh lebih tinggi dari perilaku yang tampak menurut atasan", "Minor Negative Gap","Self-assessment sedikit lebih rendah dari superior assessment", "Major Negative Gap","Self-assessment jauh lebih rendah dari perilaku yang tampak menurut atasan", "" )} -> Self-assessment jauh lebih tinggi dari perilaku yang tampak menurut atasan | P16: {=_xlfn.SWITCH(N16, "No Gap","persepsi diri Selaras dengan perilaku yang ditunjukan", "Minor Positive Gap","Individu merasa sudah sangat baik, tetapi atasan melihat baru cukup baik", "Major Positive Gap","Ada potensi blind spot; perilaku belum terlihat sekuat persepsi diri", "Minor Negative Gap","Individu mungkin kurang percaya diri atau belum menyadari kekuatannya", "Major Negative Gap","Ada hidden strength; individu tidak menyadari bahwa perilakunya sudah terlihat kuat", "" )} -> Ada potensi blind spot; perilaku belum terlihat sekuat persepsi diri
A17: =A16+1 -> 5 | B17: Intellectual Synthesis (menghubungkan berbagai informasi) | C17: Ketika menghadapi beragam data, konsep, atau temuan dari sumber berbeda yang tampak terpisah-pisah, perilaku yang paling sering saya tunjukkan adalah… (Fokus indikator: data, konsep, dan informasi (bukan pendapat orang)) | D17: Menggunakan pengetahuan yang sudah di kenal dan memilih pendekatan konvensional. | E17: Melihat kemiripan antar informasi, namun belum menghubungkannya menjadi satu kesimpulan. | F17: Menemukan keterkaitan antar informasi, data, atau konsep dari sumber yang berbeda. | G17: Menyintesis berbagai informasi menjadi satu pendekatan, rekomendasi, atau solusi baru. | H17: Membangun kerangka kerja baru dari informasi kompleks yang sebelumnya tampak tidak berkaitan. | I17: 2 | K17: 4 | M17: =I17-K17 -> -2 | N17: {=_xlfn.IFS( M17>=2, "Major Positive Gap", M17>=1, "Minor Positive Gap", M17>=0, "No Gap", M17>=-1, "Minor Negative Gap", M17<=-2, "Major Negative Gap" )} -> Major Negative Gap | O17: {=_xlfn.SWITCH(N17, "No Gap","persepsi diri Selaras dengan penilaian Atasan", "Minor Positive Gap","Self-assessment sedikit lebih tinggi dari superior assessment", "Major Positive Gap","Self-assessment jauh lebih tinggi dari perilaku yang tampak menurut atasan", "Minor Negative Gap","Self-assessment sedikit lebih rendah dari superior assessment", "Major Negative Gap","Self-assessment jauh lebih rendah dari perilaku yang tampak menurut atasan", "" )} -> Self-assessment jauh lebih rendah dari perilaku yang tampak menurut atasan | P17: {=_xlfn.SWITCH(N17, "No Gap","persepsi diri Selaras dengan perilaku yang ditunjukan", "Minor Positive Gap","Individu merasa sudah sangat baik, tetapi atasan melihat baru cukup baik", "Major Positive Gap","Ada potensi blind spot; perilaku belum terlihat sekuat persepsi diri", "Minor Negative Gap","Individu mungkin kurang percaya diri atau belum menyadari kekuatannya", "Major Negative Gap","Ada hidden strength; individu tidak menyadari bahwa perilakunya sudah terlihat kuat", "" )} -> Ada hidden strength; individu tidak menyadari bahwa perilakunya sudah terlihat kuat
A18: =A17+1 -> 6 | B18: Integrating Diverse Perspective (keputusan dari berbagai sudut pandang) | C18: Ketika mengambil keputusan yang melibatkan beragam perspektif dari para pemangku kepentingan, perilaku yang paling sering saya tunjukkan adalah… (Fokus indikator: sudut pandang, kepentingan, dan opini orang (bukan data)) | D18: Mencari informasi yang mendukung pendapat awal saya. | E18: Mempertimbangkan perspektif lain, meski sudut pandang saya sendiri masih dominan. | F18: Mempertimbangkan berbagai faktor dan sudut pandang sebelum memutuskan. | G18: Memadukan masukan berbagai pihak untuk memperkaya analisis dan menurunkan risiko keputusan. | H18: Menghubungkan perspektif yang berbeda atau bertentangan menjadi solusi inovatif yang dapat diterima. | I18: 3 | K18: 2 | M18: =I18-K18 -> 1 | N18: {=_xlfn.IFS( M18>=2, "Major Positive Gap", M18>=1, "Minor Positive Gap", M18>=0, "No Gap", M18>=-1, "Minor Negative Gap", M18<=-2, "Major Negative Gap" )} -> Minor Positive Gap | O18: {=_xlfn.SWITCH(N18, "No Gap","persepsi diri Selaras dengan penilaian Atasan", "Minor Positive Gap","Self-assessment sedikit lebih tinggi dari superior assessment", "Major Positive Gap","Self-assessment jauh lebih tinggi dari perilaku yang tampak menurut atasan", "Minor Negative Gap","Self-assessment sedikit lebih rendah dari superior assessment", "Major Negative Gap","Self-assessment jauh lebih rendah dari perilaku yang tampak menurut atasan", "" )} -> Self-assessment sedikit lebih tinggi dari superior assessment | P18: {=_xlfn.SWITCH(N18, "No Gap","persepsi diri Selaras dengan perilaku yang ditunjukan", "Minor Positive Gap","Individu merasa sudah sangat baik, tetapi atasan melihat baru cukup baik", "Major Positive Gap","Ada potensi blind spot; perilaku belum terlihat sekuat persepsi diri", "Minor Negative Gap","Individu mungkin kurang percaya diri atau belum menyadari kekuatannya", "Major Negative Gap","Ada hidden strength; individu tidak menyadari bahwa perilakunya sudah terlihat kuat", "" )} -> Individu merasa sudah sangat baik, tetapi atasan melihat baru cukup baik
A19: =A18+1 -> 7 | B19: Creative Exploration (mencari pendekatan baru) | C19: Ketika menghadapi ide baru atau pendekatan yang belum terbukti, perilaku yang paling sering saya tunjukkan adalah… | D19: Menggunakan metode yang sudah familiar bagi saya. | E19: Mendengarkan ide baru, namun tetap memilih cara yang sudah terbukti. | F19: Mencoba ide baru ketika situasi, waktu, dan sumber daya memungkinkan. | G19: Mencari ide baru secara aktif sebagai peluang perbaikan atau inovasi. | H19: Mengeksplorasi dan menguji pendekatan baru secara terencana serta menarik pembelajaran dari hasil ujinya. | I19: 3 | K19: 2 | M19: =I19-K19 -> 1 | N19: {=_xlfn.IFS( M19>=2, "Major Positive Gap", M19>=1, "Minor Positive Gap", M19>=0, "No Gap", M19>=-1, "Minor Negative Gap", M19<=-2, "Major Negative Gap" )} -> Minor Positive Gap | O19: {=_xlfn.SWITCH(N19, "No Gap","persepsi diri Selaras dengan penilaian Atasan", "Minor Positive Gap","Self-assessment sedikit lebih tinggi dari superior assessment", "Major Positive Gap","Self-assessment jauh lebih tinggi dari perilaku yang tampak menurut atasan", "Minor Negative Gap","Self-assessment sedikit lebih rendah dari superior assessment", "Major Negative Gap","Self-assessment jauh lebih rendah dari perilaku yang tampak menurut atasan", "" )} -> Self-assessment sedikit lebih tinggi dari superior assessment | P19: {=_xlfn.SWITCH(N19, "No Gap","persepsi diri Selaras dengan perilaku yang ditunjukan", "Minor Positive Gap","Individu merasa sudah sangat baik, tetapi atasan melihat baru cukup baik", "Major Positive Gap","Ada potensi blind spot; perilaku belum terlihat sekuat persepsi diri", "Minor Negative Gap","Individu mungkin kurang percaya diri atau belum menyadari kekuatannya", "Major Negative Gap","Ada hidden strength; individu tidak menyadari bahwa perilakunya sudah terlihat kuat", "" )} -> Individu merasa sudah sangat baik, tetapi atasan melihat baru cukup baik
A20: =A19+1 -> 8 | B20: Breaking Patterned thinking (menciptakan solusi baru) | C20: Ketika menghadapi masalah lama yang membutuhkan cara baru, perilaku yang paling sering saya tunjukkan adalah… | D20: Menerapkan kembali solusi yang biasa digunakan sebelumnya. | E20: Menyesuaikan solusi lama dengan kerangka berpikir yang sama. | F20: Mengevaluasi efektivitas solusi lama dan mulai mencari alternatif pendekatan. | G20: Membandingkan beberapa alternatif solusi dan memilih pendekatan yang paling relevan. | H20: Menciptakan solusi baru untuk masalah berulang yang tidak terselesaikan dengan cara lama. | I20: 3 | K20: 4 | M20: =I20-K20 -> -1 | N20: {=_xlfn.IFS( M20>=2, "Major Positive Gap", M20>=1, "Minor Positive Gap", M20>=0, "No Gap", M20>=-1, "Minor Negative Gap", M20<=-2, "Major Negative Gap" )} -> Minor Negative Gap | O20: {=_xlfn.SWITCH(N20, "No Gap","persepsi diri Selaras dengan penilaian Atasan", "Minor Positive Gap","Self-assessment sedikit lebih tinggi dari superior assessment", "Major Positive Gap","Self-assessment jauh lebih tinggi dari perilaku yang tampak menurut atasan", "Minor Negative Gap","Self-assessment sedikit lebih rendah dari superior assessment", "Major Negative Gap","Self-assessment jauh lebih rendah dari perilaku yang tampak menurut atasan", "" )} -> Self-assessment sedikit lebih rendah dari superior assessment | P20: {=_xlfn.SWITCH(N20, "No Gap","persepsi diri Selaras dengan perilaku yang ditunjukan", "Minor Positive Gap","Individu merasa sudah sangat baik, tetapi atasan melihat baru cukup baik", "Major Positive Gap","Ada potensi blind spot; perilaku belum terlihat sekuat persepsi diri", "Minor Negative Gap","Individu mungkin kurang percaya diri atau belum menyadari kekuatannya", "Major Negative Gap","Ada hidden strength; individu tidak menyadari bahwa perilakunya sudah terlihat kuat", "" )} -> Individu mungkin kurang percaya diri atau belum menyadari kekuatannya
A21: =A20+1 -> 9 | B21: Comfort with Ambiguity (tetap efektif di situasi tidak jelas) | C21: Ketika menghadapi situasi kerja yang belum jelas arah, data, prioritas, atau keputusannya, perilaku yang paling sering saya tunjukkan adalah… | D21: Menunggu arahan yang jelas sebelum menentukan langkah. | E21: Mulai bekerja dalam ketidakjelasan, namun sering memerlukan arahan tambahan. | F21: Tetap menjalankan pekerjaan dalam situasi ambigu dengan beberapa panduan. | G21: Tetap produktif dan mampu mengambil keputusan meski informasinya terbatas. | H21: Memanfaatkan situasi yang belum jelas untuk menemukan peluang, pola baru, atau alternatif strategi. | I21: 2 | K21: 1 | M21: =I21-K21 -> 1 | N21: {=_xlfn.IFS( M21>=2, "Major Positive Gap", M21>=1, "Minor Positive Gap", M21>=0, "No Gap", M21>=-1, "Minor Negative Gap", M21<=-2, "Major Negative Gap" )} -> Minor Positive Gap | O21: {=_xlfn.SWITCH(N21, "No Gap","persepsi diri Selaras dengan penilaian Atasan", "Minor Positive Gap","Self-assessment sedikit lebih tinggi dari superior assessment", "Major Positive Gap","Self-assessment jauh lebih tinggi dari perilaku yang tampak menurut atasan", "Minor Negative Gap","Self-assessment sedikit lebih rendah dari superior assessment", "Major Negative Gap","Self-assessment jauh lebih rendah dari perilaku yang tampak menurut atasan", "" )} -> Self-assessment sedikit lebih tinggi dari superior assessment | P21: {=_xlfn.SWITCH(N21, "No Gap","persepsi diri Selaras dengan perilaku yang ditunjukan", "Minor Positive Gap","Individu merasa sudah sangat baik, tetapi atasan melihat baru cukup baik", "Major Positive Gap","Ada potensi blind spot; perilaku belum terlihat sekuat persepsi diri", "Minor Negative Gap","Individu mungkin kurang percaya diri atau belum menyadari kekuatannya", "Major Negative Gap","Ada hidden strength; individu tidak menyadari bahwa perilakunya sudah terlihat kuat", "" )} -> Individu merasa sudah sangat baik, tetapi atasan melihat baru cukup baik
A22: =A21+1 -> 10 | B22: Tolerance for Ambiguity (memimpin dalam uncertainty tinggi) | C22: Ketika menghadapi atau memimpin situasi dengan ketidakpastian tinggi dan berdampak luas, perilaku yang paling sering saya tunjukkan adalah… | D22: Menunda keputusan sampai arahnya menjadi lebih jelas. | E22: Menyesuaikan langkah setelah memperoleh arahan atau keputusan dari pihak lain. | F22: Menjaga produktivitas diri dan tim dalam ketidakpastian dengan dukungan tertentu. | G22: Memberi arah, menjaga ketenangan, dan mengambil keputusan di tengah ketidakpastian tinggi. | H22: Menetapkan arah strategis dan menciptakan peluang baru bagi pihak yang menjadi tanggung jawab saya/bawahan saya. | I22: 2 | K22: 2 | M22: =I22-K22 -> 0 | N22: {=_xlfn.IFS( M22>=2, "Major Positive Gap", M22>=1, "Minor Positive Gap", M22>=0, "No Gap", M22>=-1, "Minor Negative Gap", M22<=-2, "Major Negative Gap" )} -> No Gap | O22: {=_xlfn.SWITCH(N22, "No Gap","persepsi diri Selaras dengan penilaian Atasan", "Minor Positive Gap","Self-assessment sedikit lebih tinggi dari superior assessment", "Major Positive Gap","Self-assessment jauh lebih tinggi dari perilaku yang tampak menurut atasan", "Minor Negative Gap","Self-assessment sedikit lebih rendah dari superior assessment", "Major Negative Gap","Self-assessment jauh lebih rendah dari perilaku yang tampak menurut atasan", "" )} -> persepsi diri Selaras dengan penilaian Atasan | P22: {=_xlfn.SWITCH(N22, "No Gap","persepsi diri Selaras dengan perilaku yang ditunjukan", "Minor Positive Gap","Individu merasa sudah sangat baik, tetapi atasan melihat baru cukup baik", "Major Positive Gap","Ada potensi blind spot; perilaku belum terlihat sekuat persepsi diri", "Minor Negative Gap","Individu mungkin kurang percaya diri atau belum menyadari kekuatannya", "Major Negative Gap","Ada hidden strength; individu tidak menyadari bahwa perilakunya sudah terlihat kuat", "" )} -> persepsi diri Selaras dengan perilaku yang ditunjukan
A23: AVERAGE SCORE | I23: =AVERAGE(I13:J22) -> 2.8 | J23: =AVERAGE(J13:K22) -> 2.5 | K23: =AVERAGE(K13:L22) -> 2.5 | M23: =I23-K23 -> 0.3 | N23: {=_xlfn.IFS( VALUE(M23) >= 1, "Major Positive Gap", VALUE(M23) >= 0.5, "Minor Positive Gap", VALUE(M23) >= -0.49, "Aligned", VALUE(M23) >= -0.99, "Minor Negative Gap", VALUE(M23) <= -1, "Major Negative Gap" )} -> Aligned | O23: {=_xlfn.SWITCH(N23, "Aligned","Aligned Perception", "Minor Positive Gap","Slight Overestimation", "Major Positive Gap","Significant Overestimation / Potential Blind Spot", "Minor Negative Gap","Slight Underestimation", "Major Negative Gap","Significant Underestimation / Hidden Strength", "" )} -> Aligned Perception

Sheet people agility
B2: =Identitas!B2 -> Nama | C2: =Identitas!D2 -> 0
B3: =Identitas!B3 -> Nama Atasan yang menilai | C3: =Identitas!D3 -> 0
B4: =Identitas!B4 -> Level Saat Ini | C4: =Identitas!D4 -> Officer
B5: =Identitas!B5 -> Level Tujuan | C5: =Identitas!D5 -> Analyst
B6: =Identitas!B6 -> Tanggal Assesment | C6: =Identitas!D6 -> 0
B7: =Identitas!B7 -> Unit | C7: =Identitas!D7 -> 0
B8: =Identitas!B8 -> Departemen | C8: =Identitas!D8 -> 0
B9: =Identitas!B9 -> Divisi | C9: =Identitas!D9 -> 0
B10: =Identitas!B10 -> Direktorat | C10: =Identitas!D10 -> 0
A12: No | B12: Indikator | C12: Pernyataan Situasi | D12: Level 1 (Rendah) | E12: Level 2 (Cukup) | F12: Level 3 (Baik) | G12: Level 4 (Sangat Baik) | H12: Level 5 (Luar Biasa) | I12: Rating (1-5) self | J12: Komentar / Contoh Perilaku | K12: Rating (1-5) superior | L12: Komentar / Contoh Perilaku | M12: Self Awareness GAP Score Self - Sup | N12: Gap | O12: Keterangan | P12: Intepretasi
A13: 1 | B13: Listening for understanding (mendengarkan & memahami) | C13: Ketika mendengarkan penjelasan, keluhan, masukan, atau ide dari orang lain, perilaku yang paling sering saya tunjukkan adalah… | D13: Fokus saya mudah teralihkan saat orang lain berbicara. | E13: Menyimak bagian yang saya anggap relevan dengan tugas saya. | F13: Memberi perhatian penuh, mengajukan klarifikasi, dan merangkum poin utamanya. | G13: Menangkap makna, emosi, dan nada di balik apa yang disampaikan. | H13: Menghubungkan isu, kebutuhan, dan emosi pihak lain untuk mendorong kesepakatan atau tindak lanjut. | I13: 2 | J13: 4 | K13: 3 | M13: =I13-K13 -> -1 | N13: {=_xlfn.IFS( M13>=2, "Major Positive Gap", M13>=1, "Minor Positive Gap", M13>=0, "No Gap", M13>=-1, "Minor Negative Gap", M13<=-2, "Major Negative Gap" )} -> Minor Negative Gap | O13: {=_xlfn.SWITCH(N13, "No Gap","persepsi diri Selaras dengan penilaian Atasan", "Minor Positive Gap","Self-assessment sedikit lebih tinggi dari superior assessment", "Major Positive Gap","Self-assessment jauh lebih tinggi dari perilaku yang tampak menurut atasan", "Minor Negative Gap","Self-assessment sedikit lebih rendah dari superior assessment", "Major Negative Gap","Self-assessment jauh lebih rendah dari perilaku yang tampak menurut atasan", "" )} -> Self-assessment sedikit lebih rendah dari superior assessment | P13: {=_xlfn.SWITCH(N13, "No Gap","persepsi diri Selaras dengan perilaku yang ditunjukan", "Minor Positive Gap","Individu merasa sudah sangat baik, tetapi atasan melihat baru cukup baik", "Major Positive Gap","Ada potensi blind spot; perilaku belum terlihat sekuat persepsi diri", "Minor Negative Gap","Individu mungkin kurang percaya diri atau belum menyadari kekuatannya", "Major Negative Gap","Ada hidden strength; individu tidak menyadari bahwa perilakunya sudah terlihat kuat", "" )} -> Individu mungkin kurang percaya diri atau belum menyadari kekuatannya
A14: =A13+1 -> 2 | B14: Openness to Feedback (menerima & menindaklajuti masukan) | C14: Ketika menerima masukan atau umpan balik dari orang lain, perilaku yang paling sering saya tunjukkan adalah… | D14: Menjelaskan alasan atau pembenaran atas apa yang telah saya lakukan. | E14: Menerima masukan yang bersifat ringan atau positif | F14: Meminta klarifikasi atau contoh agar dapat memahami masukan dengan tepat. | G14: Menindaklanjuti masukan melalui perubahan perilaku atau peningkatan keterampilan. | H14: Meminta masukan yang spesifik dan menantang dari berbagai pihak secara rutin. | I14: 3 | J14: 3 | K14: 2 | M14: =I14-K14 -> 1 | N14: {=_xlfn.IFS( M14>=2, "Major Positive Gap", M14>=1, "Minor Positive Gap", M14>=0, "No Gap", M14>=-1, "Minor Negative Gap", M14<=-2, "Major Negative Gap" )} -> Minor Positive Gap | O14: {=_xlfn.SWITCH(N14, "No Gap","persepsi diri Selaras dengan penilaian Atasan", "Minor Positive Gap","Self-assessment sedikit lebih tinggi dari superior assessment", "Major Positive Gap","Self-assessment jauh lebih tinggi dari perilaku yang tampak menurut atasan", "Minor Negative Gap","Self-assessment sedikit lebih rendah dari superior assessment", "Major Negative Gap","Self-assessment jauh lebih rendah dari perilaku yang tampak menurut atasan", "" )} -> Self-assessment sedikit lebih tinggi dari superior assessment | P14: {=_xlfn.SWITCH(N14, "No Gap","persepsi diri Selaras dengan perilaku yang ditunjukan", "Minor Positive Gap","Individu merasa sudah sangat baik, tetapi atasan melihat baru cukup baik", "Major Positive Gap","Ada potensi blind spot; perilaku belum terlihat sekuat persepsi diri", "Minor Negative Gap","Individu mungkin kurang percaya diri atau belum menyadari kekuatannya", "Major Negative Gap","Ada hidden strength; individu tidak menyadari bahwa perilakunya sudah terlihat kuat", "" )} -> Individu merasa sudah sangat baik, tetapi atasan melihat baru cukup baik
A15: =A14+1 -> 3 | B15: Genuine Curiosity about Others (rasa ingin tahu tulus pada orang lain) | C15: Ketika berinteraksi dengan rekan kerja, anggota tim, atau stakeholder, perilaku yang paling sering saya tunjukkan adalah… | D15: Menyimpulkan orang lain berdasarkan kesan awal. | E15: Bertanya seperlunya untuk memenuhi kebutuhan tugas. | F15: Menunjukkan ketertarikan pada kebutuhan, alasan, dan konteks orang lain. | G15: Menggali motivasi, kekhawatiran, dan harapan orang lain secara aktif. | H15: Membangun pemahaman mendalam sehingga tercipta kepercayaan dan kolaborasi yang lebih kuat. | I15: 4 | J15: 1 | K15: 2 | M15: =I15-K15 -> 2 | N15: {=_xlfn.IFS( M15>=2, "Major Positive Gap", M15>=1, "Minor Positive Gap", M15>=0, "No Gap", M15>=-1, "Minor Negative Gap", M15<=-2, "Major Negative Gap" )} -> Major Positive Gap | O15: {=_xlfn.SWITCH(N15, "No Gap","persepsi diri Selaras dengan penilaian Atasan", "Minor Positive Gap","Self-assessment sedikit lebih tinggi dari superior assessment", "Major Positive Gap","Self-assessment jauh lebih tinggi dari perilaku yang tampak menurut atasan", "Minor Negative Gap","Self-assessment sedikit lebih rendah dari superior assessment", "Major Negative Gap","Self-assessment jauh lebih rendah dari perilaku yang tampak menurut atasan", "" )} -> Self-assessment jauh lebih tinggi dari perilaku yang tampak menurut atasan | P15: {=_xlfn.SWITCH(N15, "No Gap","persepsi diri Selaras dengan perilaku yang ditunjukan", "Minor Positive Gap","Individu merasa sudah sangat baik, tetapi atasan melihat baru cukup baik", "Major Positive Gap","Ada potensi blind spot; perilaku belum terlihat sekuat persepsi diri", "Minor Negative Gap","Individu mungkin kurang percaya diri atau belum menyadari kekuatannya", "Major Negative Gap","Ada hidden strength; individu tidak menyadari bahwa perilakunya sudah terlihat kuat", "" )} -> Ada potensi blind spot; perilaku belum terlihat sekuat persepsi diri
A16: =A15+1 -> 4 | B16: Collaboration with Diversity (Bekerja efektif dalam keberagaman) | C16: Dalam kolaborasi dengan pihak yang memiliki latar belakang, fungsi, gaya kerja, atau pandangan berbeda, perilaku yang paling sering saya tunjukkan adalah… | D16: Bekerja dengan pihak yang memiliki gaya dan latar belakang serupa dengan saya. | E16: Bekerja dalam tim yang beragam ketika diarahkan. | F16: Menyesuaikan gaya komunikasi agar dapat bekerja efektif dengan pihak yang berbeda. | G16: Memanfaatkan keberagaman perspektif untuk menghasilkan ide atau solusi yang lebih baik. | H16: Membangun kolaborasi lintas perbedaan yang menghasilkan output unggul dan suasana kerja inklusif. | I16: 1 | J16: 3 | K16: 5 | M16: =I16-K16 -> -4 | N16: {=_xlfn.IFS( M16>=2, "Major Positive Gap", M16>=1, "Minor Positive Gap", M16>=0, "No Gap", M16>=-1, "Minor Negative Gap", M16<=-2, "Major Negative Gap" )} -> Major Negative Gap | O16: {=_xlfn.SWITCH(N16, "No Gap","persepsi diri Selaras dengan penilaian Atasan", "Minor Positive Gap","Self-assessment sedikit lebih tinggi dari superior assessment", "Major Positive Gap","Self-assessment jauh lebih tinggi dari perilaku yang tampak menurut atasan", "Minor Negative Gap","Self-assessment sedikit lebih rendah dari superior assessment", "Major Negative Gap","Self-assessment jauh lebih rendah dari perilaku yang tampak menurut atasan", "" )} -> Self-assessment jauh lebih rendah dari perilaku yang tampak menurut atasan | P16: {=_xlfn.SWITCH(N16, "No Gap","persepsi diri Selaras dengan perilaku yang ditunjukan", "Minor Positive Gap","Individu merasa sudah sangat baik, tetapi atasan melihat baru cukup baik", "Major Positive Gap","Ada potensi blind spot; perilaku belum terlihat sekuat persepsi diri", "Minor Negative Gap","Individu mungkin kurang percaya diri atau belum menyadari kekuatannya", "Major Negative Gap","Ada hidden strength; individu tidak menyadari bahwa perilakunya sudah terlihat kuat", "" )} -> Ada hidden strength; individu tidak menyadari bahwa perilakunya sudah terlihat kuat
A17: =A16+1 -> 5 | B17: Valuing Diverse Opinions (Menghargai opini berbeda) | C17: Ketika dihadapkan pada beragam pendapat dalam diskusi atau pengambilan keputusan, perilaku yang paling sering saya tunjukkan adalah… (Fokus indikator: respek dan ruang yang diberikan kepada pemilik pendapat) | D17: Berfokus pada pendapat yang sejalan dengan pandangan saya. | E17: Mendengarkan pendapat berbeda, meski belum memandangnya sebagai masukan bernilai. | F17: Menghargai perbedaan pendapat dan memberi ruang bagi orang lain untuk menyampaikannya. | G17: Mempertimbangkan pendapat yang berbeda secara serius sebelum keputusan ditetapkan. | H17: Mengintegrasikan berbagai pendapat menjadi solusi yang seimbang dan dapat diterima bersama. | I17: 5 | J17: 2 | K17: 4 | M17: =I17-K17 -> 1 | N17: {=_xlfn.IFS( M17>=2, "Major Positive Gap", M17>=1, "Minor Positive Gap", M17>=0, "No Gap", M17>=-1, "Minor Negative Gap", M17<=-2, "Major Negative Gap" )} -> Minor Positive Gap | O17: {=_xlfn.SWITCH(N17, "No Gap","persepsi diri Selaras dengan penilaian Atasan", "Minor Positive Gap","Self-assessment sedikit lebih tinggi dari superior assessment", "Major Positive Gap","Self-assessment jauh lebih tinggi dari perilaku yang tampak menurut atasan", "Minor Negative Gap","Self-assessment sedikit lebih rendah dari superior assessment", "Major Negative Gap","Self-assessment jauh lebih rendah dari perilaku yang tampak menurut atasan", "" )} -> Self-assessment sedikit lebih tinggi dari superior assessment | P17: {=_xlfn.SWITCH(N17, "No Gap","persepsi diri Selaras dengan perilaku yang ditunjukan", "Minor Positive Gap","Individu merasa sudah sangat baik, tetapi atasan melihat baru cukup baik", "Major Positive Gap","Ada potensi blind spot; perilaku belum terlihat sekuat persepsi diri", "Minor Negative Gap","Individu mungkin kurang percaya diri atau belum menyadari kekuatannya", "Major Negative Gap","Ada hidden strength; individu tidak menyadari bahwa perilakunya sudah terlihat kuat", "" )} -> Individu merasa sudah sangat baik, tetapi atasan melihat baru cukup baik
A18: =A17+1 -> 6 | B18: Understanding Different Perspectives (Analisis multi-sudut pandang) | C18: Ketika muncul perbedaan sudut pandang atau kepentingan dalam melihat suatu masalah, perilaku yang paling sering saya tunjukkan adalah… (Fokus indikator: kedalaman pemetaan kepentingan dan batasan pihak lain, terlepas dari keputusan akhir) | D18: Bertahan pada sudut pandang saya sendiri. | E18: Mencoba memahami sudut pandang lain, namun kembali pada perspektif awal. | F18: Menerima perspektif berbeda ketika dijelaskan secara logis dan relevan. | G18: Menganalisis kebutuhan, kepentingan, dan batasan yang mendasari sudut pandang berbagai pihak. | H18: Memetakan perspektif yang berbeda atau bertentangan untuk membangun pemahaman yang lebih utuh. | I18: 4 | J18: 2 | K18: 5 | M18: =I18-K18 -> -1 | N18: {=_xlfn.IFS( M18>=2, "Major Positive Gap", M18>=1, "Minor Positive Gap", M18>=0, "No Gap", M18>=-1, "Minor Negative Gap", M18<=-2, "Major Negative Gap" )} -> Minor Negative Gap | O18: {=_xlfn.SWITCH(N18, "No Gap","persepsi diri Selaras dengan penilaian Atasan", "Minor Positive Gap","Self-assessment sedikit lebih tinggi dari superior assessment", "Major Positive Gap","Self-assessment jauh lebih tinggi dari perilaku yang tampak menurut atasan", "Minor Negative Gap","Self-assessment sedikit lebih rendah dari superior assessment", "Major Negative Gap","Self-assessment jauh lebih rendah dari perilaku yang tampak menurut atasan", "" )} -> Self-assessment sedikit lebih rendah dari superior assessment | P18: {=_xlfn.SWITCH(N18, "No Gap","persepsi diri Selaras dengan perilaku yang ditunjukan", "Minor Positive Gap","Individu merasa sudah sangat baik, tetapi atasan melihat baru cukup baik", "Major Positive Gap","Ada potensi blind spot; perilaku belum terlihat sekuat persepsi diri", "Minor Negative Gap","Individu mungkin kurang percaya diri atau belum menyadari kekuatannya", "Major Negative Gap","Ada hidden strength; individu tidak menyadari bahwa perilakunya sudah terlihat kuat", "" )} -> Individu mungkin kurang percaya diri atau belum menyadari kekuatannya
A19: =A18+1 -> 7 | B19: Recognizing Others' Potential (mengenali potensi orang lain) | C19: Ketika bekerja bersama rekan atau anggota tim yang memiliki tingkat kemampuan berbeda-beda, perilaku yang paling sering saya tunjukkan adalah… | D19: Berfokus pada penyelesaian tugas saya sendiri. | E19: Mengetahui siapa yang kuat dan siapa yang lemah, namun belum menelusuri penyebabnya. | F19: Mengenali kekuatan dan area pengembangan orang lain berdasarkan hasil kerjanya. | G19: Menelusuri penyebab kesenjangan kemampuan dan menyesuaikan cara bekerja dengan orang tersebut. | H19: Memetakan potensi orang lain secara akurat dan mengarahkannya pada peran atau tugas yang tepat. | I19: 1 | J19: 2 | K19: 3 | M19: =I19-K19 -> -2 | N19: {=_xlfn.IFS( M19>=2, "Major Positive Gap", M19>=1, "Minor Positive Gap", M19>=0, "No Gap", M19>=-1, "Minor Negative Gap", M19<=-2, "Major Negative Gap" )} -> Major Negative Gap | O19: {=_xlfn.SWITCH(N19, "No Gap","persepsi diri Selaras dengan penilaian Atasan", "Minor Positive Gap","Self-assessment sedikit lebih tinggi dari superior assessment", "Major Positive Gap","Self-assessment jauh lebih tinggi dari perilaku yang tampak menurut atasan", "Minor Negative Gap","Self-assessment sedikit lebih rendah dari superior assessment", "Major Negative Gap","Self-assessment jauh lebih rendah dari perilaku yang tampak menurut atasan", "" )} -> Self-assessment jauh lebih rendah dari perilaku yang tampak menurut atasan | P19: {=_xlfn.SWITCH(N19, "No Gap","persepsi diri Selaras dengan perilaku yang ditunjukan", "Minor Positive Gap","Individu merasa sudah sangat baik, tetapi atasan melihat baru cukup baik", "Major Positive Gap","Ada potensi blind spot; perilaku belum terlihat sekuat persepsi diri", "Minor Negative Gap","Individu mungkin kurang percaya diri atau belum menyadari kekuatannya", "Major Negative Gap","Ada hidden strength; individu tidak menyadari bahwa perilakunya sudah terlihat kuat", "" )} -> Ada hidden strength; individu tidak menyadari bahwa perilakunya sudah terlihat kuat
A20: =A19+1 -> 8 | B20: Setting Direction & Expectations (menetapkan arah & ekspektasi) | C20: Ketika dipercaya memimpin sebuah tugas, kegiatan, atau kelompok kerja, perilaku yang paling sering saya tunjukkan adalah… | D20: Menjalankan bagian saya dan berharap orang lain memahami perannya masing-masing. | E20: Menyampaikan apa yang harus dikerjakan tanpa menjelaskan hasil yang diharapkan. | F20: Menjelaskan tujuan, pembagian peran, dan hasil yang diharapkan kepada semua pihak. | G20: Menyepakati ukuran keberhasilan bersama dan memastikan setiap orang memahami tanggung jawabnya. | H20: Menetapkan arah yang cukup jelas sehingga orang lain dapat memutuskan sendiri tanpa menunggu saya. | I20: 3 | J20: 3 | K20: 5 | M20: =I20-K20 -> -2 | N20: {=_xlfn.IFS( M20>=2, "Major Positive Gap", M20>=1, "Minor Positive Gap", M20>=0, "No Gap", M20>=-1, "Minor Negative Gap", M20<=-2, "Major Negative Gap" )} -> Major Negative Gap | O20: {=_xlfn.SWITCH(N20, "No Gap","persepsi diri Selaras dengan penilaian Atasan", "Minor Positive Gap","Self-assessment sedikit lebih tinggi dari superior assessment", "Major Positive Gap","Self-assessment jauh lebih tinggi dari perilaku yang tampak menurut atasan", "Minor Negative Gap","Self-assessment sedikit lebih rendah dari superior assessment", "Major Negative Gap","Self-assessment jauh lebih rendah dari perilaku yang tampak menurut atasan", "" )} -> Self-assessment jauh lebih rendah dari perilaku yang tampak menurut atasan | P20: {=_xlfn.SWITCH(N20, "No Gap","persepsi diri Selaras dengan perilaku yang ditunjukan", "Minor Positive Gap","Individu merasa sudah sangat baik, tetapi atasan melihat baru cukup baik", "Major Positive Gap","Ada potensi blind spot; perilaku belum terlihat sekuat persepsi diri", "Minor Negative Gap","Individu mungkin kurang percaya diri atau belum menyadari kekuatannya", "Major Negative Gap","Ada hidden strength; individu tidak menyadari bahwa perilakunya sudah terlihat kuat", "" )} -> Ada hidden strength; individu tidak menyadari bahwa perilakunya sudah terlihat kuat
A21: =A20+1 -> 9 | B21: Empathy (Merasakan & memahami emosi orang lain) | C21: Ketika menghadapi situasi yang melibatkan emosi, tekanan, atau perasaan orang lain, perilaku yang paling sering saya tunjukkan adalah… | D21: Belum menyadari emosi orang lain, sehingga respons saya kurang sesuai. | E21: Menyadari emosi yang terlihat jelas, namun belum memahami penyebabnya. | F21: Mengamati ekspresi, nada bicara, dan situasi orang lain serta menunjukkan perhatian. | G21: Menggali penyebab perasaan orang lain dan memberi respons atau dukungan yang tepat. | H21: Membaca dinamika emosi individu maupun kelompok dan meresponsnya sambil menjaga hubungan kerja tetap produktif. | I21: 3 | J21: 2 | K21: 2 | M21: =I21-K21 -> 1 | N21: {=_xlfn.IFS( M21>=2, "Major Positive Gap", M21>=1, "Minor Positive Gap", M21>=0, "No Gap", M21>=-1, "Minor Negative Gap", M21<=-2, "Major Negative Gap" )} -> Minor Positive Gap | O21: {=_xlfn.SWITCH(N21, "No Gap","persepsi diri Selaras dengan penilaian Atasan", "Minor Positive Gap","Self-assessment sedikit lebih tinggi dari superior assessment", "Major Positive Gap","Self-assessment jauh lebih tinggi dari perilaku yang tampak menurut atasan", "Minor Negative Gap","Self-assessment sedikit lebih rendah dari superior assessment", "Major Negative Gap","Self-assessment jauh lebih rendah dari perilaku yang tampak menurut atasan", "" )} -> Self-assessment sedikit lebih tinggi dari superior assessment | P21: {=_xlfn.SWITCH(N21, "No Gap","persepsi diri Selaras dengan perilaku yang ditunjukan", "Minor Positive Gap","Individu merasa sudah sangat baik, tetapi atasan melihat baru cukup baik", "Major Positive Gap","Ada potensi blind spot; perilaku belum terlihat sekuat persepsi diri", "Minor Negative Gap","Individu mungkin kurang percaya diri atau belum menyadari kekuatannya", "Major Negative Gap","Ada hidden strength; individu tidak menyadari bahwa perilakunya sudah terlihat kuat", "" )} -> Individu merasa sudah sangat baik, tetapi atasan melihat baru cukup baik
A22: =A21+1 -> 10 | B22: Conflict Navigation (menghadapi konflik secara konstruktif) | C22: Ketika menghadapi konflik kerja atau perbedaan kepentingan, perilaku yang paling sering saya tunjukkan adalah… (Fokus indikator: konflik yang melibatkan diri saya sendiri sebagai salah satu pihak) | D22: Menunda atau menghindari pembicaraan mengenai konflik tersebut. | E22: Menghadapi konflik, namun mundur ketika situasinya meningkat. | F22: Menangani konflik sederhana melalui komunikasi yang terbuka. | G22: Mengelola konflik secara konstruktif dengan fokus pada isu utama dan solusi yang adil. | H22: Menjadikan konflik sebagai kesempatan memperjelas ekspektasi dan memperkuat kepercayaan. | I22: 5 | J22: 2 | K22: 4 | M22: =I22-K22 -> 1 | N22: {=_xlfn.IFS( M22>=2, "Major Positive Gap", M22>=1, "Minor Positive Gap", M22>=0, "No Gap", M22>=-1, "Minor Negative Gap", M22<=-2, "Major Negative Gap" )} -> Minor Positive Gap | O22: {=_xlfn.SWITCH(N22, "No Gap","persepsi diri Selaras dengan penilaian Atasan", "Minor Positive Gap","Self-assessment sedikit lebih tinggi dari superior assessment", "Major Positive Gap","Self-assessment jauh lebih tinggi dari perilaku yang tampak menurut atasan", "Minor Negative Gap","Self-assessment sedikit lebih rendah dari superior assessment", "Major Negative Gap","Self-assessment jauh lebih rendah dari perilaku yang tampak menurut atasan", "" )} -> Self-assessment sedikit lebih tinggi dari superior assessment | P22: {=_xlfn.SWITCH(N22, "No Gap","persepsi diri Selaras dengan perilaku yang ditunjukan", "Minor Positive Gap","Individu merasa sudah sangat baik, tetapi atasan melihat baru cukup baik", "Major Positive Gap","Ada potensi blind spot; perilaku belum terlihat sekuat persepsi diri", "Minor Negative Gap","Individu mungkin kurang percaya diri atau belum menyadari kekuatannya", "Major Negative Gap","Ada hidden strength; individu tidak menyadari bahwa perilakunya sudah terlihat kuat", "" )} -> Individu merasa sudah sangat baik, tetapi atasan melihat baru cukup baik
A23: =A22+1 -> 11 | B23: Giving Developmental Feedback (memberi umpan balik yang mengembangkan) | C23: Ketika melihat kekurangan atau hal yang perlu ditingkatkan pada cara kerja orang lain, perilaku yang paling sering saya tunjukkan adalah… | D23: Membiarkannya, atau menyelesaikan sendiri pekerjaan yang kurang tepat tersebut. | E23: Menyampaikan ketika situasi sudah mendesak atau ketika kesalahannya berulang. | F23: Menyampaikan secara langsung disertai contoh yang jelas. | G23: Menyampaikan dengan cara yang menjaga harga diri orang tersebut dan disertai saran perbaikan. | H23: Menyampaikan secara teratur sehingga umpan balik menjadi hal yang biasa, bukan sesuatu yang ditakuti. | I23: 1 | J23: 3 | K23: 1 | M23: =I23-K23 -> 0 | N23: {=_xlfn.IFS( M23>=2, "Major Positive Gap", M23>=1, "Minor Positive Gap", M23>=0, "No Gap", M23>=-1, "Minor Negative Gap", M23<=-2, "Major Negative Gap" )} -> No Gap | O23: {=_xlfn.SWITCH(N23, "No Gap","persepsi diri Selaras dengan penilaian Atasan", "Minor Positive Gap","Self-assessment sedikit lebih tinggi dari superior assessment", "Major Positive Gap","Self-assessment jauh lebih tinggi dari perilaku yang tampak menurut atasan", "Minor Negative Gap","Self-assessment sedikit lebih rendah dari superior assessment", "Major Negative Gap","Self-assessment jauh lebih rendah dari perilaku yang tampak menurut atasan", "" )} -> persepsi diri Selaras dengan penilaian Atasan | P23: {=_xlfn.SWITCH(N23, "No Gap","persepsi diri Selaras dengan perilaku yang ditunjukan", "Minor Positive Gap","Individu merasa sudah sangat baik, tetapi atasan melihat baru cukup baik", "Major Positive Gap","Ada potensi blind spot; perilaku belum terlihat sekuat persepsi diri", "Minor Negative Gap","Individu mungkin kurang percaya diri atau belum menyadari kekuatannya", "Major Negative Gap","Ada hidden strength; individu tidak menyadari bahwa perilakunya sudah terlihat kuat", "" )} -> persepsi diri Selaras dengan perilaku yang ditunjukan
A24: =A23+1 -> 12 | B24: Managing Challenging Stakeholder (relasi berkelanjutan dengan pihak sulit) | C24: Ketika harus menjaga hubungan profesional dengan individu atau stakeholder yang sulit, berpengaruh, atau memiliki kepentingan berbeda, perilaku yang paling sering saya tunjukkan adalah… | D24: Membatasi interaksi dengan pihak tersebut seminimal mungkin. | E24: Berinteraksi seperlunya dan memerlukan bantuan pihak ketiga ketika terjadi gesekan. | F24: Menjaga profesionalisme dan mulai memahami kepentingan pihak kunci. | G24: Menyesuaikan gaya komunikasi dan mencari titik temu untuk membangun hubungan kerja yang produktif. | H24: Menjadi penghubung yang dipercaya di antara kepentingan berbeda dan menjaga kerja sama berkelanjutan. | I24: 2 | J24: 3 | K24: 3 | M24: =I24-K24 -> -1 | N24: {=_xlfn.IFS( M24>=2, "Major Positive Gap", M24>=1, "Minor Positive Gap", M24>=0, "No Gap", M24>=-1, "Minor Negative Gap", M24<=-2, "Major Negative Gap" )} -> Minor Negative Gap | O24: {=_xlfn.SWITCH(N24, "No Gap","persepsi diri Selaras dengan penilaian Atasan", "Minor Positive Gap","Self-assessment sedikit lebih tinggi dari superior assessment", "Major Positive Gap","Self-assessment jauh lebih tinggi dari perilaku yang tampak menurut atasan", "Minor Negative Gap","Self-assessment sedikit lebih rendah dari superior assessment", "Major Negative Gap","Self-assessment jauh lebih rendah dari perilaku yang tampak menurut atasan", "" )} -> Self-assessment sedikit lebih rendah dari superior assessment | P24: {=_xlfn.SWITCH(N24, "No Gap","persepsi diri Selaras dengan perilaku yang ditunjukan", "Minor Positive Gap","Individu merasa sudah sangat baik, tetapi atasan melihat baru cukup baik", "Major Positive Gap","Ada potensi blind spot; perilaku belum terlihat sekuat persepsi diri", "Minor Negative Gap","Individu mungkin kurang percaya diri atau belum menyadari kekuatannya", "Major Negative Gap","Ada hidden strength; individu tidak menyadari bahwa perilakunya sudah terlihat kuat", "" )} -> Individu mungkin kurang percaya diri atau belum menyadari kekuatannya
A25: =A24+1 -> 13 | B25: Delegating for Growth (mendelegasikan sebagai sarana pengembangan) | C25: Ketika ada tugas yang dapat saya kerjakan sendiri atau diserahkan kepada orang lain, perilaku yang paling sering saya tunjukkan adalah… | D25: Mengerjakan sendiri karena lebih cepat dan hasilnya lebih terjamin. | E25: Menyerahkan tugas rutin saja, sementara tugas penting tetap saya tangani. | F25: Menyerahkan tugas disertai penjelasan dan arahan yang memadai. | G25: Memilih tugas yang sekaligus menjadi kesempatan belajar bagi orang tersebut. | H25: Memberikan tugas yang meregangkan kemampuan orang lain, disertai pendampingan dan ruang untuk keliru. | I25: 4 | J25: 5 | K25: 4 | M25: =I25-K25 -> 0 | N25: {=_xlfn.IFS( M25>=2, "Major Positive Gap", M25>=1, "Minor Positive Gap", M25>=0, "No Gap", M25>=-1, "Minor Negative Gap", M25<=-2, "Major Negative Gap" )} -> No Gap | O25: {=_xlfn.SWITCH(N25, "No Gap","persepsi diri Selaras dengan penilaian Atasan", "Minor Positive Gap","Self-assessment sedikit lebih tinggi dari superior assessment", "Major Positive Gap","Self-assessment jauh lebih tinggi dari perilaku yang tampak menurut atasan", "Minor Negative Gap","Self-assessment sedikit lebih rendah dari superior assessment", "Major Negative Gap","Self-assessment jauh lebih rendah dari perilaku yang tampak menurut atasan", "" )} -> persepsi diri Selaras dengan penilaian Atasan | P25: {=_xlfn.SWITCH(N25, "No Gap","persepsi diri Selaras dengan perilaku yang ditunjukan", "Minor Positive Gap","Individu merasa sudah sangat baik, tetapi atasan melihat baru cukup baik", "Major Positive Gap","Ada potensi blind spot; perilaku belum terlihat sekuat persepsi diri", "Minor Negative Gap","Individu mungkin kurang percaya diri atau belum menyadari kekuatannya", "Major Negative Gap","Ada hidden strength; individu tidak menyadari bahwa perilakunya sudah terlihat kuat", "" )} -> persepsi diri Selaras dengan perilaku yang ditunjukan
... A28: =A27+1 -> 16 | B28: Coaching & Building Capability (membangun kemampuan orang lain) | C28: Dalam memastikan kesiapan kemampuan orang lain untuk tuntutan jangka panjang, perilaku yang paling sering saya tunjukkan adalah… | D28: Memandang pengembangan kemampuan sebagai tanggung jawab fungsi SDM. | E28: Mendukung pengembangan orang lain ketika diminta atau ketika programnya sudah tersedia. | F28: Mengarahkan orang lain pada kesempatan belajar yang relevan dengan kebutuhannya. | G28: Mendampingi perkembangan orang lain melalui percakapan pengembangan yang teratur. | H28: Membangun kebiasaan saling mengembangkan sehingga pembelajaran berjalan tanpa bergantung pada saya. | I28: 3 | J28: 2 | K28: 2 | M28: =I28-K28 -> 1 | N28: {=_xlfn.IFS( M28>=2, "Major Positive Gap", M28>=1, "Minor Positive Gap", M28>=0, "No Gap", M28>=-1, "Minor Negative Gap", M28<=-2, "Major Negative Gap" )} -> Minor Positive Gap | O28: {=_xlfn.SWITCH(N28, "No Gap","persepsi diri Selaras dengan penilaian Atasan", "Minor Positive Gap","Self-assessment sedikit lebih tinggi dari superior assessment", "Major Positive Gap","Self-assessment jauh lebih tinggi dari perilaku yang tampak menurut atasan", "Minor Negative Gap","Self-assessment sedikit lebih rendah dari superior assessment", "Major Negative Gap","Self-assessment jauh lebih rendah dari perilaku yang tampak menurut atasan", "" )} -> Self-assessment sedikit lebih tinggi dari superior assessment | P28: {=_xlfn.SWITCH(N28, "No Gap","persepsi diri Selaras dengan perilaku yang ditunjukan", "Minor Positive Gap","Individu merasa sudah sangat baik, tetapi atasan melihat baru cukup baik", "Major Positive Gap","Ada potensi blind spot; perilaku belum terlihat sekuat persepsi diri", "Minor Negative Gap","Individu mungkin kurang percaya diri atau belum menyadari kekuatannya", "Major Negative Gap","Ada hidden strength; individu tidak menyadari bahwa perilakunya sudah terlihat kuat", "" )} -> Individu merasa sudah sangat baik, tetapi atasan melihat baru cukup baik
A29: AVERAGE SCORE | I29: =AVERAGE(I13:J27) -> 2.8 | J29: =AVERAGE(J13:K27) -> 3.0333333 | K29: =AVERAGE(K13:L27) -> 3.1333333 | M29: =I29-K29 -> -0.33333333 | N29: {=_xlfn.IFS( VALUE(M29) >= 1, "Major Positive Gap", VALUE(M29) >= 0.5, "Minor Positive Gap", VALUE(M29) >= -0.49, "Aligned", VALUE(M29) >= -0.99, "Minor Negative Gap", VALUE(M29) <= -1, "Major Negative Gap" )} -> Aligned | O29: {=_xlfn.SWITCH(N29, "Aligned","Aligned Perception", "Minor Positive Gap","Slight Overestimation", "Major Positive Gap","Significant Overestimation / Potential Blind Spot", "Minor Negative Gap","Slight Underestimation", "Major Negative Gap","Significant Underestimation / Hidden Strength", "" )} -> Aligned Perception

Sheet change agility
B2: =Identitas!B2 -> Nama | C2: =Identitas!D2 -> 0
B3: =Identitas!B3 -> Nama Atasan yang menilai | C3: =Identitas!D3 -> 0
B4: =Identitas!B4 -> Level Saat Ini | C4: =Identitas!D4 -> Officer
B5: =Identitas!B5 -> Level Tujuan | C5: =Identitas!D5 -> Analyst
B6: =Identitas!B6 -> Tanggal Assesment | C6: =Identitas!D6 -> 0
B7: =Identitas!B7 -> Unit | C7: =Identitas!D7 -> 0
B8: =Identitas!B8 -> Departemen | C8: =Identitas!D8 -> 0
B9: =Identitas!B9 -> Divisi | C9: =Identitas!D9 -> 0
B10: =Identitas!B10 -> Direktorat | C10: =Identitas!D10 -> 0
A12: No | B12: Indikator | C12: Pernyataan Situasi | D12: Level 1 (Rendah) | E12: Level 2 (Cukup) | F12: Level 3 (Baik) | G12: Level 4 (Sangat Baik) | H12: Level 5 (Luar Biasa) | I12: Rating (1-5) self | J12: Komentar / Contoh Perilaku | K12: Rating (1-5) superior | L12: Komentar / Contoh Perilaku | M12: Self Awareness GAP Score Self - Sup | N12: Gap | O12: Keterangan | P12: Intepretasi
A13: 1 | B13: Adapting to New Systems (mengikuti perubahan sistem & prosedur) | C13: Ketika diterapkan sistem, prosedur, tools, atau mekanisme kerja baru, perilaku yang paling sering saya tunjukkan adalah… | D13: Memerlukan waktu lama untuk menggunakannya dan cenderung bertahan pada sistem lama. | E13: Mencoba menggunakan sistem baru dengan arahan yang cukup intensif. | F13: Menggunakan sistem baru secara mandiri ketika tersedia panduan yang jelas. | G13: Menguasai sistem baru dengan cepat dan membantu orang lain memahaminya. | H13: Mengoptimalkan sistem baru untuk meningkatkan efektivitas, efisiensi, atau kualitas kerja. | I13: 3 | K13: 4 | M13: =I13-K13 -> -1 | N13: {=_xlfn.IFS( M13>=2, "Major Positive Gap", M13>=1, "Minor Positive Gap", M13>=0, "No Gap", M13>=-1, "Minor Negative Gap", M13<=-2, "Major Negative Gap" )} -> Minor Negative Gap | O13: persepsi diri Selaras dengan penilaian Atasan | P13: persepsi diri Selaras dengan perilaku yang ditunjukan
A14: 2 | B14: Comfort with New Ways of Working (nyaman dengan cara kerja baru) | C14: Ketika diterapkan cara kerja, metode, atau pendekatan baru, perilaku yang paling sering saya tunjukkan adalah… | D14: Merasa tidak nyaman dan tetap menggunakan cara kerja lama. | E14: Mencoba cara kerja baru, namun sering kembali pada kebiasaan lama. | F14: Menyesuaikan diri setelah memahami alasan dan manfaat perubahan tersebut. | G14: Bekerja dengan nyaman menggunakan pendekatan baru dan cepat menyesuaikan kebiasaan kerja. | H14: Mencoba cara kerja baru dengan antusias dan mendorong perbaikan proses di sekitar saya. | I14: 3 | K14: 3 | M14: =I14-K14 -> 0 | N14: {=_xlfn.IFS( M14>=2, "Major Positive Gap", M14>=1, "Minor Positive Gap", M14>=0, "No Gap", M14>=-1, "Minor Negative Gap", M14<=-2, "Major Negative Gap" )} -> No Gap | O14: persepsi diri Selaras dengan penilaian Atasan | P14: persepsi diri Selaras dengan perilaku yang ditunjukan
A15: 3 | B15: Comfort with Sudden Change (tetap bekerja saat perubahan mendadak) | C15: Ketika menghadapi perubahan mendadak dalam prioritas, arahan, target, atau situasi kerja, perilaku yang paling sering saya tunjukkan adalah… | D15: Memerlukan waktu untuk dapat melanjutkan pekerjaan setelah perubahan terjadi. | E15: Menyesuaikan diri, namun membutuhkan waktu cukup lama untuk kembali produktif. | F15: Menyesuaikan diri dengan baik ketika perubahan dijelaskan secara jelas. | G15: Menyesuaikan prioritas dengan cepat dan tetap produktif. | H15: Memanfaatkan perubahan mendadak sebagai kesempatan memperbaiki cara kerja atau hasil. | I15: 3 | K15: 2 | M15: =I15-K15 -> 1 | N15: {=_xlfn.IFS( M15>=2, "Major Positive Gap", M15>=1, "Minor Positive Gap", M15>=0, "No Gap", M15>=-1, "Minor Negative Gap", M15<=-2, "Major Negative Gap" )} -> Minor Positive Gap | O15: Self-assessment jauh lebih rendah dari perilaku yang tampak menurut atasan | P15: Ada hidden strength; individu tidak menyadari bahwa perilakunya sudah terlihat kuat
A16: 4 | B16: Managing Resistance to Change (pengelolaan resistensi) | C16: Ketika menghadapi perubahan yang menimbulkan ketidakpastian atau ketidaknyamanan, perilaku yang paling sering saya tunjukkan adalah… | D16: Bertahan pada cara kerja dan arah yang lama. | E16: Menerima perubahan, namun kembali ke cara lama saat menghadapi kesulitan. | F16: Menerima perubahan dengan bantuan penjelasan atau dukungan tambahan. | G16: Mengenali keberatan dalam diri saya sendiri dan mengelolanya secara konstruktif. | H16: Mendukung perubahan secara aktif dan membantu orang lain mengurangi keberatannya. | I16: 4 | K16: 3 | M16: =I16-K16 -> 1 | N16: {=_xlfn.IFS( M16>=2, "Major Positive Gap", M16>=1, "Minor Positive Gap", M16>=0, "No Gap", M16>=-1, "Minor Negative Gap", M16<=-2, "Major Negative Gap" )} -> Minor Positive Gap | O16: Self-assessment sedikit lebih rendah dari superior assessment | P16: Individu mungkin kurang percaya diri atau belum menyadari kekuatannya
A17: 5 | B17: Adaptive Learning & Experimentation (aktif belajar hal baru) | C17: Ketika perubahan menuntut pengetahuan, keterampilan, atau pendekatan baru, perilaku yang paling sering saya tunjukkan adalah… | D17: Mengandalkan pengetahuan dan keterampilan yang sudah saya miliki. | E17: Tertarik pada hal baru, namun belum konsisten mempelajarinya. | F17: Mempelajari pengetahuan atau keterampilan baru yang relevan ketika dibutuhkan.. | G17: Belajar lintas bidang dan mencoba menerapkannya dalam pekerjaan. | H17: Mencari, menguji, dan menerapkan pembelajaran baru secara konsisten untuk menghasilkan solusi yang lebih baik. | I17: 4 | K17: 4 | M17: =I17-K17 -> 0 | N17: {=_xlfn.IFS( M17>=2, "Major Positive Gap", M17>=1, "Minor Positive Gap", M17>=0, "No Gap", M17>=-1, "Minor Negative Gap", M17<=-2, "Major Negative Gap" )} -> No Gap | O17: Self-assessment sedikit lebih rendah dari superior assessment | P17: Individu mungkin kurang percaya diri atau belum menyadari kekuatannya
A18: 6 | B18: Viewing Change as Opportunity (melihat perubahan sebagai peluang) | C18: Ketika menilai perubahan yang terjadi di lingkungan kerja, perilaku yang paling sering saya tunjukkan adalah… | D18: Memandang perubahan sebagai gangguan terhadap rutinitas kerja. | E18: Menerima perubahan dengan sangat berhati-hati. | F18: Memandang perubahan sebagai sesuatu yang perlu diikuti dan disesuaikan. | G18: Memandang perubahan sebagai kesempatan belajar dan memperbaiki proses kerja. | H18: Mencari peluang di dalam perubahan untuk menciptakan nilai atau cara kerja baru. | I18: 3 | K18: 2 | M18: =I18-K18 -> 1 | N18: {=_xlfn.IFS( M18>=2, "Major Positive Gap", M18>=1, "Minor Positive Gap", M18>=0, "No Gap", M18>=-1, "Minor Negative Gap", M18<=-2, "Major Negative Gap" )} -> Minor Positive Gap | O18: Self-assessment jauh lebih tinggi dari perilaku yang tampak menurut atasan | P18: Ada potensi blind spot; perilaku belum terlihat sekuat persepsi diri
A19: 7 | B19: Proposing New Ideas (menginisiasi perubahan) | C19: Ketika melihat peluang perbaikan atau kebutuhan perubahan, perilaku yang paling sering saya tunjukkan adalah… | D19: Mengikuti arahan yang sudah ditetapkan. | E19: Menyampaikan ide sederhana ketika diminta atau ketika masalahnya sudah terlihat jelas. | F19: Memberikan saran yang relevan untuk perbaikan proses atau penyelesaian masalah. | G19: Mengusulkan ide baru yang relevan dan realistis secara konsisten. | H19: Menciptakan ide inovatif dan mendorong implementasinya hingga memberi dampak nyata. | I19: 3 | K19: 3 | M19: =I19-K19 -> 0 | N19: {=_xlfn.IFS( M19>=2, "Major Positive Gap", M19>=1, "Minor Positive Gap", M19>=0, "No Gap", M19>=-1, "Minor Negative Gap", M19<=-2, "Major Negative Gap" )} -> No Gap | O19: Self-assessment sedikit lebih rendah dari superior assessment | P19: Individu mungkin kurang percaya diri atau belum menyadari kekuatannya
A20: 8 | B20: Risk-Taking for Innovation (berani mencoba pendekatan baru) | C20: Ketika perlu mencoba cara, pendekatan, atau solusi baru yang belum sepenuhnya terbukti, perilaku yang paling sering saya tunjukkan adalah… | D20: Memilih metode yang aman dan biasa digunakan. | E20: Mencoba metode baru, namun kembali ke cara lama ketika hasilnya belum terlihat. | F20: Mengambil risiko terukur setelah mempertimbangkan dampaknya. | G20: Mencoba pendekatan baru meski hasilnya belum pasti, dengan tetap mengelola risikonya. | H20: Mendorong eksperimen dalam tim dan menarik pembelajaran atau inovasi dari hasilnya. | I20: 2 | K20: 1 | M20: =I20-K20 -> 1 | N20: {=_xlfn.IFS( M20>=2, "Major Positive Gap", M20>=1, "Minor Positive Gap", M20>=0, "No Gap", M20>=-1, "Minor Negative Gap", M20<=-2, "Major Negative Gap" )} -> Minor Positive Gap | O20: Self-assessment jauh lebih tinggi dari perilaku yang tampak menurut atasan | P20: Ada potensi blind spot; perilaku belum terlihat sekuat persepsi diri
A21: 9 | B21: Calmness in Uncertainty (tetap tenang di kondisi tidak pasti) | C21: Ketika menghadapi situasi kerja yang tidak pasti, berubah cepat, atau belum memiliki arah yang jelas, perilaku yang paling sering saya tunjukkan adalah… | D21: Merasa tidak nyaman dan sulit berpikir jernih ketika arah belum jelas. | E21: Berusaha tenang, namun fokus saya mudah terganggu. | F21: Mengelola diri dan tetap menjalankan pekerjaan dalam ketidakpastian. | G21: Tetap tenang, menjaga fokus, dan mengambil keputusan yang tepat. | H21: Menjaga ketenangan diri dan orang lain, membaca peluang, serta menentukan langkah strategis. | I21: 2 | K21: 1 | M21: =I21-K21 -> 1 | N21: {=_xlfn.IFS( M21>=2, "Major Positive Gap", M21>=1, "Minor Positive Gap", M21>=0, "No Gap", M21>=-1, "Minor Negative Gap", M21<=-2, "Major Negative Gap" )} -> Minor Positive Gap | O21: Self-assessment jauh lebih rendah dari perilaku yang tampak menurut atasan | P21: Ada hidden strength; individu tidak menyadari bahwa perilakunya sudah terlihat kuat
A22: 10 | B22: Proactive in Anticipating Change (mengantisipasi perubahan) | C22: Ketika menghadapi kemungkinan perubahan di masa depan, perilaku yang paling sering saya tunjukkan adalah… | D22: Menyesuaikan diri setelah perubahan benar-benar terjadi. | E22: Bergerak ketika tanda perubahan mulai terlihat, dengan persiapan seadanya. | F22: Memperhatikan tanda-tanda perubahan dan melakukan persiapan terbatas. | G22: Memindai lingkungan, membaca tren, dan menyiapkan rencana menghadapi perubahan. | H22: Memperkirakan arah perubahan, menyiapkan skenario, dan menggerakkan pihak terkait sebelum perubahan terjadi. | I22: 3 | K22: 2 | M22: =I22-K22 -> 1 | N22: {=_xlfn.IFS( M22>=2, "Major Positive Gap", M22>=1, "Minor Positive Gap", M22>=0, "No Gap", M22>=-1, "Minor Negative Gap", M22<=-2, "Major Negative Gap" )} -> Minor Positive Gap | O22: persepsi diri Selaras dengan penilaian Atasan | P22: persepsi diri Selaras dengan perilaku yang ditunjukan
A23: AVERAGE SCORE | I23: =AVERAGE(I13:J22) -> 3 | J23: =AVERAGE(J13:K22) -> 2.5 | K23: =AVERAGE(K13:L22) -> 2.5 | M23: =I23-K23 -> 0.5 | N23: {=_xlfn.IFS( VALUE(M23) >= 1, "Major Positive Gap", VALUE(M23) >= 0.5, "Minor Positive Gap", VALUE(M23) >= -0.49, "Aligned", VALUE(M23) >= -0.99, "Minor Negative Gap", VALUE(M23) <= -1, "Major Negative Gap" )} -> Minor Positive Gap | O23: {=_xlfn.SWITCH(N23, "Aligned","Aligned Perception", "Minor Positive Gap","Slight Overestimation", "Major Positive Gap","Significant Overestimation / Potential Blind Spot", "Minor Negative Gap","Slight Underestimation", "Major Negative Gap","Significant Underestimation / Hidden Strength", "" )} -> Slight Overestimation

Sheet result agility
B2: =Identitas!B2 -> Nama | C2: =Identitas!D2 -> 0
B3: =Identitas!B3 -> Nama Atasan yang menilai | C3: =Identitas!D3 -> 0
B4: =Identitas!B4 -> Level Saat Ini | C4: =Identitas!D4 -> Officer
B5: =Identitas!B5 -> Level Tujuan | C5: =Identitas!D5 -> Analyst
B6: =Identitas!B6 -> Tanggal Assesment | C6: =Identitas!D6 -> 0
B7: =Identitas!B7 -> Unit | C7: =Identitas!D7 -> 0
B8: =Identitas!B8 -> Departemen | C8: =Identitas!D8 -> 0
B9: =Identitas!B9 -> Divisi | C9: =Identitas!D9 -> 0
B10: =Identitas!B10 -> Direktorat | C10: =Identitas!D10 -> 0
A12: No | B12: Indikator | C12: Pernyataan Situasi | D12: Level 1 (Rendah) | E12: Level 2 (Cukup) | F12: Level 3 (Baik) | G12: Level 4 (Sangat Baik) | H12: Level 5 (Luar Biasa) | I12: Rating (1-5) self | J12: Komentar / Contoh Perilaku | K12: Rating (1-5) superior | L12: Komentar / Contoh Perilaku | M12: Self Awareness GAP Score Self - Sup | N12: Gap | O12: Keterangan | P12: Intepretasi
A13: 1 | B13: Task Completion Quality (menyelesaikan tugas dengan baik) | C13: Ketika menyelesaikan tugas dan tanggung jawab kerja, termasuk tugas yang belum pernah saya kerjakan sebelumnya, perilaku yang paling sering saya tunjukkan adalah… | D13: Hasil kerja saya belum selalu memenuhi standar atau tenggat waktu. | E13: Menyelesaikan tugas dengan kualitas dan ketepatan waktu yang belum konsisten. | F13: Menyelesaikan tugas dengan kualitas yang stabil dan sesuai standar. | G13: Menghasilkan pekerjaan berkualitas tinggi dan tepat waktu secara konsisten. | H13: Menghasilkan output yang melampaui ekspektasi dan menjadi rujukan standar kualitas bagi orang lain. | I13: 1 | K13: 2 | M13: =I13-K13 -> -1 | N13: {=_xlfn.IFS( M13>=2, "Major Positive Gap", M13>=1, "Minor Positive Gap", M13>=0, "No Gap", M13>=-1, "Minor Negative Gap", M13<=-2, "Major Negative Gap" )} -> Minor Negative Gap | O13: {=_xlfn.SWITCH(N13, "No Gap","persepsi diri Selaras dengan penilaian Atasan", "Minor Positive Gap","Self-assessment sedikit lebih tinggi dari superior assessment", "Major Positive Gap","Self-assessment jauh lebih tinggi dari perilaku yang tampak menurut atasan", "Minor Negative Gap","Self-assessment sedikit lebih rendah dari superior assessment", "Major Negative Gap","Self-assessment jauh lebih rendah dari perilaku yang tampak menurut atasan", "" )} -> Self-assessment sedikit lebih rendah dari superior assessment | P13: {=_xlfn.SWITCH(N13, "No Gap","persepsi diri Selaras dengan perilaku yang ditunjukan", "Minor Positive Gap","Individu merasa sudah sangat baik, tetapi atasan melihat baru cukup baik", "Major Positive Gap","Ada potensi blind spot; perilaku belum terlihat sekuat persepsi diri", "Minor Negative Gap","Individu mungkin kurang percaya diri atau belum menyadari kekuatannya", "Major Negative Gap","Ada hidden strength; individu tidak menyadari bahwa perilakunya sudah terlihat kuat", "" )} -> Individu mungkin kurang percaya diri atau belum menyadari kekuatannya
A14: =A13+1 -> 2 | B14: Action-Oriented & Takes Initiative (proaktif bertindak) | C14: Ketika melihat peluang perbaikan, masalah, atau kebutuhan tindakan dalam pekerjaan, perilaku yang paling sering saya tunjukkan adalah… | D14: Menunggu instruksi yang jelas sebelum bertindak. | E14: Mengidentifikasi peluang atau masalah, lalu menunggu persetujuan sebelum bertindak. | F14: Mengambil inisiatif menangani masalah dalam area tanggung jawab saya. | G14: Menciptakan peluang perbaikan dan mengantisipasi masalah sebelum berdampak. | H14: Mengambil inisiatif yang menghasilkan perubahan positif dan menggerakkan orang lain untuk terlibat. | I14: 5 | K14: 5 | M14: =I14-K14 -> 0 | N14: {=_xlfn.IFS( M14>=2, "Major Positive Gap", M14>=1, "Minor Positive Gap", M14>=0, "No Gap", M14>=-1, "Minor Negative Gap", M14<=-2, "Major Negative Gap" )} -> No Gap | O14: {=_xlfn.SWITCH(N14, "No Gap","persepsi diri Selaras dengan penilaian Atasan", "Minor Positive Gap","Self-assessment sedikit lebih tinggi dari superior assessment", "Major Positive Gap","Self-assessment jauh lebih tinggi dari perilaku yang tampak menurut atasan", "Minor Negative Gap","Self-assessment sedikit lebih rendah dari superior assessment", "Major Negative Gap","Self-assessment jauh lebih rendah dari perilaku yang tampak menurut atasan", "" )} -> persepsi diri Selaras dengan penilaian Atasan | P14: {=_xlfn.SWITCH(N14, "No Gap","persepsi diri Selaras dengan perilaku yang ditunjukan", "Minor Positive Gap","Individu merasa sudah sangat baik, tetapi atasan melihat baru cukup baik", "Major Positive Gap","Ada potensi blind spot; perilaku belum terlihat sekuat persepsi diri", "Minor Negative Gap","Individu mungkin kurang percaya diri atau belum menyadari kekuatannya", "Major Negative Gap","Ada hidden strength; individu tidak menyadari bahwa perilakunya sudah terlihat kuat", "" )} -> persepsi diri Selaras dengan perilaku yang ditunjukan
A15: =A14+1 -> 3 | B15: Driving for impact (fokus pada hasil kerja) | C15: Ketika menilai keberhasilan pekerjaan saya, perilaku yang paling sering saya tunjukkan adalah… | D15: Menilai keberhasilan dari aktivitas yang telah saya kerjakan. | E15: Menyelesaikan pekerjaan sesuai prosedur tanpa memastikan efektivitas hasilnya. | F15: Memahami tujuan akhir pekerjaan dan bertanggung jawab atas pencapaiannya. | G15: Mengenali hambatan, menyesuaikan proses, dan menggunakan metrik untuk memastikan hasil tercapai. | H15: Memastikan hasil kerja memberi nilai nyata bagi tim, pelanggan, fungsi, atau organisasi. | I15: 4 | K15: 4 | M15: =I15-K15 -> 0 | N15: {=_xlfn.IFS( M15>=2, "Major Positive Gap", M15>=1, "Minor Positive Gap", M15>=0, "No Gap", M15>=-1, "Minor Negative Gap", M15<=-2, "Major Negative Gap" )} -> No Gap | O15: {=_xlfn.SWITCH(N15, "No Gap","persepsi diri Selaras dengan penilaian Atasan", "Minor Positive Gap","Self-assessment sedikit lebih tinggi dari superior assessment", "Major Positive Gap","Self-assessment jauh lebih tinggi dari perilaku yang tampak menurut atasan", "Minor Negative Gap","Self-assessment sedikit lebih rendah dari superior assessment", "Major Negative Gap","Self-assessment jauh lebih rendah dari perilaku yang tampak menurut atasan", "" )} -> persepsi diri Selaras dengan penilaian Atasan | P15: {=_xlfn.SWITCH(N15, "No Gap","persepsi diri Selaras dengan perilaku yang ditunjukan", "Minor Positive Gap","Individu merasa sudah sangat baik, tetapi atasan melihat baru cukup baik", "Major Positive Gap","Ada potensi blind spot; perilaku belum terlihat sekuat persepsi diri", "Minor Negative Gap","Individu mungkin kurang percaya diri atau belum menyadari kekuatannya", "Major Negative Gap","Ada hidden strength; individu tidak menyadari bahwa perilakunya sudah terlihat kuat", "" )} -> persepsi diri Selaras dengan perilaku yang ditunjukan
A16: =A15+1 -> 4 | B16: Tenacity & Strategic Persistence (menjaga komitmen di tengah tantangan) | C16: Ketika menghadapi tantangan berat, hambatan, atau kegagalan dalam mencapai target, perilaku yang paling sering saya tunjukkan adalah… | D16: Komitmen saya menurun ketika tantangannya berat. | E16: Tetap berupaya, namun memerlukan dorongan dari luar ketika upaya awal gagal. | F16: Berusaha menyelesaikan tugas dan meminta bantuan ketika menghadapi hambatan sulit. | G16: Menjaga energi dan komitmen dalam jangka panjang tanpa mudah frustrasi. | H16: Bertahan menghadapi tantangan berat dengan terus mencari solusi baru tanpa kehilangan arah hasil. | I16: 3 | K16: 5 | M16: =I16-K16 -> -2 | N16: {=_xlfn.IFS( M16>=2, "Major Positive Gap", M16>=1, "Minor Positive Gap", M16>=0, "No Gap", M16>=-1, "Minor Negative Gap", M16<=-2, "Major Negative Gap" )} -> Major Negative Gap | O16: {=_xlfn.SWITCH(N16, "No Gap","persepsi diri Selaras dengan penilaian Atasan", "Minor Positive Gap","Self-assessment sedikit lebih tinggi dari superior assessment", "Major Positive Gap","Self-assessment jauh lebih tinggi dari perilaku yang tampak menurut atasan", "Minor Negative Gap","Self-assessment sedikit lebih rendah dari superior assessment", "Major Negative Gap","Self-assessment jauh lebih rendah dari perilaku yang tampak menurut atasan", "" )} -> Self-assessment jauh lebih rendah dari perilaku yang tampak menurut atasan | P16: {=_xlfn.SWITCH(N16, "No Gap","persepsi diri Selaras dengan perilaku yang ditunjukan", "Minor Positive Gap","Individu merasa sudah sangat baik, tetapi atasan melihat baru cukup baik", "Major Positive Gap","Ada potensi blind spot; perilaku belum terlihat sekuat persepsi diri", "Minor Negative Gap","Individu mungkin kurang percaya diri atau belum menyadari kekuatannya", "Major Negative Gap","Ada hidden strength; individu tidak menyadari bahwa perilakunya sudah terlihat kuat", "" )} -> Ada hidden strength; individu tidak menyadari bahwa perilakunya sudah terlihat kuat
A17: =A16+1 -> 5 | B17: Prioritizing & Sequencing Work (menyusun prioritas & urutan kerja) | C17: Ketika menghadapi beberapa tugas dengan tenggat waktu dan tingkat kepentingan yang berbeda, perilaku yang paling sering saya tunjukkan adalah… | D17: Mengerjakan sesuai urutan tugas yang datang atau yang paling mudah diselesaikan. | E17: Mendahulukan tugas yang paling mendesak atau yang paling sering ditanyakan. | F17: Menyusun urutan kerja berdasarkan tenggat waktu dan tingkat kepentingannya. | G17: Menyusun urutan dengan mempertimbangkan keterkaitan antar tugas dan ketergantungan pada pihak lain. | H17: Menyusun prioritas berdasarkan dampaknya terhadap tujuan yang lebih besar, dan meninjaunya ketika situasi berubah. | I17: 5 | K17: 4 | M17: =I17-K17 -> 1 | N17: {=_xlfn.IFS( M17>=2, "Major Positive Gap", M17>=1, "Minor Positive Gap", M17>=0, "No Gap", M17>=-1, "Minor Negative Gap", M17<=-2, "Major Negative Gap" )} -> Minor Positive Gap | O17: {=_xlfn.SWITCH(N17, "No Gap","persepsi diri Selaras dengan penilaian Atasan", "Minor Positive Gap","Self-assessment sedikit lebih tinggi dari superior assessment", "Major Positive Gap","Self-assessment jauh lebih tinggi dari perilaku yang tampak menurut atasan", "Minor Negative Gap","Self-assessment sedikit lebih rendah dari superior assessment", "Major Negative Gap","Self-assessment jauh lebih rendah dari perilaku yang tampak menurut atasan", "" )} -> Self-assessment sedikit lebih tinggi dari superior assessment | P17: {=_xlfn.SWITCH(N17, "No Gap","persepsi diri Selaras dengan perilaku yang ditunjukan", "Minor Positive Gap","Individu merasa sudah sangat baik, tetapi atasan melihat baru cukup baik", "Major Positive Gap","Ada potensi blind spot; perilaku belum terlihat sekuat persepsi diri", "Minor Negative Gap","Individu mungkin kurang percaya diri atau belum menyadari kekuatannya", "Major Negative Gap","Ada hidden strength; individu tidak menyadari bahwa perilakunya sudah terlihat kuat", "" )} -> Individu merasa sudah sangat baik, tetapi atasan melihat baru cukup baik
A18: =A17+1 -> 6 | B18: Learning from Outcomes (belajar dari hasil & kesalahan) | C18: Setelah mengalami keberhasilan, kegagalan, atau hasil kerja yang belum sesuai harapan, perilaku yang paling sering saya tunjukkan adalah… | D18: Melanjutkan pekerjaan berikutnya tanpa mengevaluasi hasil sebelumnya. | E18: Mengambil pelajaran sesekali, namun belum konsisten menggunakannya untuk perbaikan. | F18: Mengevaluasi hasil kerja dan mengambil pelajaran darinya. | G18: Mengubah pelajaran dari hasil kerja menjadi tindakan perbaikan yang nyata. | H18: Mengubah pembelajaran menjadi peningkatan kinerja yang terukur bagi diri, tim, atau proses kerja. | I18: 1 | K18: 4 | M18: =I18-K18 -> -3 | N18: {=_xlfn.IFS( M18>=2, "Major Positive Gap", M18>=1, "Minor Positive Gap", M18>=0, "No Gap", M18>=-1, "Minor Negative Gap", M18<=-2, "Major Negative Gap" )} -> Major Negative Gap | O18: {=_xlfn.SWITCH(N18, "No Gap","persepsi diri Selaras dengan penilaian Atasan", "Minor Positive Gap","Self-assessment sedikit lebih tinggi dari superior assessment", "Major Positive Gap","Self-assessment jauh lebih tinggi dari perilaku yang tampak menurut atasan", "Minor Negative Gap","Self-assessment sedikit lebih rendah dari superior assessment", "Major Negative Gap","Self-assessment jauh lebih rendah dari perilaku yang tampak menurut atasan", "" )} -> Self-assessment jauh lebih rendah dari perilaku yang tampak menurut atasan | P18: {=_xlfn.SWITCH(N18, "No Gap","persepsi diri Selaras dengan perilaku yang ditunjukan", "Minor Positive Gap","Individu merasa sudah sangat baik, tetapi atasan melihat baru cukup baik", "Major Positive Gap","Ada potensi blind spot; perilaku belum terlihat sekuat persepsi diri", "Minor Negative Gap","Individu mungkin kurang percaya diri atau belum menyadari kekuatannya", "Major Negative Gap","Ada hidden strength; individu tidak menyadari bahwa perilakunya sudah terlihat kuat", "" )} -> Ada hidden strength; individu tidak menyadari bahwa perilakunya sudah terlihat kuat
A19: =A18+1 -> 7 | B19: Deciding with Incomplete Data (mengambil keputusan dengan data/informasi terbatas) | C19: Ketika harus mengambil keputusan dalam situasi baru, tidak pasti, atau dengan informasi yang belum lengkap, perilaku yang paling sering saya tunjukkan adalah… | D19: Menunda keputusan sampai informasinya lengkap.. | E19: Mengumpulkan informasi tambahan terlebih dahulu sebelum memutuskan. | F19: Mengambil keputusan dengan memilih opsi paling logis dari informasi yang tersedia. | G19: Mengambil keputusan setelah menganalisis opsi, skenario, risiko, dan konsekuensinya. | H19: Mengambil keputusan dengan mempertimbangkan pembelajaran sebelumnya dan dampak jangka panjangnya. | I19: 2 | K19: 2 | M19: =I19-K19 -> 0 | N19: {=_xlfn.IFS( M19>=2, "Major Positive Gap", M19>=1, "Minor Positive Gap", M19>=0, "No Gap", M19>=-1, "Minor Negative Gap", M19<=-2, "Major Negative Gap" )} -> No Gap | O19: {=_xlfn.SWITCH(N19, "No Gap","persepsi diri Selaras dengan penilaian Atasan", "Minor Positive Gap","Self-assessment sedikit lebih tinggi dari superior assessment", "Major Positive Gap","Self-assessment jauh lebih tinggi dari perilaku yang tampak menurut atasan", "Minor Negative Gap","Self-assessment sedikit lebih rendah dari superior assessment", "Major Negative Gap","Self-assessment jauh lebih rendah dari perilaku yang tampak menurut atasan", "" )} -> persepsi diri Selaras dengan penilaian Atasan | P19: {=_xlfn.SWITCH(N19, "No Gap","persepsi diri Selaras dengan perilaku yang ditunjukan", "Minor Positive Gap","Individu merasa sudah sangat baik, tetapi atasan melihat baru cukup baik", "Major Positive Gap","Ada potensi blind spot; perilaku belum terlihat sekuat persepsi diri", "Minor Negative Gap","Individu mungkin kurang percaya diri atau belum menyadari kekuatannya", "Major Negative Gap","Ada hidden strength; individu tidak menyadari bahwa perilakunya sudah terlihat kuat", "" )} -> persepsi diri Selaras dengan perilaku yang ditunjukan
A20: =A19+1 -> 8 | B20: Focus Under Pressure (tetap fokus dalam tekanan) | C20: Ketika menghadapi tekanan, hambatan, tenggat waktu ketat, atau tuntutan kerja tinggi, perilaku yang paling sering saya tunjukkan adalah… | D20: Fokus saya menurun ketika tekanan atau hambatan muncul. | E20: Berusaha tetap fokus, namun mudah terganggu saat tekanan meningkat. | F20: Menjaga fokus dan menyelesaikan pekerjaan dengan dukungan tertentu. | G20: Tetap fokus, produktif, dan menjaga kualitas kerja dalam tekanan berat. | H20: Menjaga fokus dalam tekanan tinggi, menenangkan situasi, dan mengubah hambatan menjadi momentum hasil. | I20: 2 | K20: 2 | M20: =I20-K20 -> 0 | N20: {=_xlfn.IFS( M20>=2, "Major Positive Gap", M20>=1, "Minor Positive Gap", M20>=0, "No Gap", M20>=-1, "Minor Negative Gap", M20<=-2, "Major Negative Gap" )} -> No Gap | O20: {=_xlfn.SWITCH(N20, "No Gap","persepsi diri Selaras dengan penilaian Atasan", "Minor Positive Gap","Self-assessment sedikit lebih tinggi dari superior assessment", "Major Positive Gap","Self-assessment jauh lebih tinggi dari perilaku yang tampak menurut atasan", "Minor Negative Gap","Self-assessment sedikit lebih rendah dari superior assessment", "Major Negative Gap","Self-assessment jauh lebih rendah dari perilaku yang tampak menurut atasan", "" )} -> persepsi diri Selaras dengan penilaian Atasan | P20: {=_xlfn.SWITCH(N20, "No Gap","persepsi diri Selaras dengan perilaku yang ditunjukan", "Minor Positive Gap","Individu merasa sudah sangat baik, tetapi atasan melihat baru cukup baik", "Major Positive Gap","Ada potensi blind spot; perilaku belum terlihat sekuat persepsi diri", "Minor Negative Gap","Individu mungkin kurang percaya diri atau belum menyadari kekuatannya", "Major Negative Gap","Ada hidden strength; individu tidak menyadari bahwa perilakunya sudah terlihat kuat", "" )} -> persepsi diri Selaras dengan perilaku yang ditunjukan
A21: =A20+1 -> 9 | B21: Adapting Strategy When Needed (mengubah strategi untuk hasil lebih baik) | C21: Ketika strategi, rencana, atau cara kerja tidak lagi efektif, perilaku yang paling sering saya tunjukkan adalah… | D21: Bertahan pada cara lama meskipun hasilnya tidak signifikan atau tidak relevan. | E21: Mencoba strategi baru dengan ragu dan mudah kembali ke cara lama. | F21: Menyesuaikan strategi ketika ada arahan, data, atau saran dari pihak lain. | G21: Menyesuaikan strategi, prioritas, atau pendekatan secara mandiri demi hasil yang lebih baik. | H21: Merancang strategi baru yang meningkatkan hasil dan memperbaiki proses secara lebih luas. | I21: 3 | K21: 5 | M21: =I21-K21 -> -2 | N21: {=_xlfn.IFS( M21>=2, "Major Positive Gap", M21>=1, "Minor Positive Gap", M21>=0, "No Gap", M21>=-1, "Minor Negative Gap", M21<=-2, "Major Negative Gap" )} -> Major Negative Gap | O21: {=_xlfn.SWITCH(N21, "No Gap","persepsi diri Selaras dengan penilaian Atasan", "Minor Positive Gap","Self-assessment sedikit lebih tinggi dari superior assessment", "Major Positive Gap","Self-assessment jauh lebih tinggi dari perilaku yang tampak menurut atasan", "Minor Negative Gap","Self-assessment sedikit lebih rendah dari superior assessment", "Major Negative Gap","Self-assessment jauh lebih rendah dari perilaku yang tampak menurut atasan", "" )} -> Self-assessment jauh lebih rendah dari perilaku yang tampak menurut atasan | P21: {=_xlfn.SWITCH(N21, "No Gap","persepsi diri Selaras dengan perilaku yang ditunjukan", "Minor Positive Gap","Individu merasa sudah sangat baik, tetapi atasan melihat baru cukup baik", "Major Positive Gap","Ada potensi blind spot; perilaku belum terlihat sekuat persepsi diri", "Minor Negative Gap","Individu mungkin kurang percaya diri atau belum menyadari kekuatannya", "Major Negative Gap","Ada hidden strength; individu tidak menyadari bahwa perilakunya sudah terlihat kuat", "" )} -> Ada hidden strength; individu tidak menyadari bahwa perilakunya sudah terlihat kuat
A22: =A21+1 -> 10 | B22: Resource Planning & Contingency (merencanakan sumber daya & rencana cadangan) | C22: Ketika menyusun rencana kerja yang membutuhkan orang, waktu, biaya, atau peralatan, perilaku yang paling sering saya tunjukkan adalah… | D22: Menyusun rencana berdasarkan target, dan menangani kebutuhan sumber daya saat pelaksanaan berjalan. | E22: Memperkirakan kebutuhan sumber daya secara garis besar. | F22: Menghitung kebutuhan orang, waktu, dan biaya secara rinci sebelum pelaksanaan dimulai. | G22: Mengalokasikan sumber daya sesuai prioritas dan mengantisipasi kendala yang mungkin muncul. | H22: Menyiapkan rencana cadangan untuk kendala yang paling mungkin terjadi, sehingga pekerjaan tetap berjalan. | I22: 1 | K22: 4 | M22: =I22-K22 -> -3 | N22: {=_xlfn.IFS( M22>=2, "Major Positive Gap", M22>=1, "Minor Positive Gap", M22>=0, "No Gap", M22>=-1, "Minor Negative Gap", M22<=-2, "Major Negative Gap" )} -> Major Negative Gap | O22: {=_xlfn.SWITCH(N22, "No Gap","persepsi diri Selaras dengan penilaian Atasan", "Minor Positive Gap","Self-assessment sedikit lebih tinggi dari superior assessment", "Major Positive Gap","Self-assessment jauh lebih tinggi dari perilaku yang tampak menurut atasan", "Minor Negative Gap","Self-assessment sedikit lebih rendah dari superior assessment", "Major Negative Gap","Self-assessment jauh lebih rendah dari perilaku yang tampak menurut atasan", "" )} -> Self-assessment jauh lebih rendah dari perilaku yang tampak menurut atasan | P22: {=_xlfn.SWITCH(N22, "No Gap","persepsi diri Selaras dengan perilaku yang ditunjukan", "Minor Positive Gap","Individu merasa sudah sangat baik, tetapi atasan melihat baru cukup baik", "Major Positive Gap","Ada potensi blind spot; perilaku belum terlihat sekuat persepsi diri", "Minor Negative Gap","Individu mungkin kurang percaya diri atau belum menyadari kekuatannya", "Major Negative Gap","Ada hidden strength; individu tidak menyadari bahwa perilakunya sudah terlihat kuat", "" )} -> Ada hidden strength; individu tidak menyadari bahwa perilakunya sudah terlihat kuat
A23: =A22+1 -> 11 | B23: Agile Problem-Solving Under Pressure (memecahkan masalah di bawah tekanan) | C23: Ketika menghadapi rintangan, krisis, atau masalah mendesak di bawah tekanan, perilaku yang paling sering saya tunjukkan adalah… | D23: Memerlukan waktu untuk menentukan langkah dan menunggu arahan sebelum bertindak. | E23: Menerapkan solusi sederhana yang sudah saya ketahui. | F23: Menyusun satu hingga dua alternatif solusi dan mencoba menerapkannya. | G23: Mengeksplorasi beberapa solusi dan cepat mengubah arah ketika kondisi berubah. | H23: Mengubah situasi krisis menjadi peluang perbaikan atau inovasi. | I23: 4 | K23: 2 | M23: =I23-K23 -> 2 | N23: {=_xlfn.IFS( M23>=2, "Major Positive Gap", M23>=1, "Minor Positive Gap", M23>=0, "No Gap", M23>=-1, "Minor Negative Gap", M23<=-2, "Major Negative Gap" )} -> Major Positive Gap | O23: {=_xlfn.SWITCH(N23, "No Gap","persepsi diri Selaras dengan penilaian Atasan", "Minor Positive Gap","Self-assessment sedikit lebih tinggi dari superior assessment", "Major Positive Gap","Self-assessment jauh lebih tinggi dari perilaku yang tampak menurut atasan", "Minor Negative Gap","Self-assessment sedikit lebih rendah dari superior assessment", "Major Negative Gap","Self-assessment jauh lebih rendah dari perilaku yang tampak menurut atasan", "" )} -> Self-assessment jauh lebih tinggi dari perilaku yang tampak menurut atasan | P23: {=_xlfn.SWITCH(N23, "No Gap","persepsi diri Selaras dengan perilaku yang ditunjukan", "Minor Positive Gap","Individu merasa sudah sangat baik, tetapi atasan melihat baru cukup baik", "Major Positive Gap","Ada potensi blind spot; perilaku belum terlihat sekuat persepsi diri", "Minor Negative Gap","Individu mungkin kurang percaya diri atau belum menyadari kekuatannya", "Major Negative Gap","Ada hidden strength; individu tidak menyadari bahwa perilakunya sudah terlihat kuat", "" )} -> Ada potensi blind spot; perilaku belum terlihat sekuat persepsi diri
A24: =A23+1 -> 12 | B24: Drive for High Performance (dorongan berkinerja tinggi) | C24: Ketika menetapkan standar kinerja dan mendorong pencapaian hasil terbaik, perilaku yang paling sering saya tunjukkan adalah… | D24: Bekerja sesuai ekspektasi minimum yang ditetapkan. | E24: Termotivasi mencapai hasil baik dengan adanya dorongan atau pengawasan. | F24: Memiliki motivasi yang stabil untuk mencapai hasil sesuai target. | G24: Mendorong diri dan tim mencapai hasil optimal dan standar tinggi secara konsisten. | H24: Membangun standar, sistem, dan kebiasaan kerja berkinerja tinggi yang bertahan dalam jangka panjang. | I24: 5 | K24: 2 | M24: =I24-K24 -> 3 | N24: {=_xlfn.IFS( M24>=2, "Major Positive Gap", M24>=1, "Minor Positive Gap", M24>=0, "No Gap", M24>=-1, "Minor Negative Gap", M24<=-2, "Major Negative Gap" )} -> Major Positive Gap | O24: {=_xlfn.SWITCH(N24, "No Gap","persepsi diri Selaras dengan penilaian Atasan", "Minor Positive Gap","Self-assessment sedikit lebih tinggi dari superior assessment", "Major Positive Gap","Self-assessment jauh lebih tinggi dari perilaku yang tampak menurut atasan", "Minor Negative Gap","Self-assessment sedikit lebih rendah dari superior assessment", "Major Negative Gap","Self-assessment jauh lebih rendah dari perilaku yang tampak menurut atasan", "" )} -> Self-assessment jauh lebih tinggi dari perilaku yang tampak menurut atasan | P24: {=_xlfn.SWITCH(N24, "No Gap","persepsi diri Selaras dengan perilaku yang ditunjukan", "Minor Positive Gap","Individu merasa sudah sangat baik, tetapi atasan melihat baru cukup baik", "Major Positive Gap","Ada potensi blind spot; perilaku belum terlihat sekuat persepsi diri", "Minor Negative Gap","Individu mungkin kurang percaya diri atau belum menyadari kekuatannya", "Major Negative Gap","Ada hidden strength; individu tidak menyadari bahwa perilakunya sudah terlihat kuat", "" )} -> Ada potensi blind spot; perilaku belum terlihat sekuat persepsi diri
A25: AVERAGE SCORE | I25: =AVERAGE(I13:J24) -> 3 | J25: =AVERAGE(J13:K24) -> 3.4166667 | K25: =AVERAGE(K13:L24) -> 3.4166667 | M25: =I25-K25 -> -0.41666667 | N25: {=_xlfn.IFS( VALUE(M25) >= 1, "Major Positive Gap", VALUE(M25) >= 0.5, "Minor Positive Gap", VALUE(M25) >= -0.49, "Aligned", VALUE(M25) >= -0.99, "Minor Negative Gap", VALUE(M25) <= -1, "Major Negative Gap" )} -> Aligned | O25: {=_xlfn.SWITCH(N25, "Aligned","Aligned Perception", "Minor Positive Gap","Slight Overestimation", "Major Positive Gap","Significant Overestimation / Potential Blind Spot", "Minor Negative Gap","Slight Underestimation", "Major Negative Gap","Significant Underestimation / Hidden Strength", "" )} -> Aligned Perception
A29: No | B29: Indikator | C29: Pernyataan Situasi | D29: Level 1 (Rendah) | E29: Level 2 (Cukup) | F29: Level 3 (Baik) | G29: Level 4 (Sangat Baik) | H29: Level 5 (Luar Biasa)
A30: 1 | B30: Task Completion Quality (menyelesaikan tugas dengan baik) | C30: Ketika menyelesaikan tugas atau tanggung jawab kerja, perilaku yang paling sering ditunjukkan adalah… | D30: Sering tidak menyelesaikan tugas sesuai standar, tenggat waktu, atau ekspektasi. | E30: Menyelesaikan tugas, tetapi kualitas/ketepatan waktu belum konsisten. | F30: Menyelesaikan tugas dengan kualitas cukup baik, stabil, dan sesuai standar. | G30: Konsisten menghasilkan pekerjaan berkualitas tinggi, tepat waktu, dan dapat diandalkan. | H30: Menghasilkan output melampaui ekspektasi, memberi nilai tambah, dan menjadi contoh standar kualitas.
A31: 2 | B31: Action-Oriented & Takes Initiative (proaktif bertindak) | C31: Ketika melihat peluang perbaikan, masalah, atau kebutuhan tindakan dalam pekerjaan, perilaku yang paling sering ditunjukkan adalah… | D31: Menunggu instruksi jelas sebelum bertindak. | E31: Mengidentifikasi peluang/masalah, tetapi masih menunggu persetujuan atau dorongan. | F31: Mengambil inisiatif menangani masalah dalam area tanggung jawab. | G31: Aktif menciptakan peluang perbaikan dan mengantisipasi masalah sebelum berdampak. | H31: Mengambil inisiatif yang menciptakan perubahan positif dan menggerakkan orang lain.
A32: 3 | B32: Driving for impact (fokus pada hasil kerja) | C32: Ketika menilai keberhasilan kerja, perilaku yang paling sering ditunjukkan adalah… | D32: Mengukur keberhasilan dari aktivitas yang dilakukan, bukan hasil/dampak. | E32: Fokus menyelesaikan pekerjaan sesuai prosedur, tetapi belum memastikan efektivitas hasil. | F32: Memahami tujuan akhir pekerjaan dan bertanggung jawab terhadap pencapaiannya. | G32: Mengidentifikasi hambatan, menyesuaikan proses, menyusun rencana, dan menggunakan metrik keberhasilan. | H32: Berorientasi pada dampak nyata dan memastikan hasil kerja memberi nilai bagi tim, pelanggan, fungsi, atau organisasi.
A33: 4 | B33: Tenacity & Strategic Persistence (menjaga komitmen di tengah tantangan) | C33: Ketika menghadapi tantangan berat, hambatan, atau kegagalan dalam mencapai target, perilaku yang paling sering ditunjukkan adalah… | D33: Mudah kehilangan komitmen atau menyerah ketika menghadapi tantangan. | E33: Tetap berupaya, tetapi membutuhkan dorongan eksternal saat upaya awal gagal. | F33: Berusaha menyelesaikan tugas dan meminta bantuan ketika menghadapi hambatan sulit. | G33: Menjaga energi, komitmen, dan ketekunan tanpa mudah frustrasi. | H33: Gigih menghadapi tantangan berat dengan mencari solusi baru dan tetap menjaga arah hasil.
A34: 5 | B34: Learning from Outcomes (belajar dari hasil & kesalahan tim) | C34: Setelah mengalami keberhasilan, kegagalan, atau hasil kerja yang belum sesuai harapan, perilaku yang paling sering ditunjukkan adalah… | D34: Jarang merefleksikan hasil sehingga cenderung mengulang kesalahan. | E34: Sesekali mengambil pelajaran, tetapi belum konsisten menggunakannya untuk perbaikan. | F34: Cukup sering mengevaluasi hasil kerja dan mengambil pelajaran. | G34: Aktif belajar dari hasil dan mengubahnya menjadi tindakan perbaikan. | H34: Konsisten mengubah pembelajaran menjadi peningkatan kinerja nyata bagi diri, tim, atau proses kerja.
A35: 6 | B35: Deciding with Incomplete Data (mengambil keputusan dengan data/informasi terbatas) | C35: Ketika harus mengambil keputusan dalam situasi baru, tidak pasti, atau dengan informasi belum lengkap, perilaku yang paling sering ditunjukkan adalah… | D35: Menghindari atau menunda keputusan ketika informasi belum lengkap. | E35: Cenderung menunggu informasi lebih lengkap sebelum mengambil keputusan. | F35: Membuat keputusan dengan opsi paling logis berdasarkan informasi terbatas. | G35: Membuat keputusan melalui analisis opsi, skenario, risiko, dan konsekuensi. | H35: Membuat keputusan berkualitas dengan kerangka berpikir baru, pembelajaran sebelumnya, dan pertimbangan dampak jangka panjang.
A36: 7 | B36: Focus Under Pressure (tetap fokus dalam tekanan tinggi) | C36: Ketika menghadapi tekanan, hambatan, tenggat waktu ketat, atau tuntutan kerja tinggi, perilaku yang paling sering ditunjukkan adalah… | D36: Mudah kehilangan fokus ketika tekanan atau hambatan muncul. | E36: Berusaha tetap fokus, tetapi sering terganggu saat tekanan meningkat. | F36: Cukup mampu menjaga fokus dan menyelesaikan pekerjaan dengan dukungan tertentu. | G36: Tetap fokus, produktif, dan menjaga kualitas kerja dalam tekanan berat. | H36: Menjaga fokus dalam tekanan tinggi, menenangkan situasi, dan mengubah hambatan menjadi momentum hasil.
A37: 8 | B37: Adapting Strategy When Needed (mengubah strategi untuk hasil lebih baik) | C37: Ketika strategi, rencana, atau cara kerja tidak lagi efektif, perilaku yang paling sering ditunjukkan adalah… | D37: Bertahan pada cara lama meskipun hasilnya tidak signifikan atau tidak relevan. | E37: Mencoba strategi baru dengan ragu-ragu dan mudah kembali ke cara lama. | F37: Menyesuaikan strategi ketika ada arahan, data, atau saran. | G37: Mandiri menyesuaikan strategi, prioritas, atau pendekatan untuk hasil lebih baik. | H37: Proaktif menciptakan strategi baru yang meningkatkan hasil, memperbaiki proses, dan berdampak luas.
A38: 9 | B38: Agile Problem-Solving Under Pressure (rencana di tengah ketidakpastian) | C38: Ketika menghadapi rintangan, krisis, atau masalah mendesak di bawah tekanan, perilaku yang paling sering ditunjukkan adalah… | D38: Bingung, panik, atau merasa masalah tidak mungkin diselesaikan. | E38: Mencoba solusi sederhana yang diketahui, tetapi cepat meminta bantuan saat tekanan meningkat. | F38: Menghasilkan 1–2 alternatif solusi dan mencoba menerapkannya. | G38: Mengeksplorasi solusi, melakukan brainstorming, dan cepat mengubah arah solusi jika kondisi berubah. | H38: Mengubah krisis menjadi peluang perbaikan, inovasi, dan peningkatan kinerja.
A39: 10 | B39: Drive for High Performance (sistem perencanaan berkinerja tinggi) | C39: Ketika menetapkan standar kinerja dan mendorong pencapaian hasil terbaik, perilaku yang paling sering ditunjukkan adalah… | D39: Kurang menunjukkan dorongan mencapai hasil tinggi atau bekerja sesuai minimum ekspektasi. | E39: Termotivasi mencapai hasil baik, tetapi masih membutuhkan dorongan atau pengawasan. | F39: Memiliki motivasi stabil untuk mencapai hasil kerja baik dan sesuai target. | G39: Konsisten mendorong diri/tim/fungsi untuk mencapai hasil optimal dan standar tinggi. | H39: Membangun standar, sistem, dan budaya kerja berkinerja tinggi secara berkelanjutan.

Sheet self awareness
B2: =Identitas!B2 -> Nama | C2: =Identitas!D2 -> 0
B3: =Identitas!B3 -> Nama Atasan yang menilai | C3: =Identitas!D3 -> 0
B4: =Identitas!B4 -> Level Saat Ini | C4: =Identitas!D4 -> Officer
B5: =Identitas!B5 -> Level Tujuan | C5: =Identitas!D5 -> Analyst
B6: =Identitas!B6 -> Tanggal Assesment | C6: =Identitas!D6 -> 0
B7: =Identitas!B7 -> Unit | C7: =Identitas!D7 -> 0
B8: =Identitas!B8 -> Departemen | C8: =Identitas!D8 -> 0
B9: =Identitas!B9 -> Divisi | C9: =Identitas!D9 -> 0
B10: =Identitas!B10 -> Direktorat | C10: =Identitas!D10 -> 0
A12: No | B12: Indikator | C12: Pernyataan Situasi | D12: Level 1 (Rendah) | E12: Level 2 (Cukup) | F12: Level 3 (Baik) | G12: Level 4 (Sangat Baik) | H12: Level 5 (Luar Biasa) | I12: Rating (1-5) self | J12: Komentar / Contoh Perilaku | K12: Rating (1-5) superior | L12: Komentar / Contoh Perilaku | M12: Self Awareness GAP Score Self - Sup | N12: Gap | O12: Keterangan | P12: Intepretasi
A13: 1 | B13: Openness to Criticism (menerima kritik) | C13: Ketika menerima kritik, masukan korektif, atau pandangan yang kurang menyenangkan, perilaku yang paling sering ditunjukkan adalah… (Fokus indikator: reaksi emosional awal saat menerima kritik.) | D13: Menjelaskan alasan mengapa kritik tersebut kurang tepat. | E13: Menerima kritik meski merasa tidak nyaman, dan belum menindaklanjutinya. | F13: Menerima kritik dengan terbuka dan memahami pesan utamanya. | G13: Meminta klarifikasi atas kritik yang diterima dan menggunakannya untuk memperbaiki diri. | H13: Mencari kritik secara aktif dan menjadikannya bahan pembelajaran berkelanjutan. | I13: 4 | K13: 2 | M13: =I13-K13 -> 2 | N13: {=_xlfn.IFS( M13>=2, "Major Positive Gap", M13>=1, "Minor Positive Gap", M13>=0, "No Gap", M13>=-1, "Minor Negative Gap", M13<=-2, "Major Negative Gap" )} -> Major Positive Gap | O13: {=_xlfn.SWITCH(N13, "No Gap","persepsi diri Selaras dengan penilaian Atasan", "Minor Positive Gap","Self-assessment sedikit lebih tinggi dari superior assessment", "Major Positive Gap","Self-assessment jauh lebih tinggi dari perilaku yang tampak menurut atasan", "Minor Negative Gap","Self-assessment sedikit lebih rendah dari superior assessment", "Major Negative Gap","Self-assessment jauh lebih rendah dari perilaku yang tampak menurut atasan", "" )} -> Self-assessment jauh lebih tinggi dari perilaku yang tampak menurut atasan | P13: {=_xlfn.SWITCH(N13, "No Gap","persepsi diri Selaras dengan perilaku yang ditunjukan", "Minor Positive Gap","Individu merasa sudah sangat baik, tetapi atasan melihat baru cukup baik", "Major Positive Gap","Ada potensi blind spot; perilaku belum terlihat sekuat persepsi diri", "Minor Negative Gap","Individu mungkin kurang percaya diri atau belum menyadari kekuatannya", "Major Negative Gap","Ada hidden strength; individu tidak menyadari bahwa perilakunya sudah terlihat kuat", "" )} -> Ada potensi blind spot; perilaku belum terlihat sekuat persepsi diri
A14: 2 | B14: Admitting Mistakes (mengakui kesalahan) | C14: Ketika melakukan kesalahan atau hasil kerja tidak sesuai harapan, perilaku yang paling sering saya tunjukkan adalah… | D14: Menjelaskan faktor situasi atau pihak lain yang memengaruhi hasil tersebut. | E14: Mengakui kesalahan yang berdampak kecil. | F14: Mengakui kesalahan dan menerima konsekuensinya pada sebagian besar situasi. | G14: Mengakui kesalahan, mengambil tanggung jawab, dan menunjukkan perbaikan. | H14: Membicarakan kesalahan secara terbuka sebagai pembelajaran bagi diri sendiri dan orang lain. | I14: 4 | K14: 5 | M14: =I14-K14 -> -1 | N14: {=_xlfn.IFS( M14>=2, "Major Positive Gap", M14>=1, "Minor Positive Gap", M14>=0, "No Gap", M14>=-1, "Minor Negative Gap", M14<=-2, "Major Negative Gap" )} -> Minor Negative Gap | O14: {=_xlfn.SWITCH(N14, "No Gap","persepsi diri Selaras dengan penilaian Atasan", "Minor Positive Gap","Self-assessment sedikit lebih tinggi dari superior assessment", "Major Positive Gap","Self-assessment jauh lebih tinggi dari perilaku yang tampak menurut atasan", "Minor Negative Gap","Self-assessment sedikit lebih rendah dari superior assessment", "Major Negative Gap","Self-assessment jauh lebih rendah dari perilaku yang tampak menurut atasan", "" )} -> Self-assessment sedikit lebih rendah dari superior assessment | P14: {=_xlfn.SWITCH(N14, "No Gap","persepsi diri Selaras dengan perilaku yang ditunjukan", "Minor Positive Gap","Individu merasa sudah sangat baik, tetapi atasan melihat baru cukup baik", "Major Positive Gap","Ada potensi blind spot; perilaku belum terlihat sekuat persepsi diri", "Minor Negative Gap","Individu mungkin kurang percaya diri atau belum menyadari kekuatannya", "Major Negative Gap","Ada hidden strength; individu tidak menyadari bahwa perilakunya sudah terlihat kuat", "" )} -> Individu mungkin kurang percaya diri atau belum menyadari kekuatannya
A15: 3 | B15: Seeking Feedback on Performance (mencari feedback) | C15: Ketika ingin memahami kualitas kinerja atau perilaku kerja saya, perilaku yang paling sering saya tunjukkan adalah… (Fokus indikator: inisiatif meminta, bukan cara menerima) | D15: Menilai kinerja saya berdasarkan penilaian saya sendiri. | E15: Meminta pendapat orang lain pada situasi tertentu atau ketika diminta. | F15: Meminta masukan cukup sering untuk meningkatkan kinerja. | G15: Meminta feedback secara rutin dan spesifik dari atasan, rekan kerja, maupun pihak terkait. | H15: Mencari feedback dari berbagai sumber secara proaktif untuk mempercepat perkembangan diri. | I15: 4 | K15: 3 | M15: =I15-K15 -> 1 | N15: {=_xlfn.IFS( M15>=2, "Major Positive Gap", M15>=1, "Minor Positive Gap", M15>=0, "No Gap", M15>=-1, "Minor Negative Gap", M15<=-2, "Major Negative Gap" )} -> Minor Positive Gap | O15: {=_xlfn.SWITCH(N15, "No Gap","persepsi diri Selaras dengan penilaian Atasan", "Minor Positive Gap","Self-assessment sedikit lebih tinggi dari superior assessment", "Major Positive Gap","Self-assessment jauh lebih tinggi dari perilaku yang tampak menurut atasan", "Minor Negative Gap","Self-assessment sedikit lebih rendah dari superior assessment", "Major Negative Gap","Self-assessment jauh lebih rendah dari perilaku yang tampak menurut atasan", "" )} -> Self-assessment sedikit lebih tinggi dari superior assessment | P15: {=_xlfn.SWITCH(N15, "No Gap","persepsi diri Selaras dengan perilaku yang ditunjukan", "Minor Positive Gap","Individu merasa sudah sangat baik, tetapi atasan melihat baru cukup baik", "Major Positive Gap","Ada potensi blind spot; perilaku belum terlihat sekuat persepsi diri", "Minor Negative Gap","Individu mungkin kurang percaya diri atau belum menyadari kekuatannya", "Major Negative Gap","Ada hidden strength; individu tidak menyadari bahwa perilakunya sudah terlihat kuat", "" )} -> Individu merasa sudah sangat baik, tetapi atasan melihat baru cukup baik
A16: 4 | B16: Understanding Strengths & Weaknesses (memahami kekuatan & kelemahan) | C16: Dalam memahami kekuatan dan area pengembangan diri, perilaku yang paling sering saya tunjukkan adalah… | D16: Belum melakukan evaluasi terhadap kekuatan dan kelemahan diri. | E16: Memikirkan kemampuan diri ketika diminta dalam konteks formal. | F16: Merefleksikan kekuatan dan kelemahan setelah pengalaman penting. | G16: Mengevaluasi perkembangan kemampuan diri secara rutin dan menyesuaikan tindakan. | H16: Menjadikan pemahaman atas kekuatan dan kelemahan sebagai dasar keputusan, pemilihan peran, dan pengembangan diri. | I16: 4 | K16: 3 | M16: =I16-K16 -> 1 | N16: {=_xlfn.IFS( M16>=2, "Major Positive Gap", M16>=1, "Minor Positive Gap", M16>=0, "No Gap", M16>=-1, "Minor Negative Gap", M16<=-2, "Major Negative Gap" )} -> Minor Positive Gap | O16: {=_xlfn.SWITCH(N16, "No Gap","persepsi diri Selaras dengan penilaian Atasan", "Minor Positive Gap","Self-assessment sedikit lebih tinggi dari superior assessment", "Major Positive Gap","Self-assessment jauh lebih tinggi dari perilaku yang tampak menurut atasan", "Minor Negative Gap","Self-assessment sedikit lebih rendah dari superior assessment", "Major Negative Gap","Self-assessment jauh lebih rendah dari perilaku yang tampak menurut atasan", "" )} -> Self-assessment sedikit lebih tinggi dari superior assessment | P16: {=_xlfn.SWITCH(N16, "No Gap","persepsi diri Selaras dengan perilaku yang ditunjukan", "Minor Positive Gap","Individu merasa sudah sangat baik, tetapi atasan melihat baru cukup baik", "Major Positive Gap","Ada potensi blind spot; perilaku belum terlihat sekuat persepsi diri", "Minor Negative Gap","Individu mungkin kurang percaya diri atau belum menyadari kekuatannya", "Major Negative Gap","Ada hidden strength; individu tidak menyadari bahwa perilakunya sudah terlihat kuat", "" )} -> Individu merasa sudah sangat baik, tetapi atasan melihat baru cukup baik
A17: 5 | B17: Reflective Practices (melakukan refleksi diri) | C17: Setelah mengalami pengalaman kerja, keberhasilan, kegagalan, atau situasi penting, perilaku yang paling sering saya tunjukkan adalah… | D17: Melanjutkan aktivitas berikutnya tanpa meninjau pengalaman sebelumnya. | E17: Melakukan evaluasi diri sesekali tanpa tindak lanjut tertentu. | F17: Melakukan refleksi setelah pengalaman penting dan mengambil pelajaran darinya. | G17: Mengevaluasi pengalaman secara konsisten dan menggunakannya untuk meningkatkan kinerja. | H17: Mengubah pengalaman menjadi pembelajaran yang mempercepat perkembangan diri secara nyata. | I17: 5 | K17: 5 | M17: =I17-K17 -> 0 | N17: {=_xlfn.IFS( M17>=2, "Major Positive Gap", M17>=1, "Minor Positive Gap", M17>=0, "No Gap", M17>=-1, "Minor Negative Gap", M17<=-2, "Major Negative Gap" )} -> No Gap | O17: {=_xlfn.SWITCH(N17, "No Gap","persepsi diri Selaras dengan penilaian Atasan", "Minor Positive Gap","Self-assessment sedikit lebih tinggi dari superior assessment", "Major Positive Gap","Self-assessment jauh lebih tinggi dari perilaku yang tampak menurut atasan", "Minor Negative Gap","Self-assessment sedikit lebih rendah dari superior assessment", "Major Negative Gap","Self-assessment jauh lebih rendah dari perilaku yang tampak menurut atasan", "" )} -> persepsi diri Selaras dengan penilaian Atasan | P17: {=_xlfn.SWITCH(N17, "No Gap","persepsi diri Selaras dengan perilaku yang ditunjukan", "Minor Positive Gap","Individu merasa sudah sangat baik, tetapi atasan melihat baru cukup baik", "Major Positive Gap","Ada potensi blind spot; perilaku belum terlihat sekuat persepsi diri", "Minor Negative Gap","Individu mungkin kurang percaya diri atau belum menyadari kekuatannya", "Major Negative Gap","Ada hidden strength; individu tidak menyadari bahwa perilakunya sudah terlihat kuat", "" )} -> persepsi diri Selaras dengan perilaku yang ditunjukan
A18: 6 | B18: Proactive Self-Development for Adaptation (aktif mengembangkan diri) | C18: Ketika menghadapi tuntutan baru, perubahan peran, atau kebutuhan kompetensi baru, perilaku yang paling sering saya tunjukkan adalah… | D18: Memandang pengembangan diri sebagai tanggung jawab perusahaan atau atasan. | E18: Menyusun rencana pengembangan diri ketika diminta. | F18: Mencari sendiri pengetahuan yang relevan dengan pekerjaan. | G18: Menyusun rencana pengembangan, mencari keterampilan baru, dan menerapkannya dalam pekerjaan. | H18: Mengembangkan pengetahuan, keterampilan, dan kematangan pribadi secara konsisten untuk tuntutan yang lebih kompleks. | I18: 3 | K18: 5 | M18: =I18-K18 -> -2 | N18: {=_xlfn.IFS( M18>=2, "Major Positive Gap", M18>=1, "Minor Positive Gap", M18>=0, "No Gap", M18>=-1, "Minor Negative Gap", M18<=-2, "Major Negative Gap" )} -> Major Negative Gap | O18: {=_xlfn.SWITCH(N18, "No Gap","persepsi diri Selaras dengan penilaian Atasan", "Minor Positive Gap","Self-assessment sedikit lebih tinggi dari superior assessment", "Major Positive Gap","Self-assessment jauh lebih tinggi dari perilaku yang tampak menurut atasan", "Minor Negative Gap","Self-assessment sedikit lebih rendah dari superior assessment", "Major Negative Gap","Self-assessment jauh lebih rendah dari perilaku yang tampak menurut atasan", "" )} -> Self-assessment jauh lebih rendah dari perilaku yang tampak menurut atasan | P18: {=_xlfn.SWITCH(N18, "No Gap","persepsi diri Selaras dengan perilaku yang ditunjukan", "Minor Positive Gap","Individu merasa sudah sangat baik, tetapi atasan melihat baru cukup baik", "Major Positive Gap","Ada potensi blind spot; perilaku belum terlihat sekuat persepsi diri", "Minor Negative Gap","Individu mungkin kurang percaya diri atau belum menyadari kekuatannya", "Major Negative Gap","Ada hidden strength; individu tidak menyadari bahwa perilakunya sudah terlihat kuat", "" )} -> Ada hidden strength; individu tidak menyadari bahwa perilakunya sudah terlihat kuat
A19: 7 | B19: Objective Self-Assessment (menilai diri secara objektif) | C19: Ketika menilai kemampuan, kinerja, atau kesiapan diri, perilaku yang paling sering saya tunjukkan adalah… | D19: Menilai diri berdasarkan persepsi pribadi saya. | E19: Berusaha menilai secara objektif, meski masih dipengaruhi asumsi pribadi. | F19: Menilai diri dengan mempertimbangkan beberapa fakta atau masukan | G19: Menilai diri secara realistis berdasarkan bukti hasil kerja dan feedback. | H19: Mengevaluasi kemampuan diri berdasarkan data, feedback, dan standar peran yang lebih tinggi. | I19: 5 | K19: 5 | M19: =I19-K19 -> 0 | N19: {=_xlfn.IFS( M19>=2, "Major Positive Gap", M19>=1, "Minor Positive Gap", M19>=0, "No Gap", M19>=-1, "Minor Negative Gap", M19<=-2, "Major Negative Gap" )} -> No Gap | O19: {=_xlfn.SWITCH(N19, "No Gap","persepsi diri Selaras dengan penilaian Atasan", "Minor Positive Gap","Self-assessment sedikit lebih tinggi dari superior assessment", "Major Positive Gap","Self-assessment jauh lebih tinggi dari perilaku yang tampak menurut atasan", "Minor Negative Gap","Self-assessment sedikit lebih rendah dari superior assessment", "Major Negative Gap","Self-assessment jauh lebih rendah dari perilaku yang tampak menurut atasan", "" )} -> persepsi diri Selaras dengan penilaian Atasan | P19: {=_xlfn.SWITCH(N19, "No Gap","persepsi diri Selaras dengan perilaku yang ditunjukan", "Minor Positive Gap","Individu merasa sudah sangat baik, tetapi atasan melihat baru cukup baik", "Major Positive Gap","Ada potensi blind spot; perilaku belum terlihat sekuat persepsi diri", "Minor Negative Gap","Individu mungkin kurang percaya diri atau belum menyadari kekuatannya", "Major Negative Gap","Ada hidden strength; individu tidak menyadari bahwa perilakunya sudah terlihat kuat", "" )} -> persepsi diri Selaras dengan perilaku yang ditunjukan
A20: 8 | B20: Awareness of Impact on Others (memahami dampak perilaku) | C20: Ketika perilaku, keputusan, atau cara komunikasi saya memengaruhi orang lain, perilaku yang paling sering saya tunjukkan adalah… | D20: Berfokus pada penyelesaian tugas tanpa memperhatikan dampaknya terhadap orang lain. | E20: Menyadari dampak perilaku saya, namun belum konsisten menyesuaikannya. | F20: Menyadari bahwa perilaku dan cara komunikasi saya memengaruhi orang lain. | G20: Memahami dampak perilaku saya dan menyesuaikan cara bertindak atau berkomunikasi. | H20: Mengelola dampak diri secara peka sehingga tercipta lingkungan kerja yang lebih sehat. | I20: 5 | K20: 2 | M20: =I20-K20 -> 3 | N20: {=_xlfn.IFS( M20>=2, "Major Positive Gap", M20>=1, "Minor Positive Gap", M20>=0, "No Gap", M20>=-1, "Minor Negative Gap", M20<=-2, "Major Negative Gap" )} -> Major Positive Gap | O20: {=_xlfn.SWITCH(N20, "No Gap","persepsi diri Selaras dengan penilaian Atasan", "Minor Positive Gap","Self-assessment sedikit lebih tinggi dari superior assessment", "Major Positive Gap","Self-assessment jauh lebih tinggi dari perilaku yang tampak menurut atasan", "Minor Negative Gap","Self-assessment sedikit lebih rendah dari superior assessment", "Major Negative Gap","Self-assessment jauh lebih rendah dari perilaku yang tampak menurut atasan", "" )} -> Self-assessment jauh lebih tinggi dari perilaku yang tampak menurut atasan | P20: {=_xlfn.SWITCH(N20, "No Gap","persepsi diri Selaras dengan perilaku yang ditunjukan", "Minor Positive Gap","Individu merasa sudah sangat baik, tetapi atasan melihat baru cukup baik", "Major Positive Gap","Ada potensi blind spot; perilaku belum terlihat sekuat persepsi diri", "Minor Negative Gap","Individu mungkin kurang percaya diri atau belum menyadari kekuatannya", "Major Negative Gap","Ada hidden strength; individu tidak menyadari bahwa perilakunya sudah terlihat kuat", "" )} -> Ada potensi blind spot; perilaku belum terlihat sekuat persepsi diri
A21: 9 | B21: Managing Emotions Effectively (mengelola emosi) | C21: Ketika berada dalam situasi yang memicu emosi, tekanan, konflik, atau ketidaknyamanan, perilaku yang paling sering saya tunjukkan adalah… | D21: Merespons secara spontan mengikuti emosi yang muncul. | E21: Menyadari emosi saya setelah reaksi tersebut terjadi. | F21: Mengenali emosi yang muncul dan mulai memilih respons yang konstruktif. | G21: Mengelola emosi dengan baik dan menjaga respons tetap profesional. | H21: Menjaga kendali emosi, menenangkan diri dan orang lain, serta menjaga kualitas keputusan dalam tekanan tinggi. | I21: 4 | K21: 3 | M21: =I21-K21 -> 1 | N21: {=_xlfn.IFS( M21>=2, "Major Positive Gap", M21>=1, "Minor Positive Gap", M21>=0, "No Gap", M21>=-1, "Minor Negative Gap", M21<=-2, "Major Negative Gap" )} -> Minor Positive Gap | O21: {=_xlfn.SWITCH(N21, "No Gap","persepsi diri Selaras dengan penilaian Atasan", "Minor Positive Gap","Self-assessment sedikit lebih tinggi dari superior assessment", "Major Positive Gap","Self-assessment jauh lebih tinggi dari perilaku yang tampak menurut atasan", "Minor Negative Gap","Self-assessment sedikit lebih rendah dari superior assessment", "Major Negative Gap","Self-assessment jauh lebih rendah dari perilaku yang tampak menurut atasan", "" )} -> Self-assessment sedikit lebih tinggi dari superior assessment | P21: {=_xlfn.SWITCH(N21, "No Gap","persepsi diri Selaras dengan perilaku yang ditunjukan", "Minor Positive Gap","Individu merasa sudah sangat baik, tetapi atasan melihat baru cukup baik", "Major Positive Gap","Ada potensi blind spot; perilaku belum terlihat sekuat persepsi diri", "Minor Negative Gap","Individu mungkin kurang percaya diri atau belum menyadari kekuatannya", "Major Negative Gap","Ada hidden strength; individu tidak menyadari bahwa perilakunya sudah terlihat kuat", "" )} -> Individu merasa sudah sangat baik, tetapi atasan melihat baru cukup baik
A22: 10 | B22: Deep Pattern Recognition & Bias Awareness (refleksi diri mendalam & autentik) | C22: Dalam melakukan refleksi mendalam terhadap pola perilaku, keputusan, emosi, dan bias diri, perilaku yang paling sering ditunjukkan adalah… | D22: Memandang refleksi mendalam atas pola diri sebagai hal yang tidak diperlukan. | E22: Melakukan refleksi terbatas dengan fokus pada faktor di luar diri saya. | F22: Merefleksikan faktor eksternal, internal, dan respons emosional pada situasi tertentu. | G22: Menganalisis pola berulang dalam tindakan, keputusan, dan respons diri saya. | H22: Mengenali pola dan bias diri secara mendalam, memperkirakan reaksi pribadi, serta mengelolanya secara matang. | I22: 3 | K22: 3 | M22: =I22-K22 -> 0 | N22: {=_xlfn.IFS( M22>=2, "Major Positive Gap", M22>=1, "Minor Positive Gap", M22>=0, "No Gap", M22>=-1, "Minor Negative Gap", M22<=-2, "Major Negative Gap" )} -> No Gap | O22: {=_xlfn.SWITCH(N22, "No Gap","persepsi diri Selaras dengan penilaian Atasan", "Minor Positive Gap","Self-assessment sedikit lebih tinggi dari superior assessment", "Major Positive Gap","Self-assessment jauh lebih tinggi dari perilaku yang tampak menurut atasan", "Minor Negative Gap","Self-assessment sedikit lebih rendah dari superior assessment", "Major Negative Gap","Self-assessment jauh lebih rendah dari perilaku yang tampak menurut atasan", "" )} -> persepsi diri Selaras dengan penilaian Atasan | P22: {=_xlfn.SWITCH(N22, "No Gap","persepsi diri Selaras dengan perilaku yang ditunjukan", "Minor Positive Gap","Individu merasa sudah sangat baik, tetapi atasan melihat baru cukup baik", "Major Positive Gap","Ada potensi blind spot; perilaku belum terlihat sekuat persepsi diri", "Minor Negative Gap","Individu mungkin kurang percaya diri atau belum menyadari kekuatannya", "Major Negative Gap","Ada hidden strength; individu tidak menyadari bahwa perilakunya sudah terlihat kuat", "" )} -> persepsi diri Selaras dengan perilaku yang ditunjukan
A23: AVERAGE SCORE | I23: =AVERAGE(I13:J22) -> 4.1 | J23: =AVERAGE(J13:K22) -> 3.6 | K23: =AVERAGE(K13:L22) -> 3.6 | M23: =I23-K23 -> 0.5 | N23: {=_xlfn.IFS( VALUE(M23) >= 1, "Major Positive Gap", VALUE(M23) >= 0.5, "Minor Positive Gap", VALUE(M23) >= -0.49, "Aligned", VALUE(M23) >= -0.99, "Minor Negative Gap", VALUE(M23) <= -1, "Major Negative Gap" )} -> Minor Positive Gap | O23: {=_xlfn.SWITCH(N23, "Aligned","Aligned Perception", "Minor Positive Gap","Slight Overestimation", "Major Positive Gap","Significant Overestimation / Potential Blind Spot", "Minor Negative Gap","Slight Underestimation", "Major Negative Gap","Significant Underestimation / Hidden Strength", "" )} -> Slight Overestimation

Sheet Profile Summary
A2: =Identitas!B2 -> Nama | B2: =Identitas!D2 -> 0
A3: =Identitas!B3 -> Nama Atasan yang menilai | B3: =Identitas!D3 -> 0
A4: =Identitas!B4 -> Level Saat Ini | B4: =Identitas!D4 -> Officer
A5: =Identitas!B5 -> Level Tujuan | B5: =Identitas!D5 -> Analyst
A6: =Identitas!B6 -> Tanggal Assesment | B6: =Identitas!D6 -> 0
A7: =Identitas!B7 -> Unit | B7: =Identitas!D7 -> 0
A8: =Identitas!B8 -> Departemen | B8: =Identitas!D8 -> 0
A9: =Identitas!B9 -> Divisi | B9: =Identitas!D9 -> 0
A10: =Identitas!B10 -> Direktorat | B10: =Identitas!D10 -> 0
A12: A. PROFILE SUMMARY
A13: Dimensi | B13: Average Score (max 5) | C13: Performance Level | D13: Outstanding Strength (Score 5) | E13: Key Strength (Score 4) | F13: Developing Areas (Score 3) | G13: Focus for Improvement (Score 2) | H13: Priority for Development (Score 1) | I13: Outstanding Strength (Score 5) | J13: Key Strength (Score 4) | K13: Developing Areas (Score 3) | L13: Focus for Improvement (Score 2) | M13: Priority for Development (Score 1) | N13: %
A14: Mental Agility | B14: ='mental agility'!K23 -> 2.5 | C14: =IF(B14>=4.5,"Excellent",IF(B14>=4,"Strong",IF(B14>=3,"Meet","Needs Development"))) -> Needs Development | D14: {=_xlfn.TEXTJOIN(CHAR(10),TRUE,IF('mental agility'!K13:K22=5,"• "&'mental agility'!B13:B22,""))} | E14: {=_xlfn.TEXTJOIN(CHAR(10),TRUE,IF('mental agility'!K13:K22=4,"• "&'mental agility'!B13:B22,""))} -> • Analytical Thinking (memahami data & fakta dasar) • Intellectual Synthesis (menghubungkan berbagai informasi) • Breaking Patterned thinking (menciptakan solusi baru) | F14: {=_xlfn.TEXTJOIN(CHAR(10),TRUE,IF('mental agility'!K13:K22=3,"• "&'mental agility'!B13:B22,""))} -> • Root Cause Analysis (mencari penyebab masalah) | G14: {=_xlfn.TEXTJOIN(CHAR(10),TRUE,IF('mental agility'!K13:K22=2,"• "&'mental agility'!B13:B22,""))} -> • Critical Thinking & Inquisitiveness (mempertanyakan & mengevaluasi) • Integrating Diverse Perspective (keputusan dari berbagai sudut pandang) • Creative Exploration (mencari pendekatan baru) • Tolerance for Ambiguity (memimpin dalam uncertainty tinggi) | H14: {=_xlfn.TEXTJOIN(CHAR(10),TRUE,IF('mental agility'!K13:K22=1,"• "&'mental agility'!B13:B22,""))} -> • Explaining Complexity (menjelaskan hal kompleks secara sederhana) • Comfort with Ambiguity (tetap efektif di situasi tidak jelas) | I14: =LEN(D14)-LEN(SUBSTITUTE(D14,"•","")) -> 0 | J14: =LEN(E14)-LEN(SUBSTITUTE(E14,"•","")) -> 3 | K14: =LEN(F14)-LEN(SUBSTITUTE(F14,"•","")) -> 1 | L14: =LEN(G14)-LEN(SUBSTITUTE(G14,"•","")) -> 4 | M14: =LEN(H14)-LEN(SUBSTITUTE(H14,"•","")) -> 2 | N14: =(J14+I14)/(SUM(I14:M14)) -> 0.3
A15: People Agility | B15: ='people agility'!K29 -> 3.1333333 | C15: =IF(B15>=4.5,"Excellent",IF(B15>=4,"Strong",IF(B15>=3,"Meet","Needs Development"))) -> Meet | D15: {=_xlfn.TEXTJOIN(CHAR(10),TRUE,IF('people agility'!K13:K28=5,"• "&'people agility'!B13:B28,""))} -> • Collaboration with Diversity (Bekerja efektif dalam keberagaman) • Understanding Different Perspectives (Analisis multi-sudut pandang) • Setting Direction & Expectations (menetapkan arah & ekspektasi) | E15: {=_xlfn.TEXTJOIN(CHAR(10),TRUE,IF('people agility'!K13:K28=4,"• "&'people agility'!B13:B28,""))} -> • Valuing Diverse Opinions (Menghargai opini berbeda) • Conflict Navigation (menghadapi konflik secara konstruktif) • Delegating for Growth (mendelegasikan sebagai sarana pengembangan) | F15: {=_xlfn.TEXTJOIN(CHAR(10),TRUE,IF('people agility'!K13:K28=3,"• "&'people agility'!B13:B28,""))} -> • Listening for understanding (mendengarkan & memahami) • Recognizing Others' Potential (mengenali potensi orang lain) • Managing Challenging Stakeholder (relasi berkelanjutan dengan pihak sulit) • Adapting Leadership Style (menyesuaikan gaya kepemimpinan) | G15: {=_xlfn.TEXTJOIN(CHAR(10),TRUE,IF('people agility'!K13:K28=2,"• "&'people agility'!B13:B28,""))} -> • Openness to Feedback (menerima & menindaklajuti masukan) • Genuine Curiosity about Others (rasa ingin tahu tulus pada orang lain) • Empathy (Merasakan & memahami emosi orang lain) • Coaching & Building Capability (membangun kemampuan orang lain) | H15: {=_xlfn.TEXTJOIN(CHAR(10),TRUE,IF('people agility'!K13:K28=1,"• "&'people agility'!B13:B28,""))} -> • Giving Developmental Feedback (memberi umpan balik yang mengembangkan) • Conflict Mediation (menjadi penengah pihak berbeda) | I15: =LEN(D15)-LEN(SUBSTITUTE(D15,"•","")) -> 3 | J15: =LEN(E15)-LEN(SUBSTITUTE(E15,"•","")) -> 3 | K15: =LEN(F15)-LEN(SUBSTITUTE(F15,"•","")) -> 4 | L15: =LEN(G15)-LEN(SUBSTITUTE(G15,"•","")) -> 4 | M15: =LEN(H15)-LEN(SUBSTITUTE(H15,"•","")) -> 2 | N15: =(J15+I15)/(SUM(I15:M15)) -> 0.375
A16: Change Agility | B16: ='change agility'!K23 -> 2.5 | C16: =IF(B16>=4.5,"Excellent",IF(B16>=4,"Strong",IF(B16>=3,"Meet","Needs Development"))) -> Needs Development | D16: {=_xlfn.TEXTJOIN(CHAR(10),TRUE,IF('change agility'!K13:K22=5,"• "&'change agility'!B13:B22,""))} | E16: {=_xlfn.TEXTJOIN(CHAR(10),TRUE,IF('change agility'!K13:K22=4,"• "&'change agility'!B13:B22,""))} -> • Adapting to New Systems (mengikuti perubahan sistem & prosedur) • Adaptive Learning & Experimentation (aktif belajar hal baru) | F16: {=_xlfn.TEXTJOIN(CHAR(10),TRUE,IF('change agility'!K13:K22=3,"• "&'change agility'!B13:B22,""))} -> • Comfort with New Ways of Working (nyaman dengan cara kerja baru) • Managing Resistance to Change (pengelolaan resistensi) • Proposing New Ideas (menginisiasi perubahan) | G16: {=_xlfn.TEXTJOIN(CHAR(10),TRUE,IF('change agility'!K13:K22=2,"• "&'change agility'!B13:B22,""))} -> • Comfort with Sudden Change (tetap bekerja saat perubahan mendadak) • Viewing Change as Opportunity (melihat perubahan sebagai peluang) • Proactive in Anticipating Change (mengantisipasi perubahan) | H16: {=_xlfn.TEXTJOIN(CHAR(10),TRUE,IF('change agility'!K13:K22=1,"• "&'change agility'!B13:B22,""))} -> • Risk-Taking for Innovation (berani mencoba pendekatan baru) • Calmness in Uncertainty (tetap tenang di kondisi tidak pasti) | I16: =LEN(D16)-LEN(SUBSTITUTE(D16,"•","")) -> 0 | J16: =LEN(E16)-LEN(SUBSTITUTE(E16,"•","")) -> 2 | K16: =LEN(F16)-LEN(SUBSTITUTE(F16,"•","")) -> 3 | L16: =LEN(G16)-LEN(SUBSTITUTE(G16,"•","")) -> 3 | M16: =LEN(H16)-LEN(SUBSTITUTE(H16,"•","")) -> 2 | N16: =(J16+I16)/(SUM(I16:M16)) -> 0.2
A17: Result Agility | B17: ='result agility'!K25 -> 3.4166667 | C17: =IF(B17>=4.5,"Excellent",IF(B17>=4,"Strong",IF(B17>=3,"Meet","Needs Development"))) -> Meet | D17: {=_xlfn.TEXTJOIN(CHAR(10),TRUE,IF('result agility'!K13:K24=5,"• "&'result agility'!B13:B24,""))} -> • Action-Oriented & Takes Initiative (proaktif bertindak) • Tenacity & Strategic Persistence (menjaga komitmen di tengah tantangan) • Adapting Strategy When Needed (mengubah strategi untuk hasil lebih baik) | E17: {=_xlfn.TEXTJOIN(CHAR(10),TRUE,IF('result agility'!K13:K24=4,"• "&'result agility'!B13:B24,""))} -> • Driving for impact (fokus pada hasil kerja) • Prioritizing & Sequencing Work (menyusun prioritas & urutan kerja) • Learning from Outcomes (belajar dari hasil & kesalahan) • Resource Planning & Contingency (merencanakan sumber daya & rencana cadangan) | F17: {=_xlfn.TEXTJOIN(CHAR(10),TRUE,IF('result agility'!K13:K24=3,"• "&'result agility'!B13:B24,""))} | G17: {=_xlfn.TEXTJOIN(CHAR(10),TRUE,IF('result agility'!K13:K24=2,"• "&'result agility'!B13:B24,""))} -> • Task Completion Quality (menyelesaikan tugas dengan baik) • Deciding with Incomplete Data (mengambil keputusan dengan data/informasi terbatas) • Focus Under Pressure (tetap fokus dalam tekanan) • Agile Problem-Solving Under Pressure (memecahkan masalah di bawah tekanan) • Drive for High Performance (dorongan berkinerja tinggi) | H17: {=_xlfn.TEXTJOIN(CHAR(10),TRUE,IF('result agility'!K13:K24=1,"• "&'result agility'!B13:B24,""))} | I17: =LEN(D17)-LEN(SUBSTITUTE(D17,"•","")) -> 3 | J17: =LEN(E17)-LEN(SUBSTITUTE(E17,"•","")) -> 4 | K17: =LEN(F17)-LEN(SUBSTITUTE(F17,"•","")) -> 0 | L17: =LEN(G17)-LEN(SUBSTITUTE(G17,"•","")) -> 5 | M17: =LEN(H17)-LEN(SUBSTITUTE(H17,"•","")) -> 0 | N17: =(J17+I17)/(SUM(I17:M17)) -> 0.58333333
A18: Self Awareness | B18: ='self awareness'!K23 -> 3.6 | C18: =IF(B18>=4.5,"Excellent",IF(B18>=4,"Strong",IF(B18>=3,"Meet","Needs Development"))) -> Meet | D18: {=_xlfn.TEXTJOIN(CHAR(10),TRUE,IF('self awareness'!K13:K22=5,"• "&'self awareness'!B13:B22,""))} -> • Admitting Mistakes (mengakui kesalahan) • Reflective Practices (melakukan refleksi diri) • Proactive Self-Development for Adaptation (aktif mengembangkan diri) • Objective Self-Assessment (menilai diri secara objektif) | E18: {=_xlfn.TEXTJOIN(CHAR(10),TRUE,IF('self awareness'!K13:K22=4,"• "&'self awareness'!B13:B22,""))} | F18: {=_xlfn.TEXTJOIN(CHAR(10),TRUE,IF('self awareness'!K13:K22=3,"• "&'self awareness'!B13:B22,""))} -> • Seeking Feedback on Performance (mencari feedback) • Understanding Strengths & Weaknesses (memahami kekuatan & kelemahan) • Managing Emotions Effectively (mengelola emosi) • Deep Pattern Recognition & Bias Awareness (refleksi diri mendalam & autentik) | G18: {=_xlfn.TEXTJOIN(CHAR(10),TRUE,IF('self awareness'!K13:K22=2,"• "&'self awareness'!B13:B22,""))} -> • Openness to Criticism (menerima kritik) • Awareness of Impact on Others (memahami dampak perilaku) | H18: {=_xlfn.TEXTJOIN(CHAR(10),TRUE,IF('self awareness'!K13:K22=1,"• "&'self awareness'!B13:B22,""))} | I18: =LEN(D18)-LEN(SUBSTITUTE(D18,"•","")) -> 4 | J18: =LEN(E18)-LEN(SUBSTITUTE(E18,"•","")) -> 0 | K18: =LEN(F18)-LEN(SUBSTITUTE(F18,"•","")) -> 4 | L18: =LEN(G18)-LEN(SUBSTITUTE(G18,"•","")) -> 2 | M18: =LEN(H18)-LEN(SUBSTITUTE(H18,"•","")) -> 0 | N18: =(J18+I18)/(SUM(I18:M18)) -> 0.4
A19: OVERALL | B19: =AVERAGE(B14:B18) -> 3.03 | C19: =IF(B19>=4.5,"Highly Agile",IF(B19>=4,"Agile",IF(B19>=3,"Moderately Agile","Developing"))) -> Moderately Agile | D19: mentor skala agility 4
A22: 2. Self Awareness Gap Score
A23: a. Mental Agility
A24: Indicator | B24: Score Self | C24: Score Superior | D24: Gap Score Self-Sup | E24: Gap
A25: ='mental agility'!B13 -> Analytical Thinking (memahami data & fakta dasar) | B25: ='mental agility'!I13 -> 4 | C25: ='mental agility'!K13 -> 4 | D25: ='mental agility'!M13 -> 0 | E25: ='mental agility'!N13 -> No Gap
A26: ='mental agility'!B14 -> Root Cause Analysis (mencari penyebab masalah) | B26: ='mental agility'!I14 -> 3 | C26: ='mental agility'!K14 -> 3 | D26: ='mental agility'!M14 -> 0 | E26: ='mental agility'!N14 -> No Gap
A27: ='mental agility'!B15 -> Critical Thinking & Inquisitiveness (mempertanyakan & mengevaluasi) | B27: ='mental agility'!I15 -> 3 | C27: ='mental agility'!K15 -> 2 | D27: ='mental agility'!M15 -> 1 | E27: ='mental agility'!N15 -> Minor Positive Gap
A28: ='mental agility'!B16 -> Explaining Complexity (menjelaskan hal kompleks secara sederhana) | B28: ='mental agility'!I16 -> 3 | C28: ='mental agility'!K16 -> 1 | D28: ='mental agility'!M16 -> 2 | E28: ='mental agility'!N16 -> Major Positive Gap
A29: ='mental agility'!B17 -> Intellectual Synthesis (menghubungkan berbagai informasi) | B29: ='mental agility'!I17 -> 2 | C29: ='mental agility'!K17 -> 4 | D29: ='mental agility'!M17 -> -2 | E29: ='mental agility'!N17 -> Major Negative Gap
A30: ='mental agility'!B18 -> Integrating Diverse Perspective (keputusan dari berbagai sudut pandang) | B30: ='mental agility'!I18 -> 3 | C30: ='mental agility'!K18 -> 2 | D30: ='mental agility'!M18 -> 1 | E30: ='mental agility'!N18 -> Minor Positive Gap
A31: ='mental agility'!B19 -> Creative Exploration (mencari pendekatan baru) | B31: ='mental agility'!I19 -> 3 | C31: ='mental agility'!K19 -> 2 | D31: ='mental agility'!M19 -> 1 | E31: ='mental agility'!N19 -> Minor Positive Gap
A32: ='mental agility'!B20 -> Breaking Patterned thinking (menciptakan solusi baru) | B32: ='mental agility'!I20 -> 3 | C32: ='mental agility'!K20 -> 4 | D32: ='mental agility'!M20 -> -1 | E32: ='mental agility'!N20 -> Minor Negative Gap
A33: ='mental agility'!B21 -> Comfort with Ambiguity (tetap efektif di situasi tidak jelas) | B33: ='mental agility'!I21 -> 2 | C33: ='mental agility'!K21 -> 1 | D33: ='mental agility'!M21 -> 1 | E33: ='mental agility'!N21 -> Minor Positive Gap
A34: ='mental agility'!B22 -> Tolerance for Ambiguity (memimpin dalam uncertainty tinggi) | B34: ='mental agility'!I22 -> 2 | C34: ='mental agility'!K22 -> 2 | D34: ='mental agility'!M22 -> 0 | E34: ='mental agility'!N22 -> No Gap
A35: Overall Average | B35: ='mental agility'!I23 -> 2.8 | C35: ='mental agility'!K23 -> 2.5 | D35: ='mental agility'!M23 -> 0.3 | E35: ='mental agility'!N23 -> Aligned
A38: b. People Agility
A39: Indicator | B39: Score Self | C39: Score Superior | D39: Gap Score Self-Sup | E39: Gap
A40: ='people agility'!B13 -> Listening for understanding (mendengarkan & memahami) | B40: ='people agility'!I13 -> 2 | C40: ='people agility'!K13 -> 3 | D40: ='people agility'!M13 -> -1 | E40: ='people agility'!N13 -> Minor Negative Gap
A41: ='people agility'!B14 -> Openness to Feedback (menerima & menindaklajuti masukan) | B41: ='people agility'!I14 -> 3 | C41: ='people agility'!K14 -> 2 | D41: ='people agility'!M14 -> 1 | E41: ='people agility'!N14 -> Minor Positive Gap
A42: ='people agility'!B15 -> Genuine Curiosity about Others (rasa ingin tahu tulus pada orang lain) | B42: ='people agility'!I15 -> 4 | C42: ='people agility'!K15 -> 2 | D42: ='people agility'!M15 -> 2 | E42: ='people agility'!N15 -> Major Positive Gap
A43: ='people agility'!B16 -> Collaboration with Diversity (Bekerja efektif dalam keberagaman) | B43: ='people agility'!I16 -> 1 | C43: ='people agility'!K16 -> 5 | D43: ='people agility'!M16 -> -4 | E43: ='people agility'!N16 -> Major Negative Gap
A44: ='people agility'!B17 -> Valuing Diverse Opinions (Menghargai opini berbeda) | B44: ='people agility'!I17 -> 5 | C44: ='people agility'!K17 -> 4 | D44: ='people agility'!M17 -> 1 | E44: ='people agility'!N17 -> Minor Positive Gap
A45: ='people agility'!B18 -> Understanding Different Perspectives (Analisis multi-sudut pandang) | B45: ='people agility'!I18 -> 4 | C45: ='people agility'!K18 -> 5 | D45: ='people agility'!M18 -> -1 | E45: ='people agility'!N18 -> Minor Negative Gap
A46: ='people agility'!B19 -> Recognizing Others' Potential (mengenali potensi orang lain) | B46: ='people agility'!I19 -> 1 | C46: ='people agility'!K19 -> 3 | D46: ='people agility'!M19 -> -2 | E46: ='people agility'!N19 -> Major Negative Gap
A47: ='people agility'!B20 -> Setting Direction & Expectations (menetapkan arah & ekspektasi) | B47: ='people agility'!I20 -> 3 | C47: ='people agility'!K20 -> 5 | D47: ='people agility'!M20 -> -2 | E47: ='people agility'!N20 -> Major Negative Gap
A48: ='people agility'!B21 -> Empathy (Merasakan & memahami emosi orang lain) | B48: ='people agility'!I21 -> 3 | C48: ='people agility'!K21 -> 2 | D48: ='people agility'!M21 -> 1 | E48: ='people agility'!N21 -> Minor Positive Gap
A49: ='people agility'!B22 -> Conflict Navigation (menghadapi konflik secara konstruktif) | B49: ='people agility'!I22 -> 5 | C49: ='people agility'!K22 -> 4 | D49: ='people agility'!M22 -> 1 | E49: ='people agility'!N22 -> Minor Positive Gap
A50: ='people agility'!B23 -> Giving Developmental Feedback (memberi umpan balik yang mengembangkan) | B50: ='people agility'!I23 -> 1 | C50: ='people agility'!K23 -> 1 | D50: ='people agility'!M23 -> 0 | E50: ='people agility'!N23 -> No Gap
A51: ='people agility'!B24 -> Managing Challenging Stakeholder (relasi berkelanjutan dengan pihak sulit) | B51: ='people agility'!I24 -> 2 | C51: ='people agility'!K24 -> 3 | D51: ='people agility'!M24 -> -1 | E51: ='people agility'!N24 -> Minor Negative Gap
... A55: ='people agility'!B28 -> Coaching & Building Capability (membangun kemampuan orang lain) | B55: ='people agility'!I28 -> 3 | C55: ='people agility'!K28 -> 2 | D55: ='people agility'!M28 -> 1 | E55: ='people agility'!N28 -> Minor Positive Gap
A56: Overall Average | B56: ='people agility'!I29 -> 2.8 | C56: ='people agility'!K29 -> 3.1333333 | D56: ='people agility'!M29 -> -0.33333333 | E56: ='people agility'!N29 -> Aligned
A59: c. Change Agility
A60: Indicator | B60: Score Self | C60: Score Superior | D60: Gap Score Self-Sup | E60: Gap
A61: ='change agility'!B13 -> Adapting to New Systems (mengikuti perubahan sistem & prosedur) | B61: ='change agility'!I13 -> 3 | C61: ='change agility'!K13 -> 4 | D61: ='change agility'!M13 -> -1 | E61: ='change agility'!N13 -> Minor Negative Gap
A62: ='change agility'!B14 -> Comfort with New Ways of Working (nyaman dengan cara kerja baru) | B62: ='change agility'!I14 -> 3 | C62: ='change agility'!K14 -> 3 | D62: ='change agility'!M14 -> 0 | E62: ='change agility'!N14 -> No Gap
A63: ='change agility'!B15 -> Comfort with Sudden Change (tetap bekerja saat perubahan mendadak) | B63: ='change agility'!I15 -> 3 | C63: ='change agility'!K15 -> 2 | D63: ='change agility'!M15 -> 1 | E63: ='change agility'!N15 -> Minor Positive Gap
A64: ='change agility'!B16 -> Managing Resistance to Change (pengelolaan resistensi) | B64: ='change agility'!I16 -> 4 | C64: ='change agility'!K16 -> 3 | D64: ='change agility'!M16 -> 1 | E64: ='change agility'!N16 -> Minor Positive Gap
A65: ='change agility'!B17 -> Adaptive Learning & Experimentation (aktif belajar hal baru) | B65: ='change agility'!I17 -> 4 | C65: ='change agility'!K17 -> 4 | D65: ='change agility'!M17 -> 0 | E65: ='change agility'!N17 -> No Gap
A66: ='change agility'!B18 -> Viewing Change as Opportunity (melihat perubahan sebagai peluang) | B66: ='change agility'!I18 -> 3 | C66: ='change agility'!K18 -> 2 | D66: ='change agility'!M18 -> 1 | E66: ='change agility'!N18 -> Minor Positive Gap
A67: ='change agility'!B19 -> Proposing New Ideas (menginisiasi perubahan) | B67: ='change agility'!I19 -> 3 | C67: ='change agility'!K19 -> 3 | D67: ='change agility'!M19 -> 0 | E67: ='change agility'!N19 -> No Gap
A68: ='change agility'!B20 -> Risk-Taking for Innovation (berani mencoba pendekatan baru) | B68: ='change agility'!I20 -> 2 | C68: ='change agility'!K20 -> 1 | D68: ='change agility'!M20 -> 1 | E68: ='change agility'!N20 -> Minor Positive Gap
A69: ='change agility'!B21 -> Calmness in Uncertainty (tetap tenang di kondisi tidak pasti) | B69: ='change agility'!I21 -> 2 | C69: ='change agility'!K21 -> 1 | D69: ='change agility'!M21 -> 1 | E69: ='change agility'!N21 -> Minor Positive Gap
A70: ='change agility'!B22 -> Proactive in Anticipating Change (mengantisipasi perubahan) | B70: ='change agility'!I22 -> 3 | C70: ='change agility'!K22 -> 2 | D70: ='change agility'!M22 -> 1 | E70: ='change agility'!N22 -> Minor Positive Gap
A71: Overall Average | B71: ='change agility'!I23 -> 3 | C71: ='change agility'!K23 -> 2.5 | D71: ='change agility'!M23 -> 0.5 | E71: ='change agility'!N23 -> Minor Positive Gap
A74: d. Result Agility
A75: Indicator | B75: Score Self | C75: Score Superior | D75: Gap Score Self-Sup | E75: Gap
A76: ='result agility'!B13 -> Task Completion Quality (menyelesaikan tugas dengan baik) | B76: ='result agility'!I13 -> 1 | C76: ='result agility'!K13 -> 2 | D76: ='result agility'!M13 -> -1 | E76: ='result agility'!N13 -> Minor Negative Gap
A77: ='result agility'!B14 -> Action-Oriented & Takes Initiative (proaktif bertindak) | B77: ='result agility'!I14 -> 5 | C77: ='result agility'!K14 -> 5 | D77: ='result agility'!M14 -> 0 | E77: ='result agility'!N14 -> No Gap
A78: ='result agility'!B15 -> Driving for impact (fokus pada hasil kerja) | B78: ='result agility'!I15 -> 4 | C78: ='result agility'!K15 -> 4 | D78: ='result agility'!M15 -> 0 | E78: ='result agility'!N15 -> No Gap
A79: ='result agility'!B16 -> Tenacity & Strategic Persistence (menjaga komitmen di tengah tantangan) | B79: ='result agility'!I16 -> 3 | C79: ='result agility'!K16 -> 5 | D79: ='result agility'!M16 -> -2 | E79: ='result agility'!N16 -> Major Negative Gap
A80: ='result agility'!B17 -> Prioritizing & Sequencing Work (menyusun prioritas & urutan kerja) | B80: ='result agility'!I17 -> 5 | C80: ='result agility'!K17 -> 4 | D80: ='result agility'!M17 -> 1 | E80: ='result agility'!N17 -> Minor Positive Gap
A81: ='result agility'!B18 -> Learning from Outcomes (belajar dari hasil & kesalahan) | B81: ='result agility'!I18 -> 1 | C81: ='result agility'!K18 -> 4 | D81: ='result agility'!M18 -> -3 | E81: ='result agility'!N18 -> Major Negative Gap
A82: ='result agility'!B19 -> Deciding with Incomplete Data (mengambil keputusan dengan data/informasi terbatas) | B82: ='result agility'!I19 -> 2 | C82: ='result agility'!K19 -> 2 | D82: ='result agility'!M19 -> 0 | E82: ='result agility'!N19 -> No Gap
A83: ='result agility'!B20 -> Focus Under Pressure (tetap fokus dalam tekanan) | B83: ='result agility'!I20 -> 2 | C83: ='result agility'!K20 -> 2 | D83: ='result agility'!M20 -> 0 | E83: ='result agility'!N20 -> No Gap
A84: ='result agility'!B21 -> Adapting Strategy When Needed (mengubah strategi untuk hasil lebih baik) | B84: ='result agility'!I21 -> 3 | C84: ='result agility'!K21 -> 5 | D84: ='result agility'!M21 -> -2 | E84: ='result agility'!N21 -> Major Negative Gap
A85: ='result agility'!B22 -> Resource Planning & Contingency (merencanakan sumber daya & rencana cadangan) | B85: ='result agility'!I22 -> 1 | C85: ='result agility'!K22 -> 4 | D85: ='result agility'!M22 -> -3 | E85: ='result agility'!N22 -> Major Negative Gap
A86: ='result agility'!B23 -> Agile Problem-Solving Under Pressure (memecahkan masalah di bawah tekanan) | B86: ='result agility'!I23 -> 4 | C86: ='result agility'!K23 -> 2 | D86: ='result agility'!M23 -> 2 | E86: ='result agility'!N23 -> Major Positive Gap
A87: ='result agility'!B24 -> Drive for High Performance (dorongan berkinerja tinggi) | B87: ='result agility'!I24 -> 5 | C87: ='result agility'!K24 -> 2 | D87: ='result agility'!M24 -> 3 | E87: ='result agility'!N24 -> Major Positive Gap
A88: Overall Average | B88: ='result agility'!I25 -> 3 | C88: ='result agility'!K25 -> 3.4166667 | D88: ='result agility'!M25 -> -0.41666667 | E88: ='result agility'!N25 -> Aligned
A91: e. Self Awareness
A92: Indicator | B92: Score Self | C92: Score Superior | D92: Gap Score Self-Sup | E92: Gap
A93: ='self awareness'!B13 -> Openness to Criticism (menerima kritik) | B93: ='self awareness'!I13 -> 4 | C93: ='self awareness'!K13 -> 2 | D93: ='self awareness'!M13 -> 2 | E93: ='self awareness'!N13 -> Major Positive Gap
A94: ='self awareness'!B14 -> Admitting Mistakes (mengakui kesalahan) | B94: ='self awareness'!I14 -> 4 | C94: ='self awareness'!K14 -> 5 | D94: ='self awareness'!M14 -> -1 | E94: ='self awareness'!N14 -> Minor Negative Gap
A95: ='self awareness'!B15 -> Seeking Feedback on Performance (mencari feedback) | B95: ='self awareness'!I15 -> 4 | C95: ='self awareness'!K15 -> 3 | D95: ='self awareness'!M15 -> 1 | E95: ='self awareness'!N15 -> Minor Positive Gap
A96: ='self awareness'!B16 -> Understanding Strengths & Weaknesses (memahami kekuatan & kelemahan) | B96: ='self awareness'!I16 -> 4 | C96: ='self awareness'!K16 -> 3 | D96: ='self awareness'!M16 -> 1 | E96: ='self awareness'!N16 -> Minor Positive Gap
A97: ='self awareness'!B17 -> Reflective Practices (melakukan refleksi diri) | B97: ='self awareness'!I17 -> 5 | C97: ='self awareness'!K17 -> 5 | D97: ='self awareness'!M17 -> 0 | E97: ='self awareness'!N17 -> No Gap
A98: ='self awareness'!B18 -> Proactive Self-Development for Adaptation (aktif mengembangkan diri) | B98: ='self awareness'!I18 -> 3 | C98: ='self awareness'!K18 -> 5 | D98: ='self awareness'!M18 -> -2 | E98: ='self awareness'!N18 -> Major Negative Gap
A99: ='self awareness'!B19 -> Objective Self-Assessment (menilai diri secara objektif) | B99: ='self awareness'!I19 -> 5 | C99: ='self awareness'!K19 -> 5 | D99: ='self awareness'!M19 -> 0 | E99: ='self awareness'!N19 -> No Gap
A100: ='self awareness'!B20 -> Awareness of Impact on Others (memahami dampak perilaku) | B100: ='self awareness'!I20 -> 5 | C100: ='self awareness'!K20 -> 2 | D100: ='self awareness'!M20 -> 3 | E100: ='self awareness'!N20 -> Major Positive Gap
A101: ='self awareness'!B21 -> Managing Emotions Effectively (mengelola emosi) | B101: ='self awareness'!I21 -> 4 | C101: ='self awareness'!K21 -> 3 | D101: ='self awareness'!M21 -> 1 | E101: ='self awareness'!N21 -> Minor Positive Gap
A102: ='self awareness'!B22 -> Deep Pattern Recognition & Bias Awareness (refleksi diri mendalam & autentik) | B102: ='self awareness'!I22 -> 3 | C102: ='self awareness'!K22 -> 3 | D102: ='self awareness'!M22 -> 0 | E102: ='self awareness'!N22 -> No Gap
A103: Overall Average | B103: ='self awareness'!I23 -> 4.1 | C103: ='self awareness'!K23 -> 3.6 | D103: ='self awareness'!M23 -> 0.5 | E103: ='self awareness'!N23 -> Minor Positive Gap
A106: f. Summary
A107: Indicator | B107: Score Self | C107: Score Superior | D107: Gap Score Self-Sup | E107: Gap
A108: Mental Agility | B108: =B35 -> 2.8 | C108: =C35 -> 2.5 | D108: =D35 -> 0.3 | E108: =E35 -> Aligned
A109: People Agility | B109: =B56 -> 2.8 | C109: =C56 -> 3.1333333 | D109: =D56 -> -0.33333333 | E109: =E56 -> Aligned
A110: Change Agility | B110: =B71 -> 3 | C110: =C71 -> 2.5 | D110: =D71 -> 0.5 | E110: =E71 -> Minor Positive Gap
A111: Result Agility | B111: =B88 -> 3 | C111: =C88 -> 3.4166667 | D111: =D88 -> -0.41666667 | E111: =E88 -> Aligned
A112: Self Awareness | B112: =B103 -> 4.1 | C112: =C103 -> 3.6 | D112: =D103 -> 0.5 | E112: =E103 -> Minor Positive Gap
A113: Average | B113: =AVERAGE(B108:B112) -> 3.14 | C113: =AVERAGE(C108:C112) -> 3.03 | D113: =B113-C113 -> 0.11 | E113: {=_xlfn.IFS( VALUE(D113) >= 1, "Major Positive Gap", VALUE(D113) >= 0.5, "Minor Positive Gap", VALUE(D113) >= -0.49, "Aligned", VALUE(D113) >= -0.99, "Minor Negative Gap", VALUE(D113) <= -1, "Major Negative Gap" )} -> Aligned
A116: g. RADAR CHART DATA (for visualization)
A118: Dimensi | B118: Score | C118: Performance Level
A119: Mental Agility | B119: =C108 -> 2.5 | C119: ='Profile Summary'!C14 -> Needs Development
A120: People Agility | B120: =C109 -> 3.1333333 | C120: ='Profile Summary'!C15 -> Meet
...

Sheet Kompetensi
A2: =Identitas!B2 -> Nama | B2: =Identitas!D2 -> 0
A3: =Identitas!B3 -> Nama Atasan yang menilai | B3: =Identitas!D3 -> 0
A4: =Identitas!B4 -> Level Saat Ini | B4: =Identitas!D4 -> Officer
A5: =Identitas!B5 -> Level Tujuan | B5: =Identitas!D5 -> Analyst
A6: =Identitas!B6 -> Tanggal Assesment | B6: =Identitas!D6 -> 0
A7: =Identitas!B7 -> Unit | B7: =Identitas!D7 -> 0
A8: =Identitas!B8 -> Departemen | B8: =Identitas!D8 -> 0
A9: =Identitas!B9 -> Divisi | B9: =Identitas!D9 -> 0
A10: =Identitas!B10 -> Direktorat | B10: =Identitas!D10 -> 0
A12: Kompetensi | B12: Proficiency Level Saat ini | C12: Proficiency Level Tujuan | D12: Hasil Potential | E12: Gap Kompetensi | F12: Absolut gap | G12: Metode Pengembangan dari matriks | H12: Metode dalam teks | I12: Prioritas | J12: Key Metode 1 | K12: Key Metode 2 | L12: Key Metode 3 | M12: Key Metode 4 | N12: Aktivitas Metode 1 | V12: Aktivitas Metode 2 | AD12: Aktivitas Metode 3 | AL12: Aktivitas Metode 4
A13: Achievement Drive | B13: =IFERROR(INDEX(panduan!$C$3:$H$16, MATCH(TRIM(A13), panduan!$B$3:$B$16, 0), MATCH(TRIM($B$4), panduan!$C$2:$H$2, 0)),"") -> 2 | C13: =IFERROR(INDEX(panduan!$C$3:$H$16, MATCH(TRIM(A13), panduan!$B$3:$B$16, 0), MATCH(TRIM($B$5), panduan!$C$2:$H$2, 0)),"") -> 3 | D13: 1 | E13: =D13-C13 -> -2 | F13: =IF(E13<0, MIN(-E13, 4), "") -> 2 | G13: =IFERROR( INDEX(panduan!$C$181:$G$185, MATCH($F$65,panduan!$B$181:$B$185,0), MATCH($F13,panduan!$C$180:$G$180,0) ), "") -> 1,2,3,4 | H13: =IF(G13="", "", SUBSTITUTE( SUBSTITUTE( SUBSTITUTE( SUBSTITUTE(G13, "1", "Personal Development"), "2", "Education-Based Development"), "3", "Relation-Based Development"), "4", "Experience-Based Development") ) -> Personal Development,Education-Based Development,Relation-Based Development,Experience-Based Development | I13: =IF(E13<0,_xlfn.RANK.EQ(E13,$E$13:$E$54,1)+COUNTIF($E$13:E13,E13)-1,"") -> 1 | J13: =IF(ISNUMBER(FIND("1",$G13)), $A13&"|"&$B$5&"|1", "") -> Achievement Drive|Analyst|1 | K13: =IF(ISNUMBER(FIND("2",$G13)), $A13&"|"&$B$5&"|2", "") -> Achievement Drive|Analyst|2 | L13: =IF(ISNUMBER(FIND("3",$G13)), $A13&"|"&$B$5&"|3", "") -> Achievement Drive|Analyst|3 | M13: =IF(ISNUMBER(FIND("4",$G13)), $A13&"|"&$B$5&"|4", "") -> Achievement Drive|Analyst|4 | N13: {=_xlfn.LET( _xlpm.gap, $F13, _xlpm.key, $J13, _xlpm.data, _xlfn._xlws.FILTER('sheet template'!$F$2:$M$1009, ('sheet template'!$A$2:$A$1009=_xlpm.key) * ('sheet template'!$F$2:$F$1009<=_xlpm.gap), ""), IF(OR(_xlpm.key="", _xlpm.gap<=0, ROWS(_xlpm.data)=0), "", _xlpm.data) )} -> 1 | O13: Log "Target yang Menghadapi Hambatan Berulang" | P13: Mengukur ketekunan pada target yang sulit dan berlangsung lama. | Q13: Pilih 1 target yang sedang dikejar dan diperkirakan menghadapi hambatan berulang. Setiap kali mengalami hambatan atau kegagalan pada target itu, catat: apa hambatannya, bagaimana perasaan saat itu, dan apa yang dilakukan — melanjutkan, mengubah cara, atau berhenti sebentar untuk kembali lagi. | R13: Log minimal 15 hambatan pada target yang sama; rentang waktu minimal 3 bulan. | S13: Bulan 1–12 | T13: Bulanan | U13: Minimal 15 hambatan tercatat pada target yang SAMA, berlangsung minimal 3 bulan. Target tersebut tetap dikejar sampai akhir periode logging, tidak ditinggalkan di tengah jalan. Milestone Bulan 6: 8 hambatan tercatat, target masih dikejar. | V13: {=_xlfn.LET( _xlpm.gap, $F13, _xlpm.key, $K13, _xlpm.data, _xlfn._xlws.FILTER('sheet template'!$F$2:$M$1009, ('sheet template'!$A$2:$A$1009=_xlpm.key) * ('sheet template'!$F$2:$F$1009<=_xlpm.gap), ""), IF(OR(_xlpm.key="", _xlpm.gap<=0, ROWS(_xlpm.data)=0), "", _xlpm.data) )} -> 1 | W13: Workshop "Bertahan Melewati Hambatan Berulang" | X13: Menguasai teknik menjaga komitmen ketika hambatan datang berulang kali. | Y13: Ikuti workshop tentang: mengenali tanda mulai kehilangan arah, memisahkan kegagalan taktik dari kegagalan tujuan, dan menjaga energi tanpa dukungan eksternal terus-menerus. | Z13: Sertifikat; 1 rencana bertahan untuk target yang sedang menghadapi hambatan berulang. | AA13: Bulan 1–12 | AB13: Bulanan | AC13: Rencana disetujui atasan dan dipakai pada target yang dipilih peserta dalam aktivitas ini minimal 2 bulan. | AD13: {=_xlfn.LET( _xlpm.gap, $F13, _xlpm.key, $L13, _xlpm.data, _xlfn._xlws.FILTER('sheet template'!$F$2:$M$1009, ('sheet template'!$A$2:$A$1009=_xlpm.key) * ('sheet template'!$F$2:$F$1009<=_xlpm.gap), ""), IF(OR(_xlpm.key="", _xlpm.gap<=0, ROWS(_xlpm.data)=0), "", _xlpm.data) )} -> 1 | AE13: Diskusi dengan Rekan yang Dikenal Tidak Mudah Menyerah | AF13: Mempelajari cara rekan menjaga komitmen di tengah hambatan berulang. | AG13: Diskusi dengan 1 rekan yang dikenal tidak mudah menyerah pada target sulit. Tanyakan: bagaimana ia menjaga energinya, apa yang ia lakukan saat hambatan datang berulang, dan kapan ia tahu harus mengubah cara tanpa mengubah tujuan. | AH13: Catatan diskusi; minimal 3 praktik yang akan diadopsi. | AI13: Bulan 1–12 | AJ13: Bulanan | AK13: Minimal 3 praktik diidentifikasi dan minimal 2 diterapkan pada target yang dipilih peserta dalam aktivitas ini. | AL13: {=_xlfn.LET( _xlpm.gap, $F13, _xlpm.key, $L13, _xlpm.data, _xlfn._xlws.FILTER('sheet template'!$F$2:$M$1009, ('sheet template'!$A$2:$A$1009=_xlpm.key) * ('sheet template'!$F$2:$F$1009<=_xlpm.gap), ""), IF(OR(_xlpm.key="", _xlpm.gap<=0, ROWS(_xlpm.data)=0), "", _xlpm.data) )} -> 1 | AM13: Diskusi dengan Rekan yang Dikenal Tidak Mudah Menyerah | AN13: Mempelajari cara rekan menjaga komitmen di tengah hambatan berulang. | AO13: Diskusi dengan 1 rekan yang dikenal tidak mudah menyerah pada target sulit. Tanyakan: bagaimana ia menjaga energinya, apa yang ia lakukan saat hambatan datang berulang, dan kapan ia tahu harus mengubah cara tanpa mengubah tujuan. | AP13: Catatan diskusi; minimal 3 praktik yang akan diadopsi. | AQ13: Bulan 1–12 | AR13: Bulanan | AS13: Minimal 3 praktik diidentifikasi dan minimal 2 diterapkan pada target yang dipilih peserta dalam aktivitas ini.
N14: 2 | O14: Jurnal Energi Mingguan pada Target yang Sulit | P14: Memantau naik-turunnya energi dan komitmen selama mengejar target sulit. | Q14: Pilih 1 target sulit yang sedang dikejar. Setiap minggu, catat tingkat energi dan komitmen pada skala 1–5, beserta apa yang membuatnya naik atau turun. | R14: Jurnal mingguan minimal 20 minggu. | S14: Bulan 1–12 | T14: Bulanan | U14: Minimal 20 entri mingguan. Meski energi tercatat turun pada sebagian minggu, target tetap dikejar tanpa terputus lebih dari 2 minggu berturut-turut. | V14: 2 | W14: Studi Kasus Orang yang Bertahan Melewati Kegagalan Berulang | X14: Belajar dari pola nyata orang yang tidak menyerah pada hambatan berulang. | Y14: Pilih 1 tokoh (internal atau publik) yang dikenal bertahan melewati kegagalan berulang mencapai targetnya. Pelajari: berapa lama ia bertahan, apa yang membuatnya tidak menyerah, dan kapan ia mengubah taktik tanpa mengubah tujuan. | Z14: Catatan 3 pola ketekunan yang dipelajari. | AA14: Bulan 1–12 | AB14: Bulanan | AC14: Minimal 3 pola ketekunan diidentifikasi dan minimal 1 diterapkan pada target sendiri. | AD14: 2 | AE14: Coaching Berkala dengan Atasan saat Menghadapi Hambatan Berulang | AF14: Mendapatkan dukungan yang menjaga komitmen tanpa menggantikan kemandirian. | AG14: Lakukan sesi coaching dengan atasan setiap kali menghadapi hambatan pada target sulit yang dipilih peserta, minimal 4 kali sepanjang program. Diskusikan apakah akan melanjutkan, mengubah taktik, atau butuh dukungan tambahan. | AH14: 4 catatan coaching. | AI14: Bulan 1–12 | AJ14: Bulanan | AK14: 4 sesi terlaksana. Target tetap dikejar setelah setiap sesi, dan pada sesi-sesi terakhir peserta menunjukkan lebih sedikit kebutuhan didorong dibanding sesi awal. | AL14: 2 | AM14: Coaching Berkala dengan Atasan saat Menghadapi Hambatan Berulang | AN14: Mendapatkan dukungan yang menjaga komitmen tanpa menggantikan kemandirian. | AO14: Lakukan sesi coaching dengan atasan setiap kali menghadapi hambatan pada target sulit yang dipilih peserta, minimal 4 kali sepanjang program. Diskusikan apakah akan melanjutkan, mengubah taktik, atau butuh dukungan tambahan. | AP14: 4 catatan coaching. | AQ14: Bulan 1–12 | AR14: Bulanan | AS14: 4 sesi terlaksana. Target tetap dikejar setelah setiap sesi, dan pada sesi-sesi terakhir peserta menunjukkan lebih sedikit kebutuhan didorong dibanding sesi awal.
A16: Developing Oneself | B16: =IFERROR(INDEX(panduan!$C$3:$H$16, MATCH(TRIM(A16), panduan!$B$3:$B$16, 0), MATCH(TRIM($B$4), panduan!$C$2:$H$2, 0)),"") -> 1 | C16: =IFERROR(INDEX(panduan!$C$3:$H$16, MATCH(TRIM(A16), panduan!$B$3:$B$16, 0), MATCH(TRIM($B$5), panduan!$C$2:$H$2, 0)),"") -> 2 | D16: 2 | E16: =D16-C16 -> 0 | F16: =IF(E16<0, MIN(-E16, 4), "") | G16: =IFERROR( INDEX(panduan!$C$181:$G$185, MATCH($F$65,panduan!$B$181:$B$185,0), MATCH($F16,panduan!$C$180:$G$180,0) ), "") | H16: =IF(G16="", "", SUBSTITUTE( SUBSTITUTE( SUBSTITUTE( SUBSTITUTE(G16, "1", "Personal Development"), "2", "Education-Based Development"), "3", "Relation-Based Development"), "4", "Experience-Based Development") ) | I16: =IF(E16<0,_xlfn.RANK.EQ(E16,$E$13:$E$54,1)+COUNTIF($E$13:E18,E16)-1,"") | J16: =IF(ISNUMBER(FIND("1",$G16)), $A16&"|"&$B$5&"|1", "") | K16: =IF(ISNUMBER(FIND("2",$G16)), $A16&"|"&$B$5&"|2", "") | L16: =IF(ISNUMBER(FIND("3",$G16)), $A16&"|"&$B$5&"|3", "") | M16: =IF(ISNUMBER(FIND("4",$G16)), $A16&"|"&$B$5&"|4", "") | N16: {=_xlfn.LET( _xlpm.gap, $F16, _xlpm.key, $J16, _xlpm.data, _xlfn._xlws.FILTER('sheet template'!$F$2:$M$1009, ('sheet template'!$A$2:$A$1009=_xlpm.key) * ('sheet template'!$F$2:$F$1009<=_xlpm.gap), ""), IF(OR(_xlpm.key="", _xlpm.gap<=0, ROWS(_xlpm.data)=0), "", _xlpm.data) )} | V16: {=_xlfn.LET( _xlpm.gap, $F16, _xlpm.key, $K16, _xlpm.data, _xlfn._xlws.FILTER('sheet template'!$F$2:$M$1009, ('sheet template'!$A$2:$A$1009=_xlpm.key) * ('sheet template'!$F$2:$F$1009<=_xlpm.gap), ""), IF(OR(_xlpm.key="", _xlpm.gap<=0, ROWS(_xlpm.data)=0), "", _xlpm.data) )} | AD16: {=_xlfn.LET( _xlpm.gap, $F16, _xlpm.key, $L16, _xlpm.data, _xlfn._xlws.FILTER('sheet template'!$F$2:$M$1009, ('sheet template'!$A$2:$A$1009=_xlpm.key) * ('sheet template'!$F$2:$F$1009<=_xlpm.gap), ""), IF(OR(_xlpm.key="", _xlpm.gap<=0, ROWS(_xlpm.data)=0), "", _xlpm.data) )} | AL16: {=_xlfn.LET( _xlpm.gap, $F16, _xlpm.key, $L16, _xlpm.data, _xlfn._xlws.FILTER('sheet template'!$F$2:$M$1009, ('sheet template'!$A$2:$A$1009=_xlpm.key) * ('sheet template'!$F$2:$F$1009<=_xlpm.gap), ""), IF(OR(_xlpm.key="", _xlpm.gap<=0, ROWS(_xlpm.data)=0), "", _xlpm.data) )}
A19: Planning & Organizing | B19: =IFERROR(INDEX(panduan!$C$3:$H$16, MATCH(TRIM(A19), panduan!$B$3:$B$16, 0), MATCH(TRIM($B$4), panduan!$C$2:$H$2, 0)),"") -> 1 | C19: =IFERROR(INDEX(panduan!$C$3:$H$16, MATCH(TRIM(A19), panduan!$B$3:$B$16, 0), MATCH(TRIM($B$5), panduan!$C$2:$H$2, 0)),"") -> 2 | D19: 2 | E19: =D19-C19 -> 0 | F19: =IF(E19<0, MIN(-E19, 4), "") | G19: =IFERROR( INDEX(panduan!$C$181:$G$185, MATCH($F$65,panduan!$B$181:$B$185,0), MATCH($F19,panduan!$C$180:$G$180,0) ), "") | H19: =IF(G19="", "", SUBSTITUTE( SUBSTITUTE( SUBSTITUTE( SUBSTITUTE(G19, "1", "Personal Development"), "2", "Education-Based Development"), "3", "Relation-Based Development"), "4", "Experience-Based Development") ) | I19: =IF(E19<0,_xlfn.RANK.EQ(E19,$E$13:$E$54,1)+COUNTIF($E$13:E21,E19)-1,"") | J19: =IF(ISNUMBER(FIND("1",$G19)), $A19&"|"&$B$5&"|1", "") | K19: =IF(ISNUMBER(FIND("2",$G19)), $A19&"|"&$B$5&"|2", "") | L19: =IF(ISNUMBER(FIND("3",$G19)), $A19&"|"&$B$5&"|3", "") | M19: =IF(ISNUMBER(FIND("4",$G19)), $A19&"|"&$B$5&"|4", "") | N19: {=_xlfn.LET( _xlpm.gap, $F19, _xlpm.key, $J19, _xlpm.data, _xlfn._xlws.FILTER('sheet template'!$F$2:$M$1009, ('sheet template'!$A$2:$A$1009=_xlpm.key) * ('sheet template'!$F$2:$F$1009<=_xlpm.gap), ""), IF(OR(_xlpm.key="", _xlpm.gap<=0, ROWS(_xlpm.data)=0), "", _xlpm.data) )} | V19: {=_xlfn.LET( _xlpm.gap, $F19, _xlpm.key, $K19, _xlpm.data, _xlfn._xlws.FILTER('sheet template'!$F$2:$M$1009, ('sheet template'!$A$2:$A$1009=_xlpm.key) * ('sheet template'!$F$2:$F$1009<=_xlpm.gap), ""), IF(OR(_xlpm.key="", _xlpm.gap<=0, ROWS(_xlpm.data)=0), "", _xlpm.data) )} | AD19: {=_xlfn.LET( _xlpm.gap, $F19, _xlpm.key, $L19, _xlpm.data, _xlfn._xlws.FILTER('sheet template'!$F$2:$M$1009, ('sheet template'!$A$2:$A$1009=_xlpm.key) * ('sheet template'!$F$2:$F$1009<=_xlpm.gap), ""), IF(OR(_xlpm.key="", _xlpm.gap<=0, ROWS(_xlpm.data)=0), "", _xlpm.data) )} | AL19: {=_xlfn.LET( _xlpm.gap, $F19, _xlpm.key, $L19, _xlpm.data, _xlfn._xlws.FILTER('sheet template'!$F$2:$M$1009, ('sheet template'!$A$2:$A$1009=_xlpm.key) * ('sheet template'!$F$2:$F$1009<=_xlpm.gap), ""), IF(OR(_xlpm.key="", _xlpm.gap<=0, ROWS(_xlpm.data)=0), "", _xlpm.data) )}
A22: Problem Solving & Decision Making | B22: =IFERROR(INDEX(panduan!$C$3:$H$16, MATCH(TRIM(A22), panduan!$B$3:$B$16, 0), MATCH(TRIM($B$4), panduan!$C$2:$H$2, 0)),"") -> 1 | C22: =IFERROR(INDEX(panduan!$C$3:$H$16, MATCH(TRIM(A22), panduan!$B$3:$B$16, 0), MATCH(TRIM($B$5), panduan!$C$2:$H$2, 0)),"") -> 2 | D22: 2 | E22: =D22-C22 -> 0 | F22: =IF(E22<0, MIN(-E22, 4), "") | G22: =IFERROR( INDEX(panduan!$C$181:$G$185, MATCH($F$65,panduan!$B$181:$B$185,0), MATCH($F22,panduan!$C$180:$G$180,0) ), "") | H22: =IF(G22="", "", SUBSTITUTE( SUBSTITUTE( SUBSTITUTE( SUBSTITUTE(G22, "1", "Personal Development"), "2", "Education-Based Development"), "3", "Relation-Based Development"), "4", "Experience-Based Development") ) | I22: =IF(E22<0,_xlfn.RANK.EQ(E22,$E$13:$E$54,1)+COUNTIF($E$13:E24,E22)-1,"") | J22: =IF(ISNUMBER(FIND("1",$G22)), $A22&"|"&$B$5&"|1", "") | K22: =IF(ISNUMBER(FIND("2",$G22)), $A22&"|"&$B$5&"|2", "") | L22: =IF(ISNUMBER(FIND("3",$G22)), $A22&"|"&$B$5&"|3", "") | M22: =IF(ISNUMBER(FIND("4",$G22)), $A22&"|"&$B$5&"|4", "") | N22: {=_xlfn.LET( _xlpm.gap, $F22, _xlpm.key, $J22, _xlpm.data, _xlfn._xlws.FILTER('sheet template'!$F$2:$M$1009, ('sheet template'!$A$2:$A$1009=_xlpm.key) * ('sheet template'!$F$2:$F$1009<=_xlpm.gap), ""), IF(OR(_xlpm.key="", _xlpm.gap<=0, ROWS(_xlpm.data)=0), "", _xlpm.data) )} | V22: {=_xlfn.LET( _xlpm.gap, $F22, _xlpm.key, $K22, _xlpm.data, _xlfn._xlws.FILTER('sheet template'!$F$2:$M$1009, ('sheet template'!$A$2:$A$1009=_xlpm.key) * ('sheet template'!$F$2:$F$1009<=_xlpm.gap), ""), IF(OR(_xlpm.key="", _xlpm.gap<=0, ROWS(_xlpm.data)=0), "", _xlpm.data) )} | AD22: {=_xlfn.LET( _xlpm.gap, $F22, _xlpm.key, $L22, _xlpm.data, _xlfn._xlws.FILTER('sheet template'!$F$2:$M$1009, ('sheet template'!$A$2:$A$1009=_xlpm.key) * ('sheet template'!$F$2:$F$1009<=_xlpm.gap), ""), IF(OR(_xlpm.key="", _xlpm.gap<=0, ROWS(_xlpm.data)=0), "", _xlpm.data) )} | AL22: {=_xlfn.LET( _xlpm.gap, $F22, _xlpm.key, $L22, _xlpm.data, _xlfn._xlws.FILTER('sheet template'!$F$2:$M$1009, ('sheet template'!$A$2:$A$1009=_xlpm.key) * ('sheet template'!$F$2:$F$1009<=_xlpm.gap), ""), IF(OR(_xlpm.key="", _xlpm.gap<=0, ROWS(_xlpm.data)=0), "", _xlpm.data) )}
A25: Controlling & Corrective Action | B25: =IFERROR(INDEX(panduan!$C$3:$H$16, MATCH(TRIM(A25), panduan!$B$3:$B$16, 0), MATCH(TRIM($B$4), panduan!$C$2:$H$2, 0)),"") -> 2 | C25: =IFERROR(INDEX(panduan!$C$3:$H$16, MATCH(TRIM(A25), panduan!$B$3:$B$16, 0), MATCH(TRIM($B$5), panduan!$C$2:$H$2, 0)),"") -> 3 | D25: 3 | E25: =D25-C25 -> 0 | F25: =IF(E25<0, MIN(-E25, 4), "") | G25: =IFERROR( INDEX(panduan!$C$181:$G$185, MATCH($F$65,panduan!$B$181:$B$185,0), MATCH($F25,panduan!$C$180:$G$180,0) ), "") | H25: =IF(G25="", "", SUBSTITUTE( SUBSTITUTE( SUBSTITUTE( SUBSTITUTE(G25, "1", "Personal Development"), "2", "Education-Based Development"), "3", "Relation-Based Development"), "4", "Experience-Based Development") ) | I25: =IF(E25<0,_xlfn.RANK.EQ(E25,$E$13:$E$54,1)+COUNTIF($E$13:E27,E25)-1,"") | J25: =IF(ISNUMBER(FIND("1",$G25)), $A25&"|"&$B$5&"|1", "") | K25: =IF(ISNUMBER(FIND("2",$G25)), $A25&"|"&$B$5&"|2", "") | L25: =IF(ISNUMBER(FIND("3",$G25)), $A25&"|"&$B$5&"|3", "") | M25: =IF(ISNUMBER(FIND("4",$G25)), $A25&"|"&$B$5&"|4", "") | N25: {=_xlfn.LET( _xlpm.gap, $F25, _xlpm.key, $J25, _xlpm.data, _xlfn._xlws.FILTER('sheet template'!$F$2:$M$1009, ('sheet template'!$A$2:$A$1009=_xlpm.key) * ('sheet template'!$F$2:$F$1009<=_xlpm.gap), ""), IF(OR(_xlpm.key="", _xlpm.gap<=0, ROWS(_xlpm.data)=0), "", _xlpm.data) )} | V25: {=_xlfn.LET( _xlpm.gap, $F25, _xlpm.key, $K25, _xlpm.data, _xlfn._xlws.FILTER('sheet template'!$F$2:$M$1009, ('sheet template'!$A$2:$A$1009=_xlpm.key) * ('sheet template'!$F$2:$F$1009<=_xlpm.gap), ""), IF(OR(_xlpm.key="", _xlpm.gap<=0, ROWS(_xlpm.data)=0), "", _xlpm.data) )} | AD25: {=_xlfn.LET( _xlpm.gap, $F25, _xlpm.key, $L25, _xlpm.data, _xlfn._xlws.FILTER('sheet template'!$F$2:$M$1009, ('sheet template'!$A$2:$A$1009=_xlpm.key) * ('sheet template'!$F$2:$F$1009<=_xlpm.gap), ""), IF(OR(_xlpm.key="", _xlpm.gap<=0, ROWS(_xlpm.data)=0), "", _xlpm.data) )} | AL25: {=_xlfn.LET( _xlpm.gap, $F25, _xlpm.key, $L25, _xlpm.data, _xlfn._xlws.FILTER('sheet template'!$F$2:$M$1009, ('sheet template'!$A$2:$A$1009=_xlpm.key) * ('sheet template'!$F$2:$F$1009<=_xlpm.gap), ""), IF(OR(_xlpm.key="", _xlpm.gap<=0, ROWS(_xlpm.data)=0), "", _xlpm.data) )}
A28: Analytical Thinking | B28: =IFERROR(INDEX(panduan!$C$3:$H$16, MATCH(TRIM(A28), panduan!$B$3:$B$16, 0), MATCH(TRIM($B$4), panduan!$C$2:$H$2, 0)),"") -> 1 | C28: =IFERROR(INDEX(panduan!$C$3:$H$16, MATCH(TRIM(A28), panduan!$B$3:$B$16, 0), MATCH(TRIM($B$5), panduan!$C$2:$H$2, 0)),"") -> 2 | D28: 1 | E28: =D28-C28 -> -1 | F28: =IF(E28<0, MIN(-E28, 4), "") -> 1 | G28: =IFERROR( INDEX(panduan!$C$181:$G$185, MATCH($F$65,panduan!$B$181:$B$185,0), MATCH($F28,panduan!$C$180:$G$180,0) ), "") -> 1,2,3,4 | H28: =IF(G28="", "", SUBSTITUTE( SUBSTITUTE( SUBSTITUTE( SUBSTITUTE(G28, "1", "Personal Development"), "2", "Education-Based Development"), "3", "Relation-Based Development"), "4", "Experience-Based Development") ) -> Personal Development,Education-Based Development,Relation-Based Development,Experience-Based Development | I28: =IF(E28<0,_xlfn.RANK.EQ(E28,$E$13:$E$54,1)+COUNTIF($E$13:E30,E28)-1,"") -> 3 | J28: =IF(ISNUMBER(FIND("1",$G28)), $A28&"|"&$B$5&"|1", "") -> Analytical Thinking|Analyst|1 | K28: =IF(ISNUMBER(FIND("2",$G28)), $A28&"|"&$B$5&"|2", "") -> Analytical Thinking|Analyst|2 | L28: =IF(ISNUMBER(FIND("3",$G28)), $A28&"|"&$B$5&"|3", "") -> Analytical Thinking|Analyst|3 | M28: =IF(ISNUMBER(FIND("4",$G28)), $A28&"|"&$B$5&"|4", "") -> Analytical Thinking|Analyst|4 | N28: {=_xlfn.LET( _xlpm.gap, $F28, _xlpm.key, $J28, _xlpm.data, _xlfn._xlws.FILTER('sheet template'!$F$2:$M$1009, ('sheet template'!$A$2:$A$1009=_xlpm.key) * ('sheet template'!$F$2:$F$1009<=_xlpm.gap), ""), IF(OR(_xlpm.key="", _xlpm.gap<=0, ROWS(_xlpm.data)=0), "", _xlpm.data) )} -> 1 | O28: Log "Yang Saya Terima Begitu Saja" | P28: Menyadari seberapa sering informasi dan arahan diterima tanpa diperiksa. | Q28: Setiap arahan, laporan, atau usulan yang peserta terima, catat: apa premis atau klaim di dalamnya, apakah peserta mempertanyakannya, dan bila tidak — mengapa. Beri tanda khusus pada yang tidak dipertanyakan karena sungkan atau karena yang menyampaikan lebih senior. | R28: Log minimal 40 entri; rekap triwulanan proporsi yang dipertanyakan, dan proporsi yang tidak dipertanyakan karena sungkan. Termasuk rekap triwulanan. | S28: Bulan 1–12 | T28: Bulanan | U28: Minimal 40 entri. Proporsi yang dipertanyakan naik dari baseline triwulan 1 menjadi ≥60% pada triwulan 4, DAN proporsi yang tidak dipertanyakan karena sungkan turun menjadi ≤15%. Milestone Bulan 6: 20 entri dan baseline terbentuk. | V28: {=_xlfn.LET( _xlpm.gap, $F28, _xlpm.key, $K28, _xlpm.data, _xlfn._xlws.FILTER('sheet template'!$F$2:$M$1009, ('sheet template'!$A$2:$A$1009=_xlpm.key) * ('sheet template'!$F$2:$F$1009<=_xlpm.gap), ""), IF(OR(_xlpm.key="", _xlpm.gap<=0, ROWS(_xlpm.data)=0), "", _xlpm.data) )} -> 1 | W28: Workshop "Critical Thinking: Menguji Klaim dan Bukti" | X28: Menguasai cara memeriksa apakah sebuah klaim benar-benar didukung buktinya. | Y28: Pelatihan 2 hari: struktur argumen, membedakan klaim dari bukti, mengenali korelasi yang disalahartikan sebagai sebab, bias konfirmasi, ukuran sampel dan keterwakilan, serta cara menantang sebuah klaim tanpa menyerang orangnya. Peserta membawa 3 klaim kerja nyata sebagai bahan. | Z28: Sertifikat; 3 klaim kerja nyata yang diuji beserta hasilnya. | AA28: Bulan 1–12 | AB28: Bulanan | AC28: Lulus studi kasus dengan skor ≥80. Ketiga klaim kerja nyata diuji dan hasilnya dilaporkan kepada pihak yang menyampaikan klaim tersebut. | AD28: {=_xlfn.LET( _xlpm.gap, $F28, _xlpm.key, $L28, _xlpm.data, _xlfn._xlws.FILTER('sheet template'!$F$2:$M$1009, ('sheet template'!$A$2:$A$1009=_xlpm.key) * ('sheet template'!$F$2:$F$1009<=_xlpm.gap), ""), IF(OR(_xlpm.key="", _xlpm.gap<=0, ROWS(_xlpm.data)=0), "", _xlpm.data) )} -> 1 | AE28: "Challenge Circle" — Peer Officer + Mentor Analyst | AF28: Menemukan cacat penalaran sebelum kesimpulan dipakai. | AG28: Bentuk forum 3–4 peer setingkat ditambah 1 mentor berjenjang Analyst. Setiap bulan, satu peserta membawa 1 kesimpulan kerja yang ia buat. Peserta lain BERTUGAS mencari cacat dalam penalarannya: bukti yang kurang, asumsi yang belum diuji, atau sumber yang terlalu sepihak. | AH28: 10 sesi (minimal 3 sebagai pemapar); catatan cacat penalaran yang ditemukan. Termasuk review catatan pada Bulan ke-6 dan ke-12 oleh mentor. | AI28: Bulan 1–12 | AJ28: Bulanan | AK28: Minimal 8 dari 10 sesi terlaksana. Pada 3 pemaparan sendiri, jumlah cacat penalaran yang ditemukan rekan turun ≥50% dari pemaparan pertama ke ketiga. Milestone Bulan 6: 4 sesi, minimal 1 sebagai pemapar. | AL28: {=_xlfn.LET( _xlpm.gap, $F28, _xlpm.key, $L28, _xlpm.data, _xlfn._xlws.FILTER('sheet template'!$F$2:$M$1009, ('sheet template'!$A$2:$A$1009=_xlpm.key) * ('sheet template'!$F$2:$F$1009<=_xlpm.gap), ""), IF(OR(_xlpm.key="", _xlpm.gap<=0, ROWS(_xlpm.data)=0), "", _xlpm.data) )} -> 1 | AM28: "Challenge Circle" — Peer Officer + Mentor Analyst | AN28: Menemukan cacat penalaran sebelum kesimpulan dipakai. | AO28: Bentuk forum 3–4 peer setingkat ditambah 1 mentor berjenjang Analyst. Setiap bulan, satu peserta membawa 1 kesimpulan kerja yang ia buat. Peserta lain BERTUGAS mencari cacat dalam penalarannya: bukti yang kurang, asumsi yang belum diuji, atau sumber yang terlalu sepihak. | AP28: 10 sesi (minimal 3 sebagai pemapar); catatan cacat penalaran yang ditemukan. Termasuk review catatan pada Bulan ke-6 dan ke-12 oleh mentor. | AQ28: Bulan 1–12 | AR28: Bulanan | AS28: Minimal 8 dari 10 sesi terlaksana. Pada 3 pemaparan sendiri, jumlah cacat penalaran yang ditemukan rekan turun ≥50% dari pemaparan pertama ke ketiga. Milestone Bulan 6: 4 sesi, minimal 1 sebagai pemapar.
A31: Managing Change | B31: =IFERROR(INDEX(panduan!$C$3:$H$16, MATCH(TRIM(A31), panduan!$B$3:$B$16, 0), MATCH(TRIM($B$4), panduan!$C$2:$H$2, 0)),"") -> 1 | C31: =IFERROR(INDEX(panduan!$C$3:$H$16, MATCH(TRIM(A31), panduan!$B$3:$B$16, 0), MATCH(TRIM($B$5), panduan!$C$2:$H$2, 0)),"") -> 2 | D31: 1 | E31: =D31-C31 -> -1 | F31: =IF(E31<0, MIN(-E31, 4), "") -> 1 | G31: =IFERROR( INDEX(panduan!$C$181:$G$185, MATCH($F$65,panduan!$B$181:$B$185,0), MATCH($F31,panduan!$C$180:$G$180,0) ), "") -> 1,2,3,4 | H31: =IF(G31="", "", SUBSTITUTE( SUBSTITUTE( SUBSTITUTE( SUBSTITUTE(G31, "1", "Personal Development"), "2", "Education-Based Development"), "3", "Relation-Based Development"), "4", "Experience-Based Development") ) -> Personal Development,Education-Based Development,Relation-Based Development,Experience-Based Development | I31: =IF(E31<0,_xlfn.RANK.EQ(E31,$E$13:$E$54,1)+COUNTIF($E$13:E331,E31)-1,"") -> 8 | J31: =IF(ISNUMBER(FIND("1",$G31)), $A31&"|"&$B$5&"|1", "") -> Managing Change|Analyst|1 | K31: =IF(ISNUMBER(FIND("2",$G31)), $A31&"|"&$B$5&"|2", "") -> Managing Change|Analyst|2 | L31: =IF(ISNUMBER(FIND("3",$G31)), $A31&"|"&$B$5&"|3", "") -> Managing Change|Analyst|3 | M31: =IF(ISNUMBER(FIND("4",$G31)), $A31&"|"&$B$5&"|4", "") -> Managing Change|Analyst|4 | N31: {=_xlfn.LET( _xlpm.gap, $F31, _xlpm.key, $J31, _xlpm.data, _xlfn._xlws.FILTER('sheet template'!$F$2:$M$1009, ('sheet template'!$A$2:$A$1009=_xlpm.key) * ('sheet template'!$F$2:$F$1009<=_xlpm.gap), ""), IF(OR(_xlpm.key="", _xlpm.gap<=0, ROWS(_xlpm.data)=0), "", _xlpm.data) )} -> 1 | O31: Log "Perubahan Mendadak" | P31: Mengukur berapa lama peserta kembali produktif setelah perubahan datang tanpa persiapan. | Q31: Setiap kali arahan, target, prioritas, atau situasi kerja berubah MENDADAK — tanpa pemberitahuan sebelumnya — catat: apa yang berubah, kapan peserta diberi tahu, apa yang peserta lakukan pada jam-jam pertama, dan kapan peserta kembali bekerja dengan produktivitas normal. Perubahan yang sudah diumumkan jauh hari TIDAK dicatat di sini. | R31: Log minimal 20 perubahan mendadak; rekap triwulanan rata-rata waktu pemulihan produktivitas. Termasuk review rekap triwulanan. | S31: Bulan 1–12 | T31: Bulanan | U31: Minimal 20 kejadian tercatat. Rata-rata waktu pemulihan turun ≥50% dari baseline triwulan 1 pada triwulan 4. Milestone bulan ke-6: 10 kejadian dan baseline terbentuk. | V31: {=_xlfn.LET( _xlpm.gap, $F31, _xlpm.key, $K31, _xlpm.data, _xlfn._xlws.FILTER('sheet template'!$F$2:$M$1009, ('sheet template'!$A$2:$A$1009=_xlpm.key) * ('sheet template'!$F$2:$F$1009<=_xlpm.gap), ""), IF(OR(_xlpm.key="", _xlpm.gap<=0, ROWS(_xlpm.data)=0), "", _xlpm.data) )} -> 1 | W31: Workshop "Bekerja Saat Prioritas Berubah Mendadak" (1 hari) | X31: Menguasai langkah yang mempercepat kembali produktif setelah perubahan mendadak. | Y31: Pelatihan 1 hari: menyusun ulang prioritas dengan cepat, memutuskan pekerjaan mana yang dihentikan dan mana yang diteruskan, menegosiasikan ulang komitmen yang terdampak, serta apa yang harus dikerjakan pada jam-jam pertama setelah perubahan datang. | Z31: Sertifikat; 1 daftar langkah pribadi untuk jam-jam pertama setelah perubahan mendadak. | AA31: Bulan 1–12 | AB31: Bulanan | AC31: Lulus simulasi dengan skor ≥80 (skala 0–100). Daftar langkah dipakai pada minimal 5 kejadian nyata dan tercatat dalam dokumentasi peserta, dengan waktu pemulihan turun ≥20% dibanding kejadian sebelum pelatihan. | AD31: {=_xlfn.LET( _xlpm.gap, $F31, _xlpm.key, $L31, _xlpm.data, _xlfn._xlws.FILTER('sheet template'!$F$2:$M$1009, ('sheet template'!$A$2:$A$1009=_xlpm.key) * ('sheet template'!$F$2:$F$1009<=_xlpm.gap), ""), IF(OR(_xlpm.key="", _xlpm.gap<=0, ROWS(_xlpm.data)=0), "", _xlpm.data) )} -> 1 | AE31: Shadowing Atasan saat Menerima Perubahan Mendadak | AF31: Mempelajari apa yang dilakukan senior pada 24 jam pertama setelah perubahan datang. | AG31: Minta izin mengamati 3 kesempatan di mana atasan menerima perubahan arahan atau prioritas secara mendadak. Catat: apa yang ia lakukan lebih dulu, pekerjaan apa yang ia hentikan, siapa yang ia hubungi dan dalam urutan apa, dan berapa lama sampai unit kembali bekerja normal. | AH31: 3 laporan observasi; daftar 4 langkah yang akan diadopsi. | AI31: Bulan 1–12 | AJ31: Bulanan | AK31: Minimal 3 langkah diterapkan pada kejadian nyata peserta; waktu pemulihan terkait turun ≥20% dari baseline. Divalidasi Atasan ≥4 (skala 1–5). | AL31: {=_xlfn.LET( _xlpm.gap, $F31, _xlpm.key, $L31, _xlpm.data, _xlfn._xlws.FILTER('sheet template'!$F$2:$M$1009, ('sheet template'!$A$2:$A$1009=_xlpm.key) * ('sheet template'!$F$2:$F$1009<=_xlpm.gap), ""), IF(OR(_xlpm.key="", _xlpm.gap<=0, ROWS(_xlpm.data)=0), "", _xlpm.data) )} -> 1 | AM31: Shadowing Atasan saat Menerima Perubahan Mendadak | AN31: Mempelajari apa yang dilakukan senior pada 24 jam pertama setelah perubahan datang. | AO31: Minta izin mengamati 3 kesempatan di mana atasan menerima perubahan arahan atau prioritas secara mendadak. Catat: apa yang ia lakukan lebih dulu, pekerjaan apa yang ia hentikan, siapa yang ia hubungi dan dalam urutan apa, dan berapa lama sampai unit kembali bekerja normal. | AP31: 3 laporan observasi; daftar 4 langkah yang akan diadopsi. | AQ31: Bulan 1–12 | AR31: Bulanan | AS31: Minimal 3 langkah diterapkan pada kejadian nyata peserta; waktu pemulihan terkait turun ≥20% dari baseline. Divalidasi Atasan ≥4 (skala 1–5).
A34: Strategic Thinking | B34: =IFERROR(INDEX(panduan!$C$3:$H$16, MATCH(TRIM(A34), panduan!$B$3:$B$16, 0), MATCH(TRIM($B$4), panduan!$C$2:$H$2, 0)),"") -> 1 | C34: =IFERROR(INDEX(panduan!$C$3:$H$16, MATCH(TRIM(A34), panduan!$B$3:$B$16, 0), MATCH(TRIM($B$5), panduan!$C$2:$H$2, 0)),"") -> 2 | D34: 1 | E34: =D34-C34 -> -1 | F34: =IF(E34<0, MIN(-E34, 4), "") -> 1 | G34: =IFERROR( INDEX(panduan!$C$181:$G$185, MATCH($F$65,panduan!$B$181:$B$185,0), MATCH($F34,panduan!$C$180:$G$180,0) ), "") -> 1,2,3,4 | H34: =IF(G34="", "", SUBSTITUTE( SUBSTITUTE( SUBSTITUTE( SUBSTITUTE(G34, "1", "Personal Development"), "2", "Education-Based Development"), "3", "Relation-Based Development"), "4", "Experience-Based Development") ) -> Personal Development,Education-Based Development,Relation-Based Development,Experience-Based Development | I34: =IF(E34<0,_xlfn.RANK.EQ(E34,$E$13:$E$54,1)+COUNTIF($E$13:E36,E34)-1,"") -> 5 | J34: =IF(ISNUMBER(FIND("1",$G34)), $A34&"|"&$B$5&"|1", "") -> Strategic Thinking|Analyst|1 | K34: =IF(ISNUMBER(FIND("2",$G34)), $A34&"|"&$B$5&"|2", "") -> Strategic Thinking|Analyst|2 | L34: =IF(ISNUMBER(FIND("3",$G34)), $A34&"|"&$B$5&"|3", "") -> Strategic Thinking|Analyst|3 | M34: =IF(ISNUMBER(FIND("4",$G34)), $A34&"|"&$B$5&"|4", "") -> Strategic Thinking|Analyst|4 | N34: {=_xlfn.LET( _xlpm.gap, $F34, _xlpm.key, $J34, _xlpm.data, _xlfn._xlws.FILTER('sheet template'!$F$2:$M$1009, ('sheet template'!$A$2:$A$1009=_xlpm.key) * ('sheet template'!$F$2:$F$1009<=_xlpm.gap), ""), IF(OR(_xlpm.key="", _xlpm.gap<=0, ROWS(_xlpm.data)=0), "", _xlpm.data) )} -> 1 | O34: Latihan "Satu Analisis, Tiga Audiens" | P34: Menyesuaikan bentuk penjelasan analisis tanpa mengubah kesimpulannya. | Q34: Setiap 2 minggu, ambil 1 analisis bisnis yang peserta buat — kondisi internal, pembanding pesaing, atau faktor eksternal. Tulis 3 versi: untuk atasan (keputusan apa yang peserta minta), untuk rekan pelaksana (apa yang harus dikerjakan), dan untuk pihak di luar unit yang tidak menguasai istilahnya. Catat apa yang dibuang dan apa yang wajib dipertahankan. | R34: 24 set latihan (72 versi); daftar istilah bisnis beserta padanan awamnya. Termasuk review bulan ke-6 dan ke-12 oleh Mentor. | S34: Bulan 1–12 | T34: Bulanan | U34: Minimal 20 dari 24 set lengkap. Mentor menilai ≥4 (skala 1–5) pada aspek "kesimpulan tetap sama di ketiga versi" — versi yang lebih sederhana tidak boleh mengubah arah kesimpulannya. Milestone bulan ke-6: 10 set. | V34: {=_xlfn.LET( _xlpm.gap, $F34, _xlpm.key, $K34, _xlpm.data, _xlfn._xlws.FILTER('sheet template'!$F$2:$M$1009, ('sheet template'!$A$2:$A$1009=_xlpm.key) * ('sheet template'!$F$2:$F$1009<=_xlpm.gap), ""), IF(OR(_xlpm.key="", _xlpm.gap<=0, ROWS(_xlpm.data)=0), "", _xlpm.data) )} -> 1 | W34: Workshop "Structured Business Communication: Pyramid Principle & SCQA" (2 hari) | X34: Menguasai kerangka menyusun penjelasan analisis yang runtut. | Y34: Pelatihan 2 hari: Pyramid Principle (kesimpulan di depan, pengelompokan alasan secara MECE), kerangka SCQA untuk membingkai persoalan bisnis, menurunkan tingkat abstraksi, dan menyesuaikan kedalaman per audiens. Peserta membawa 1 analisis bisnis nyata. | Z34: Sertifikat; 1 analisis bisnis nyata yang disusun ulang dengan kerangka piramida — versi sebelum dan sesudah. | AA34: Bulan 1–12 | AB34: Bulanan | AC34: Lulus studi kasus dengan skor ≥80 (skala 0–100). Atasan menilai versi sesudah ≥4 (skala 1–5) pada kejelasan struktur dibanding versi sebelum. | AD34: {=_xlfn.LET( _xlpm.gap, $F34, _xlpm.key, $L34, _xlpm.data, _xlfn._xlws.FILTER('sheet template'!$F$2:$M$1009, ('sheet template'!$A$2:$A$1009=_xlpm.key) * ('sheet template'!$F$2:$F$1009<=_xlpm.gap), ""), IF(OR(_xlpm.key="", _xlpm.gap<=0, ROWS(_xlpm.data)=0), "", _xlpm.data) )} -> 1 | AE34: "Clarity Circle" — Uji Penjelasan Analisis ke Rekan Lintas Fungsi | AF34: Menguji apakah analisis dipahami oleh orang yang tidak menguasai konteksnya. | AG34: Bentuk forum 4 orang dari fungsi berbeda. Setiap bulan, satu peserta menjelaskan 1 analisis bisnis selama 5 menit. Pendengar WAJIB menjelaskan ulang isinya dengan bahasa sendiri; pemapar mencatat bagian mana yang maknanya bergeser, lalu memperbaiki penjelasannya. | AH34: 10 sesi (minimal 3 sebagai pemapar); catatan pergeseran makna dan perbaikannya. | AI34: Bulan 1–12 | AJ34: Bulanan | AK34: Minimal 8 dari 10 sesi terlaksana. Pada 3 pemaparan sendiri, ketepatan penjelasan-ulang pendengar naik ≥20% dari pemaparan pertama ke ketiga. Milestone bulan ke-6: 4 sesi, minimal 1 sebagai pemapar. | AL34: {=_xlfn.LET( _xlpm.gap, $F34, _xlpm.key, $L34, _xlpm.data, _xlfn._xlws.FILTER('sheet template'!$F$2:$M$1009, ('sheet template'!$A$2:$A$1009=_xlpm.key) * ('sheet template'!$F$2:$F$1009<=_xlpm.gap), ""), IF(OR(_xlpm.key="", _xlpm.gap<=0, ROWS(_xlpm.data)=0), "", _xlpm.data) )} -> 1 | AM34: "Clarity Circle" — Uji Penjelasan Analisis ke Rekan Lintas Fungsi | AN34: Menguji apakah analisis dipahami oleh orang yang tidak menguasai konteksnya. | AO34: Bentuk forum 4 orang dari fungsi berbeda. Setiap bulan, satu peserta menjelaskan 1 analisis bisnis selama 5 menit. Pendengar WAJIB menjelaskan ulang isinya dengan bahasa sendiri; pemapar mencatat bagian mana yang maknanya bergeser, lalu memperbaiki penjelasannya. | AP34: 10 sesi (minimal 3 sebagai pemapar); catatan pergeseran makna dan perbaikannya. | AQ34: Bulan 1–12 | AR34: Bulanan | AS34: Minimal 8 dari 10 sesi terlaksana. Pada 3 pemaparan sendiri, ketepatan penjelasan-ulang pendengar naik ≥20% dari pemaparan pertama ke ketiga. Milestone bulan ke-6: 4 sesi, minimal 1 sebagai pemapar.
A37: Conceptual Thinking | B37: =IFERROR(INDEX(panduan!$C$3:$H$16, MATCH(TRIM(A37), panduan!$B$3:$B$16, 0), MATCH(TRIM($B$4), panduan!$C$2:$H$2, 0)),"") -> 1 | C37: =IFERROR(INDEX(panduan!$C$3:$H$16, MATCH(TRIM(A37), panduan!$B$3:$B$16, 0), MATCH(TRIM($B$5), panduan!$C$2:$H$2, 0)),"") -> 2 | D37: 2 | E37: =D37-C37 -> 0 | F37: =IF(E37<0, MIN(-E37, 4), "") | G37: =IFERROR( INDEX(panduan!$C$181:$G$185, MATCH($F$65,panduan!$B$181:$B$185,0), MATCH($F37,panduan!$C$180:$G$180,0) ), "") | H37: =IF(G37="", "", SUBSTITUTE( SUBSTITUTE( SUBSTITUTE( SUBSTITUTE(G37, "1", "Personal Development"), "2", "Education-Based Development"), "3", "Relation-Based Development"), "4", "Experience-Based Development") ) | I37: =IF(E37<0,_xlfn.RANK.EQ(E37,$E$13:$E$54,1)+COUNTIF($E$13:E39,E37)-1,"") | J37: =IF(ISNUMBER(FIND("1",$G37)), $A37&"|"&$B$5&"|1", "") | K37: =IF(ISNUMBER(FIND("2",$G37)), $A37&"|"&$B$5&"|2", "") | L37: =IF(ISNUMBER(FIND("3",$G37)), $A37&"|"&$B$5&"|3", "") | M37: =IF(ISNUMBER(FIND("4",$G37)), $A37&"|"&$B$5&"|4", "") | N37: {=_xlfn.LET( _xlpm.gap, $F37, _xlpm.key, $J37, _xlpm.data, _xlfn._xlws.FILTER('sheet template'!$F$2:$M$1009, ('sheet template'!$A$2:$A$1009=_xlpm.key) * ('sheet template'!$F$2:$F$1009<=_xlpm.gap), ""), IF(OR(_xlpm.key="", _xlpm.gap<=0, ROWS(_xlpm.data)=0), "", _xlpm.data) )} | V37: {=_xlfn.LET( _xlpm.gap, $F37, _xlpm.key, $K37, _xlpm.data, _xlfn._xlws.FILTER('sheet template'!$F$2:$M$1009, ('sheet template'!$A$2:$A$1009=_xlpm.key) * ('sheet template'!$F$2:$F$1009<=_xlpm.gap), ""), IF(OR(_xlpm.key="", _xlpm.gap<=0, ROWS(_xlpm.data)=0), "", _xlpm.data) )} | AD37: {=_xlfn.LET( _xlpm.gap, $F37, _xlpm.key, $L37, _xlpm.data, _xlfn._xlws.FILTER('sheet template'!$F$2:$M$1009, ('sheet template'!$A$2:$A$1009=_xlpm.key) * ('sheet template'!$F$2:$F$1009<=_xlpm.gap), ""), IF(OR(_xlpm.key="", _xlpm.gap<=0, ROWS(_xlpm.data)=0), "", _xlpm.data) )} | AL37: {=_xlfn.LET( _xlpm.gap, $F37, _xlpm.key, $L37, _xlpm.data, _xlfn._xlws.FILTER('sheet template'!$F$2:$M$1009, ('sheet template'!$A$2:$A$1009=_xlpm.key) * ('sheet template'!$F$2:$F$1009<=_xlpm.gap), ""), IF(OR(_xlpm.key="", _xlpm.gap<=0, ROWS(_xlpm.data)=0), "", _xlpm.data) )}
A40: Leadership | B40: =IFERROR(INDEX(panduan!$C$3:$H$16, MATCH(TRIM(A40), panduan!$B$3:$B$16, 0), MATCH(TRIM($B$4), panduan!$C$2:$H$2, 0)),"") -> 2 | C40: =IFERROR(INDEX(panduan!$C$3:$H$16, MATCH(TRIM(A40), panduan!$B$3:$B$16, 0), MATCH(TRIM($B$5), panduan!$C$2:$H$2, 0)),"") -> 3 | D40: 1 | E40: =D40-C40 -> -2 | F40: =IF(E40<0, MIN(-E40, 4), "") -> 2 | G40: =IFERROR( INDEX(panduan!$C$181:$G$185, MATCH($F$65,panduan!$B$181:$B$185,0), MATCH($F40,panduan!$C$180:$G$180,0) ), "") -> 1,2,3,4 | H40: =IF(G40="", "", SUBSTITUTE( SUBSTITUTE( SUBSTITUTE( SUBSTITUTE(G40, "1", "Personal Development"), "2", "Education-Based Development"), "3", "Relation-Based Development"), "4", "Experience-Based Development") ) -> Personal Development,Education-Based Development,Relation-Based Development,Experience-Based Development | I40: =IF(E40<0,_xlfn.RANK.EQ(E40,$E$13:$E$54,1)+COUNTIF($E$13:E42,E40)-1,"") -> 2 | J40: =IF(ISNUMBER(FIND("1",$G40)), $A40&"|"&$B$5&"|1", "") -> Leadership|Analyst|1 | K40: =IF(ISNUMBER(FIND("2",$G40)), $A40&"|"&$B$5&"|2", "") -> Leadership|Analyst|2 | L40: =IF(ISNUMBER(FIND("3",$G40)), $A40&"|"&$B$5&"|3", "") -> Leadership|Analyst|3 | M40: =IF(ISNUMBER(FIND("4",$G40)), $A40&"|"&$B$5&"|4", "") -> Leadership|Analyst|4 | N40: {=_xlfn.LET( _xlpm.gap, $F40, _xlpm.key, $J40, _xlpm.data, _xlfn._xlws.FILTER('sheet template'!$F$2:$M$1009, ('sheet template'!$A$2:$A$1009=_xlpm.key) * ('sheet template'!$F$2:$F$1009<=_xlpm.gap), ""), IF(OR(_xlpm.key="", _xlpm.gap<=0, ROWS(_xlpm.data)=0), "", _xlpm.data) )} -> 1 | O40: Log "Dasar Saya Mengurutkan Pekerjaan Tim" | P40: Mengukur dasar yang dipakai untuk mengurutkan pekerjaan tim yang bersaing. | Q40: Setiap kali menghadapi lebih dari 2 tugas tim yang bersaing memperebutkan waktu, catat: tugas apa saja, urutan yang peserta tetapkan, dan dasar sebenarnya. | R40: Log minimal 24 situasi. Termasuk rekap triwulanan. | S40: Bulan 1–12 | T40: Bulanan | U40: Minimal 24 situasi tercatat. Proporsi berdasar dampak naik menjadi ≥50% pada triwulan 4. Milestone bulan ke-6: 12 situasi. | V40: {=_xlfn.LET( _xlpm.gap, $F40, _xlpm.key, $K40, _xlpm.data, _xlfn._xlws.FILTER('sheet template'!$F$2:$M$1009, ('sheet template'!$A$2:$A$1009=_xlpm.key) * ('sheet template'!$F$2:$F$1009<=_xlpm.gap), ""), IF(OR(_xlpm.key="", _xlpm.gap<=0, ROWS(_xlpm.data)=0), "", _xlpm.data) )} -> 1 | W40: Workshop "Mengurutkan dan Mengomunikasikan Prioritas Tim Berdasarkan Dampak" | X40: Menguasai kerangka mengurutkan berdasarkan dampak dan mengomunikasikannya kepada tim. | Y40: Ikuti workshop tentang urgent-important matrix, keterkaitan antar tugas, dan cara mengomunikasikan prioritas agar tim memahami tanpa perlu terus bertanya. | Z40: 1 kerangka pengurutan yang dipakai peserta dalam aktivitas ini. Termasuk persetujuan Atasan. | AA40: Bulan 1–12 | AB40: Bulanan | AC40: Kerangka disetujui Atasan dan dipakai pada minimal 10 situasi. | AD40: {=_xlfn.LET( _xlpm.gap, $F40, _xlpm.key, $L40, _xlpm.data, _xlfn._xlws.FILTER('sheet template'!$F$2:$M$1009, ('sheet template'!$A$2:$A$1009=_xlpm.key) * ('sheet template'!$F$2:$F$1009<=_xlpm.gap), ""), IF(OR(_xlpm.key="", _xlpm.gap<=0, ROWS(_xlpm.data)=0), "", _xlpm.data) )} -> 1 | AE40: Diskusi dengan Rekan Senior tentang Mengurutkan Pekerjaan Tim | AF40: Mempelajari dasar pengurutan yang dipakai senior untuk tim mereka. | AG40: Diskusi dengan rekan senior tentang bagaimana mereka mengurutkan pekerjaan tim yang bersaing dan mengomunikasikannya. | AH40: Catatan diskusi; dasar yang diadopsi. | AI40: Bulan 1–12 | AJ40: Bulanan | AK40: Minimal 3 dasar pengurutan diadopsi dan diterapkan pada log peserta dalam aktivitas ini. | AL40: {=_xlfn.LET( _xlpm.gap, $F40, _xlpm.key, $L40, _xlpm.data, _xlfn._xlws.FILTER('sheet template'!$F$2:$M$1009, ('sheet template'!$A$2:$A$1009=_xlpm.key) * ('sheet template'!$F$2:$F$1009<=_xlpm.gap), ""), IF(OR(_xlpm.key="", _xlpm.gap<=0, ROWS(_xlpm.data)=0), "", _xlpm.data) )} -> 1 | AM40: Diskusi dengan Rekan Senior tentang Mengurutkan Pekerjaan Tim | AN40: Mempelajari dasar pengurutan yang dipakai senior untuk tim mereka. | AO40: Diskusi dengan rekan senior tentang bagaimana mereka mengurutkan pekerjaan tim yang bersaing dan mengomunikasikannya. | AP40: Catatan diskusi; dasar yang diadopsi. | AQ40: Bulan 1–12 | AR40: Bulanan | AS40: Minimal 3 dasar pengurutan diadopsi dan diterapkan pada log peserta dalam aktivitas ini.
N41: 2 | O41: Latihan "Mengomunikasikan Prioritas kepada Tim" | P41: Melatih menjelaskan dasar urutan prioritas kepada tim, bukan hanya menetapkannya sendiri. | Q41: Setiap kali menetapkan urutan prioritas untuk tugas tim, jelaskan kepada anggota tim dasarnya — mengapa tugas ini lebih dulu daripada yang lain. | R41: Log 20 komunikasi prioritas. Termasuk konfirmasi anggota tim. | S41: Bulan 1–12 | T41: Bulanan | U41: Minimal 20 komunikasi tercatat. Minimal 15 dikonfirmasi anggota tim sebagai jelas dan masuk akal. | V41: 2 | W41: Kursus Online "Leading Teams Through Competing Priorities" | X41: Mempelajari cara memimpin tim yang menghadapi banyak tugas bersaing. | Y41: Selesaikan kursus tentang mengelola beban kerja tim yang majemuk dan mengomunikasikan perubahan prioritas. | Z41: 1 rencana penerapan pada tim sendiri. Termasuk konfirmasi Atasan. | AA41: Bulan 1–12 | AB41: Bulanan | AC41: Rencana diterapkan dan dikonfirmasi Atasan sebagai efektif mengurangi kebingungan prioritas tim. | AD41: 2 | AE41: Meminta Anggota Tim Menantang Urutan Prioritas yang Ditetapkan | AF41: Menguji apakah urutan yang ditetapkan benar-benar berdasar dampak. | AG41: Setiap bulan, tunjukkan urutan prioritas tim kepada 1 anggota. Minta mereka menantang apakah urutan itu berdasar dampak atau kemudahan. | AH41: Catatan tantangan; revisi urutan. | AI41: Bulan 1–12 | AJ41: Bulanan | AK41: Minimal 6 sesi terlaksana. Minimal 3 urutan direvisi setelah ditantang. | AL41: 2 | AM41: Meminta Anggota Tim Menantang Urutan Prioritas yang Ditetapkan | AN41: Menguji apakah urutan yang ditetapkan benar-benar berdasar dampak. | AO41: Setiap bulan, tunjukkan urutan prioritas tim kepada 1 anggota. Minta mereka menantang apakah urutan itu berdasar dampak atau kemudahan. | AP41: Catatan tantangan; revisi urutan. | AQ41: Bulan 1–12 | AR41: Bulanan | AS41: Minimal 6 sesi terlaksana. Minimal 3 urutan direvisi setelah ditantang.
A43: Developing Others | B43: =IFERROR(INDEX(panduan!$C$3:$H$16, MATCH(TRIM(A43), panduan!$B$3:$B$16, 0), MATCH(TRIM($B$4), panduan!$C$2:$H$2, 0)),"") -> 1 | C43: =IFERROR(INDEX(panduan!$C$3:$H$16, MATCH(TRIM(A43), panduan!$B$3:$B$16, 0), MATCH(TRIM($B$5), panduan!$C$2:$H$2, 0)),"") -> 2 | D43: 3 | E43: =D43-C43 -> 1 | F43: =IF(E43<0, MIN(-E43, 4), "") | G43: =IFERROR( INDEX(panduan!$C$181:$G$185, MATCH($F$65,panduan!$B$181:$B$185,0), MATCH($F43,panduan!$C$180:$G$180,0) ), "") | H43: =IF(G43="", "", SUBSTITUTE( SUBSTITUTE( SUBSTITUTE( SUBSTITUTE(G43, "1", "Personal Development"), "2", "Education-Based Development"), "3", "Relation-Based Development"), "4", "Experience-Based Development") ) | I43: =IF(E43<0,_xlfn.RANK.EQ(E43,$E$13:$E$54,1)+COUNTIF($E$13:E45,E43)-1,"") | J43: =IF(ISNUMBER(FIND("1",$G43)), $A43&"|"&$B$5&"|1", "") | K43: =IF(ISNUMBER(FIND("2",$G43)), $A43&"|"&$B$5&"|2", "") | L43: =IF(ISNUMBER(FIND("3",$G43)), $A43&"|"&$B$5&"|3", "") | M43: =IF(ISNUMBER(FIND("4",$G43)), $A43&"|"&$B$5&"|4", "") | N43: {=_xlfn.LET( _xlpm.gap, $F43, _xlpm.key, $J43, _xlpm.data, _xlfn._xlws.FILTER('sheet template'!$F$2:$M$1009, ('sheet template'!$A$2:$A$1009=_xlpm.key) * ('sheet template'!$F$2:$F$1009<=_xlpm.gap), ""), IF(OR(_xlpm.key="", _xlpm.gap<=0, ROWS(_xlpm.data)=0), "", _xlpm.data) )} | V43: {=_xlfn.LET( _xlpm.gap, $F43, _xlpm.key, $K43, _xlpm.data, _xlfn._xlws.FILTER('sheet template'!$F$2:$M$1009, ('sheet template'!$A$2:$A$1009=_xlpm.key) * ('sheet template'!$F$2:$F$1009<=_xlpm.gap), ""), IF(OR(_xlpm.key="", _xlpm.gap<=0, ROWS(_xlpm.data)=0), "", _xlpm.data) )} | AD43: {=_xlfn.LET( _xlpm.gap, $F43, _xlpm.key, $L43, _xlpm.data, _xlfn._xlws.FILTER('sheet template'!$F$2:$M$1009, ('sheet template'!$A$2:$A$1009=_xlpm.key) * ('sheet template'!$F$2:$F$1009<=_xlpm.gap), ""), IF(OR(_xlpm.key="", _xlpm.gap<=0, ROWS(_xlpm.data)=0), "", _xlpm.data) )} | AL43: {=_xlfn.LET( _xlpm.gap, $F43, _xlpm.key, $L43, _xlpm.data, _xlfn._xlws.FILTER('sheet template'!$F$2:$M$1009, ('sheet template'!$A$2:$A$1009=_xlpm.key) * ('sheet template'!$F$2:$F$1009<=_xlpm.gap), ""), IF(OR(_xlpm.key="", _xlpm.gap<=0, ROWS(_xlpm.data)=0), "", _xlpm.data) )}
A46: Team Work | B46: =IFERROR(INDEX(panduan!$C$3:$H$16, MATCH(TRIM(A46), panduan!$B$3:$B$16, 0), MATCH(TRIM($B$4), panduan!$C$2:$H$2, 0)),"") -> 2 | C46: =IFERROR(INDEX(panduan!$C$3:$H$16, MATCH(TRIM(A46), panduan!$B$3:$B$16, 0), MATCH(TRIM($B$5), panduan!$C$2:$H$2, 0)),"") -> 3 | D46: 4 | E46: =D46-C46 -> 1 | F46: =IF(E46<0, MIN(-E46, 4), "") | G46: =IFERROR( INDEX(panduan!$C$181:$G$185, MATCH($F$65,panduan!$B$181:$B$185,0), MATCH($F46,panduan!$C$180:$G$180,0) ), "") | H46: =IF(G46="", "", SUBSTITUTE( SUBSTITUTE( SUBSTITUTE( SUBSTITUTE(G46, "1", "Personal Development"), "2", "Education-Based Development"), "3", "Relation-Based Development"), "4", "Experience-Based Development") ) | I46: =IF(E46<0,_xlfn.RANK.EQ(E46,$E$13:$E$54,1)+COUNTIF($E$13:E48,E46)-1,"") | J46: =IF(ISNUMBER(FIND("1",$G46)), $A46&"|"&$B$5&"|1", "") | K46: =IF(ISNUMBER(FIND("2",$G46)), $A46&"|"&$B$5&"|2", "") | L46: =IF(ISNUMBER(FIND("3",$G46)), $A46&"|"&$B$5&"|3", "") | M46: =IF(ISNUMBER(FIND("4",$G46)), $A46&"|"&$B$5&"|4", "") | N46: {=_xlfn.LET( _xlpm.gap, $F46, _xlpm.key, $J46, _xlpm.data, _xlfn._xlws.FILTER('sheet template'!$F$2:$M$1009, ('sheet template'!$A$2:$A$1009=_xlpm.key) * ('sheet template'!$F$2:$F$1009<=_xlpm.gap), ""), IF(OR(_xlpm.key="", _xlpm.gap<=0, ROWS(_xlpm.data)=0), "", _xlpm.data) )} | V46: {=_xlfn.LET( _xlpm.gap, $F46, _xlpm.key, $K46, _xlpm.data, _xlfn._xlws.FILTER('sheet template'!$F$2:$M$1009, ('sheet template'!$A$2:$A$1009=_xlpm.key) * ('sheet template'!$F$2:$F$1009<=_xlpm.gap), ""), IF(OR(_xlpm.key="", _xlpm.gap<=0, ROWS(_xlpm.data)=0), "", _xlpm.data) )} | AD46: {=_xlfn.LET( _xlpm.gap, $F46, _xlpm.key, $L46, _xlpm.data, _xlfn._xlws.FILTER('sheet template'!$F$2:$M$1009, ('sheet template'!$A$2:$A$1009=_xlpm.key) * ('sheet template'!$F$2:$F$1009<=_xlpm.gap), ""), IF(OR(_xlpm.key="", _xlpm.gap<=0, ROWS(_xlpm.data)=0), "", _xlpm.data) )} | AL46: {=_xlfn.LET( _xlpm.gap, $F46, _xlpm.key, $L46, _xlpm.data, _xlfn._xlws.FILTER('sheet template'!$F$2:$M$1009, ('sheet template'!$A$2:$A$1009=_xlpm.key) * ('sheet template'!$F$2:$F$1009<=_xlpm.gap), ""), IF(OR(_xlpm.key="", _xlpm.gap<=0, ROWS(_xlpm.data)=0), "", _xlpm.data) )}
A49: Communication & Deal with Others | B49: =IFERROR(INDEX(panduan!$C$3:$H$16, MATCH(TRIM(A49), panduan!$B$3:$B$16, 0), MATCH(TRIM($B$4), panduan!$C$2:$H$2, 0)),"") -> 1 | C49: =IFERROR(INDEX(panduan!$C$3:$H$16, MATCH(TRIM(A49), panduan!$B$3:$B$16, 0), MATCH(TRIM($B$5), panduan!$C$2:$H$2, 0)),"") -> 2 | D49: 4 | E49: =D49-C49 -> 2 | F49: =IF(E49<0, MIN(-E49, 4), "") | G49: =IFERROR( INDEX(panduan!$C$181:$G$185, MATCH($F$65,panduan!$B$181:$B$185,0), MATCH($F49,panduan!$C$180:$G$180,0) ), "") | H49: =IF(G49="", "", SUBSTITUTE( SUBSTITUTE( SUBSTITUTE( SUBSTITUTE(G49, "1", "Personal Development"), "2", "Education-Based Development"), "3", "Relation-Based Development"), "4", "Experience-Based Development") ) | I49: =IF(E49<0,_xlfn.RANK.EQ(E49,$E$13:$E$54,1)+COUNTIF($E$13:E51,E49)-1,"") | J49: =IF(ISNUMBER(FIND("1",$G49)), $A49&"|"&$B$5&"|1", "") | K49: =IF(ISNUMBER(FIND("2",$G49)), $A49&"|"&$B$5&"|2", "") | L49: =IF(ISNUMBER(FIND("3",$G49)), $A49&"|"&$B$5&"|3", "") | M49: =IF(ISNUMBER(FIND("4",$G49)), $A49&"|"&$B$5&"|4", "") | N49: {=_xlfn.LET( _xlpm.gap, $F49, _xlpm.key, $J49, _xlpm.data, _xlfn._xlws.FILTER('sheet template'!$F$2:$M$1009, ('sheet template'!$A$2:$A$1009=_xlpm.key) * ('sheet template'!$F$2:$F$1009<=_xlpm.gap), ""), IF(OR(_xlpm.key="", _xlpm.gap<=0, ROWS(_xlpm.data)=0), "", _xlpm.data) )} | V49: {=_xlfn.LET( _xlpm.gap, $F49, _xlpm.key, $K49, _xlpm.data, _xlfn._xlws.FILTER('sheet template'!$F$2:$M$1009, ('sheet template'!$A$2:$A$1009=_xlpm.key) * ('sheet template'!$F$2:$F$1009<=_xlpm.gap), ""), IF(OR(_xlpm.key="", _xlpm.gap<=0, ROWS(_xlpm.data)=0), "", _xlpm.data) )} | AD49: {=_xlfn.LET( _xlpm.gap, $F49, _xlpm.key, $L49, _xlpm.data, _xlfn._xlws.FILTER('sheet template'!$F$2:$M$1009, ('sheet template'!$A$2:$A$1009=_xlpm.key) * ('sheet template'!$F$2:$F$1009<=_xlpm.gap), ""), IF(OR(_xlpm.key="", _xlpm.gap<=0, ROWS(_xlpm.data)=0), "", _xlpm.data) )} | AL49: {=_xlfn.LET( _xlpm.gap, $F49, _xlpm.key, $L49, _xlpm.data, _xlfn._xlws.FILTER('sheet template'!$F$2:$M$1009, ('sheet template'!$A$2:$A$1009=_xlpm.key) * ('sheet template'!$F$2:$F$1009<=_xlpm.gap), ""), IF(OR(_xlpm.key="", _xlpm.gap<=0, ROWS(_xlpm.data)=0), "", _xlpm.data) )}
A52: Customer Focus | B52: =IFERROR(INDEX(panduan!$C$3:$H$16, MATCH(TRIM(A52), panduan!$B$3:$B$16, 0), MATCH(TRIM($B$4), panduan!$C$2:$H$2, 0)),"") -> 1 | C52: =IFERROR(INDEX(panduan!$C$3:$H$16, MATCH(TRIM(A52), panduan!$B$3:$B$16, 0), MATCH(TRIM($B$5), panduan!$C$2:$H$2, 0)),"") -> 2 | D52: 4 | E52: =D52-C52 -> 2 | F52: =IF(E52<0, MIN(-E52, 4), "") | G52: =IFERROR( INDEX(panduan!$C$181:$G$185, MATCH($F$65,panduan!$B$181:$B$185,0), MATCH($F52,panduan!$C$180:$G$180,0) ), "") | H52: =IF(G52="", "", SUBSTITUTE( SUBSTITUTE( SUBSTITUTE( SUBSTITUTE(G52, "1", "Personal Development"), "2", "Education-Based Development"), "3", "Relation-Based Development"), "4", "Experience-Based Development") ) | I52: =IF(E52<0,_xlfn.RANK.EQ(E52,$E$13:$E$54,1)+COUNTIF($E$13:E54,E52)-1,"") | J52: =IF(ISNUMBER(FIND("1",$G52)), $A52&"|"&$B$5&"|1", "") | K52: =IF(ISNUMBER(FIND("2",$G52)), $A52&"|"&$B$5&"|2", "") | L52: =IF(ISNUMBER(FIND("3",$G52)), $A52&"|"&$B$5&"|3", "") | M52: =IF(ISNUMBER(FIND("4",$G52)), $A52&"|"&$B$5&"|4", "") | N52: {=_xlfn.LET( _xlpm.gap, $F52, _xlpm.key, $J52, _xlpm.data, _xlfn._xlws.FILTER('sheet template'!$F$2:$M$1009, ('sheet template'!$A$2:$A$1009=_xlpm.key) * ('sheet template'!$F$2:$F$1009<=_xlpm.gap), ""), IF(OR(_xlpm.key="", _xlpm.gap<=0, ROWS(_xlpm.data)=0), "", _xlpm.data) )} | V52: {=_xlfn.LET( _xlpm.gap, $F52, _xlpm.key, $K52, _xlpm.data, _xlfn._xlws.FILTER('sheet template'!$F$2:$M$1009, ('sheet template'!$A$2:$A$1009=_xlpm.key) * ('sheet template'!$F$2:$F$1009<=_xlpm.gap), ""), IF(OR(_xlpm.key="", _xlpm.gap<=0, ROWS(_xlpm.data)=0), "", _xlpm.data) )} | AD52: {=_xlfn.LET( _xlpm.gap, $F52, _xlpm.key, $L52, _xlpm.data, _xlfn._xlws.FILTER('sheet template'!$F$2:$M$1009, ('sheet template'!$A$2:$A$1009=_xlpm.key) * ('sheet template'!$F$2:$F$1009<=_xlpm.gap), ""), IF(OR(_xlpm.key="", _xlpm.gap<=0, ROWS(_xlpm.data)=0), "", _xlpm.data) )} | AL52: {=_xlfn.LET( _xlpm.gap, $F52, _xlpm.key, $L52, _xlpm.data, _xlfn._xlws.FILTER('sheet template'!$F$2:$M$1009, ('sheet template'!$A$2:$A$1009=_xlpm.key) * ('sheet template'!$F$2:$F$1009<=_xlpm.gap), ""), IF(OR(_xlpm.key="", _xlpm.gap<=0, ROWS(_xlpm.data)=0), "", _xlpm.data) )}
N54: {=_xlfn.LET( _xlpm.key, J52, _xlpm.data, _xlfn._xlws.FILTER('sheet template'!$F$2:$M$1009, 'sheet template'!$A$2:$A$1009=_xlpm.key, ""), _xlpm.jmlBaris, ROWS(_xlpm.data), IF(OR(_xlpm.key="", _xlpm.jmlBaris=0), "", INDEX(_xlpm.data, RANDBETWEEN(1, _xlpm.jmlBaris), 0)) )} | V54: {=IF(K52="", "", INDEX(_xlfn._xlws.FILTER('sheet template'!$F$2:$M$1009, 'sheet template'!$A$2:$A$1009=K52), RANDBETWEEN(1,3), 0))} | AD54: {=IF(L52="", "", INDEX(_xlfn._xlws.FILTER('sheet template'!$F$2:$M$1009, 'sheet template'!$A$2:$A$1009=L52), RANDBETWEEN(1,3), 0))} | AL54: {=IF(M52="", "", INDEX(_xlfn._xlws.FILTER('sheet template'!$F$2:$M$1009, 'sheet template'!$A$2:$A$1009=M52), RANDBETWEEN(1,3), 0))}
A59: Learning Agility | B59: Score Self | C59: Score Superior | D59: Gap Score Sup-Self | E59: Gap | F59: Gap Matriks
A60: ='Profile Summary'!A108 -> Mental Agility | B60: ='Profile Summary'!B108 -> 2.8 | C60: ='Profile Summary'!C108 -> 2.5 | D60: ='Profile Summary'!D108 -> 0.3 | E60: ='Profile Summary'!E108 -> Aligned
A61: ='Profile Summary'!A109 -> People Agility | B61: ='Profile Summary'!B109 -> 2.8 | C61: ='Profile Summary'!C109 -> 3.1333333 | D61: ='Profile Summary'!D109 -> -0.33333333 | E61: ='Profile Summary'!E109 -> Aligned
A62: ='Profile Summary'!A110 -> Change Agility | B62: ='Profile Summary'!B110 -> 3 | C62: ='Profile Summary'!C110 -> 2.5 | D62: ='Profile Summary'!D110 -> 0.5 | E62: ='Profile Summary'!E110 -> Minor Positive Gap
A63: ='Profile Summary'!A111 -> Result Agility | B63: ='Profile Summary'!B111 -> 3 | C63: ='Profile Summary'!C111 -> 3.4166667 | D63: ='Profile Summary'!D111 -> -0.41666667 | E63: ='Profile Summary'!E111 -> Aligned
A64: ='Profile Summary'!A112 -> Self Awareness | B64: ='Profile Summary'!B112 -> 4.1 | C64: ='Profile Summary'!C112 -> 3.6 | D64: ='Profile Summary'!D112 -> 0.5 | E64: ='Profile Summary'!E112 -> Minor Positive Gap
B65: ='Profile Summary'!B113 -> 3.14 | C65: ='Profile Summary'!C113 -> 3.03 | D65: ='Profile Summary'!D113 -> 0.11 | E65: ='Profile Summary'!E113 -> Aligned | F65: {=_xlfn.IFS( D65>=1, 0, D65>=0.5, 1, D65>=-0.49, 2, D65>=-0.99, 3, D65<=-1, 4 )} -> 2
A69: Level Next Path | B69: =Identitas!D12 -> Unit Head/Specialist
I70: =IF(E13<0,RANK.EQ(E13,$E$13:$E$54,1)+COUNTIF($E$13:E13,E13)-1,"")
A71: Kompetensi | B71: Proficiency Level Saat ini | C71: Proficiency Level Tujuan | D71: Hasil Potential | E71: Gap Kompetensi | F71: Absolut gap | G71: Metode Pengembangan dari matriks | H71: Metode dalam teks | I71: Prioritas | J71: Key Metode 1 | K71: Key Metode 2 | L71: Key Metode 3 | M71: Key Metode 4 | N71: Aktivitas Metode 1 | V71: Aktivitas Metode 2 | AD71: Aktivitas Metode 3 | AL71: Aktivitas Metode 4
A72: Achievement Drive | B72: =IFERROR(INDEX(panduan!$C$3:$H$16, MATCH(TRIM(A72), panduan!$B$3:$B$16, 0), MATCH(TRIM($B$4), panduan!$C$2:$H$2, 0)),"") -> 2 | C72: =IFERROR(INDEX(panduan!$C$3:$H$16, MATCH(TRIM(A72), panduan!$B$3:$B$16, 0), MATCH(TRIM($B$69), panduan!$C$2:$H$2, 0)),"") -> 3 | D72: 1 | E72: =D72-C72 -> -2 | F72: =IF(E72<0, MIN(-E72, 4), "") -> 2 | G72: =IFERROR( INDEX(panduan!$C$181:$G$185, MATCH($F$65,panduan!$B$181:$B$185,0), MATCH($F72,panduan!$C$180:$G$180,0) ), "") -> 1,2,3,4 | H72: =IF(G72="", "", SUBSTITUTE( SUBSTITUTE( SUBSTITUTE( SUBSTITUTE(G72, "1", "Personal Development"), "2", "Education-Based Development"), "3", "Relation-Based Development"), "4", "Experience-Based Development") ) -> Personal Development,Education-Based Development,Relation-Based Development,Experience-Based Development | I72: =IF(E72<0,_xlfn.RANK.EQ(E72,$E$72:$E$113,1)+COUNTIF($E$72:E74,E72)-1,"") -> 2 | J72: =IF(ISNUMBER(FIND("1",$G72)), $A72&"|"&$B$5&"|1", "") -> Achievement Drive|Analyst|1 | K72: =IF(ISNUMBER(FIND("2",$G72)), $A72&"|"&$B$5&"|2", "") -> Achievement Drive|Analyst|2 | L72: =IF(ISNUMBER(FIND("3",$G72)), $A72&"|"&$B$5&"|3", "") -> Achievement Drive|Analyst|3 | M72: =IF(ISNUMBER(FIND("4",$G72)), $A72&"|"&$B$5&"|4", "") -> Achievement Drive|Analyst|4 | N72: {=_xlfn.LET( _xlpm.gap, $F72, _xlpm.key, $J72, _xlpm.data, _xlfn._xlws.FILTER('sheet template'!$F$2:$M$1009, ('sheet template'!$A$2:$A$1009=_xlpm.key) * ('sheet template'!$F$2:$F$1009<=_xlpm.gap), ""), IF(OR(_xlpm.key="", _xlpm.gap<=0, ROWS(_xlpm.data)=0), "", _xlpm.data) )} -> 1 | O72: Log "Target yang Menghadapi Hambatan Berulang" | P72: Mengukur ketekunan pada target yang sulit dan berlangsung lama. | Q72: Pilih 1 target yang sedang dikejar dan diperkirakan menghadapi hambatan berulang. Setiap kali mengalami hambatan atau kegagalan pada target itu, catat: apa hambatannya, bagaimana perasaan saat itu, dan apa yang dilakukan — melanjutkan, mengubah cara, atau berhenti sebentar untuk kembali lagi. | R72: Log minimal 15 hambatan pada target yang sama; rentang waktu minimal 3 bulan. | S72: Bulan 1–12 | T72: Bulanan | U72: Minimal 15 hambatan tercatat pada target yang SAMA, berlangsung minimal 3 bulan. Target tersebut tetap dikejar sampai akhir periode logging, tidak ditinggalkan di tengah jalan. Milestone Bulan 6: 8 hambatan tercatat, target masih dikejar. | V72: {=_xlfn.LET( _xlpm.gap, $F72, _xlpm.key, $K72, _xlpm.data, _xlfn._xlws.FILTER('sheet template'!$F$2:$M$1009, ('sheet template'!$A$2:$A$1009=_xlpm.key) * ('sheet template'!$F$2:$F$1009<=_xlpm.gap), ""), IF(OR(_xlpm.key="", _xlpm.gap<=0, ROWS(_xlpm.data)=0), "", _xlpm.data) )} -> 1 | W72: Workshop "Bertahan Melewati Hambatan Berulang" | X72: Menguasai teknik menjaga komitmen ketika hambatan datang berulang kali. | Y72: Ikuti workshop tentang: mengenali tanda mulai kehilangan arah, memisahkan kegagalan taktik dari kegagalan tujuan, dan menjaga energi tanpa dukungan eksternal terus-menerus. | Z72: Sertifikat; 1 rencana bertahan untuk target yang sedang menghadapi hambatan berulang. | AA72: Bulan 1–12 | AB72: Bulanan | AC72: Rencana disetujui atasan dan dipakai pada target yang dipilih peserta dalam aktivitas ini minimal 2 bulan. | AD72: {=_xlfn.LET( _xlpm.gap, $F72, _xlpm.key, $L72, _xlpm.data, _xlfn._xlws.FILTER('sheet template'!$F$2:$M$1009, ('sheet template'!$A$2:$A$1009=_xlpm.key) * ('sheet template'!$F$2:$F$1009<=_xlpm.gap), ""), IF(OR(_xlpm.key="", _xlpm.gap<=0, ROWS(_xlpm.data)=0), "", _xlpm.data) )} -> 1 | AE72: Diskusi dengan Rekan yang Dikenal Tidak Mudah Menyerah | AF72: Mempelajari cara rekan menjaga komitmen di tengah hambatan berulang. | AG72: Diskusi dengan 1 rekan yang dikenal tidak mudah menyerah pada target sulit. Tanyakan: bagaimana ia menjaga energinya, apa yang ia lakukan saat hambatan datang berulang, dan kapan ia tahu harus mengubah cara tanpa mengubah tujuan. | AH72: Catatan diskusi; minimal 3 praktik yang akan diadopsi. | AI72: Bulan 1–12 | AJ72: Bulanan | AK72: Minimal 3 praktik diidentifikasi dan minimal 2 diterapkan pada target yang dipilih peserta dalam aktivitas ini. | AL72: {=_xlfn.LET( _xlpm.gap, $F72, _xlpm.key, $L72, _xlpm.data, _xlfn._xlws.FILTER('sheet template'!$F$2:$M$1009, ('sheet template'!$A$2:$A$1009=_xlpm.key) * ('sheet template'!$F$2:$F$1009<=_xlpm.gap), ""), IF(OR(_xlpm.key="", _xlpm.gap<=0, ROWS(_xlpm.data)=0), "", _xlpm.data) )} -> 1 | AM72: Diskusi dengan Rekan yang Dikenal Tidak Mudah Menyerah | AN72: Mempelajari cara rekan menjaga komitmen di tengah hambatan berulang. | AO72: Diskusi dengan 1 rekan yang dikenal tidak mudah menyerah pada target sulit. Tanyakan: bagaimana ia menjaga energinya, apa yang ia lakukan saat hambatan datang berulang, dan kapan ia tahu harus mengubah cara tanpa mengubah tujuan. | AP72: Catatan diskusi; minimal 3 praktik yang akan diadopsi. | AQ72: Bulan 1–12 | AR72: Bulanan | AS72: Minimal 3 praktik diidentifikasi dan minimal 2 diterapkan pada target yang dipilih peserta dalam aktivitas ini.
